Workbook

Sheet 00_Kontenrahmen
A1: 📋 DATEV KONTENRAHMEN — SKR03 / SKR04 Mapping → BWA-Gruppen & GuV/Bilanz
A2: SKR03 | B2: SKR04 | C2: Kontobezeichnung | D2: BWA-Gruppe | E2: GuV/Bilanz Position | F2: Kontenklasse | G2: Vorzeichen | H2: Aktiv
A3: ▶ ERLÖSE — Umsatzerlöse
A4: 8000 | B4: 4000 | C4: Umsatzerlöse 19% USt | D4: Umsatz | E4: GuV: Umsatzerlöse | F4: Erlöse | G4: + | H4: ✓
A5: 8100 | B5: 4100 | C5: Umsatzerlöse 7% USt | D5: Umsatz | E5: GuV: Umsatzerlöse | F5: Erlöse | G5: + | H5: ✓
A6: 8200 | B6: 4200 | C6: Steuerfreie Umsätze §4 UStG | D6: Umsatz | E6: GuV: Umsatzerlöse | F6: Erlöse | G6: + | H6: ✓
A7: 8300 | B7: 4300 | C7: Umsatzerlöse Ausland (EU) | D7: Umsatz | E7: GuV: Umsatzerlöse | F7: Erlöse | G7: + | H7: ✓
A8: 8400 | B8: 4400 | C8: Umsatzerlöse Drittland | D8: Umsatz | E8: GuV: Umsatzerlöse | F8: Erlöse | G8: + | H8: ✓
A9: 8500 | B9: 4500 | C9: Provisionserlöse | D9: Umsatz | E9: GuV: Umsatzerlöse | F9: Erlöse | G9: + | H9: ✓
A10: 8600 | B10: 4600 | C10: Mieterlöse | D10: Umsatz | E10: GuV: Umsatzerlöse | F10: Erlöse | G10: + | H10: ✓
A11: 8700 | B11: 4700 | C11: Erlöse aus Anlagenverkäufen | D11: Sonstige Erlöse | E11: GuV: Sonstige betriebliche Erlöse | F11: Erlöse | G11: + | H11: ✓
A12: 8900 | B12: 4900 | C12: Andere sonstige Erlöse | D12: Sonstige Erlöse | E12: GuV: Sonstige betriebliche Erlöse | F12: Erlöse | G12: + | H12: ✓
A13: 8910 | B13: 4910 | C13: Bestandsveränderungen | D13: Bestandsveränd. | E13: GuV: Bestandsveränderungen | F13: Erlöse | G13: + | H13: ✓
A14: ▶ AUFWAND — Materialaufwand
A15: 3000 | B15: 5000 | C15: Wareneinkauf 19% VSt | D15: Wareneinsatz | E15: GuV: Materialaufwand | F15: Aufwand | G15: - | H15: ✓
A16: 3100 | B16: 5100 | C16: Wareneinkauf 7% VSt | D16: Wareneinsatz | E16: GuV: Materialaufwand | F16: Aufwand | G16: - | H16: ✓
A17: 3200 | B17: 5200 | C17: Wareneinkauf steuerfreie Einnahmen | D17: Wareneinsatz | E17: GuV: Materialaufwand | F17: Aufwand | G17: - | H17: ✓
A18: 3400 | B18: 5400 | C18: Bezogene Leistungen | D18: Fremdleistungen | E18: GuV: Materialaufwand | F18: Aufwand | G18: - | H18: ✓
A19: 3500 | B19: 5500 | C19: Hilfsstoffe & Betriebsmittel | D19: Wareneinsatz | E19: GuV: Materialaufwand | F19: Aufwand | G19: - | H19: ✓
A20: 3600 | B20: 5600 | C20: Roh- und Betriebsstoffe | D20: Wareneinsatz | E20: GuV: Materialaufwand | F20: Aufwand | G20: - | H20: ✓
A21: 3800 | B21: 5800 | C21: Wareneingang ohne Vorsteuer | D21: Wareneinsatz | E21: GuV: Materialaufwand | F21: Aufwand | G21: - | H21: ✓
A22: 4100 | B22: 6000 | C22: Löhne und Gehälter | D22: Personal | E22: GuV: Personalaufwand | F22: Aufwand | G22: - | H22: ✓
A23: 4110 | B23: 6010 | C23: Gehälter Angestellte | D23: Personal | E23: GuV: Personalaufwand | F23: Aufwand | G23: - | H23: ✓
A24: 4120 | B24: 6020 | C24: Löhne Arbeiter | D24: Personal | E24: GuV: Personalaufwand | F24: Aufwand | G24: - | H24: ✓
A25: 4130 | B25: 6030 | C25: Gehälter Geschäftsführung | D25: Personal | E25: GuV: Personalaufwand | F25: Aufwand | G25: - | H25: ✓
A26: 4140 | B26: 6040 | C26: Aushilfslöhne | D26: Personal | E26: GuV: Personalaufwand | F26: Aufwand | G26: - | H26: ✓
... A53: 4910 | B53: 6990 | C53: Sonstige Kosten allgemein | D53: Sonstige | E53: GuV: Sonstige betriebliche Aufwände | F53: Aufwand | G53: - | H53: ✓
A54: ▶ ERTRAG — Finanzergebnis
A55: 2100 | B55: 7100 | C55: Zinserträge | D55: Finanzergebnis | E55: GuV: Finanzergebnis | F55: Ertrag | G55: + | H55: ✓
A56: 2120 | B56: 7120 | C56: Erträge Beteiligungen | D56: Finanzergebnis | E56: GuV: Finanzergebnis | F56: Ertrag | G56: + | H56: ✓
A57: ▶ AUFWAND — Finanzergebnis
A58: 2200 | B58: 7200 | C58: Zinsaufwand kurzfristig | D58: Finanzergebnis | E58: GuV: Finanzergebnis | F58: Aufwand | G58: - | H58: ✓
A59: 2210 | B59: 7210 | C59: Zinsaufwand langfristig | D59: Finanzergebnis | E59: GuV: Finanzergebnis | F59: Aufwand | G59: - | H59: ✓
A60: 2300 | B60: 7300 | C60: Kursverluste / Kursgewinne | D60: Finanzergebnis | E60: GuV: Finanzergebnis | F60: Aufwand | G60: +- | H60: ✓
A61: 7600 | B61: 8600 | C61: Körperschaftsteuer | D61: Steuern | E61: GuV: Steuern | F61: Aufwand | G61: - | H61: ✓
A62: 7620 | B62: 8620 | C62: Gewerbesteuer | D62: Steuern | E62: GuV: Steuern | F62: Aufwand | G62: - | H62: ✓
A63: 7640 | B63: 8640 | C63: Umsatzsteuer-Zahllast | D63: Steuern | E63: GuV: Steuern | F63: Aufwand | G63: - | H63: ✓
A64: ▶ AKTIVA — Anlagevermögen
A65: 100 | B65: 100 | C65: Grundstücke & Gebäude | D65: Anlagevermögen | E65: Bilanz Aktiva: Anlagevermögen | F65: Aktiva | G65: + | H65: ✓
A66: 200 | B66: 200 | C66: Maschinen & Anlagen | D66: Anlagevermögen | E66: Bilanz Aktiva: Anlagevermögen | F66: Aktiva | G66: + | H66: ✓
A67: 400 | B67: 400 | C67: Fahrzeuge | D67: Anlagevermögen | E67: Bilanz Aktiva: Anlagevermögen | F67: Aktiva | G67: + | H67: ✓
A68: 650 | B68: 650 | C68: BGA (Betriebs- & Geschäftsausst.) | D68: Anlagevermögen | E68: Bilanz Aktiva: Anlagevermögen | F68: Aktiva | G68: + | H68: ✓
A69: 800 | B69: 800 | C69: Software / immaterielle WG | D69: Anlagevermögen | E69: Bilanz Aktiva: Anlagevermögen | F69: Aktiva | G69: + | H69: ✓
A70: 1000 | B70: 1000 | C70: Kasse | D70: Kassenbestand | E70: Bilanz Aktiva: Umlaufvermögen | F70: Aktiva | G70: + | H70: ✓
A71: 1200 | B71: 1800 | C71: Bank (Girokonten) | D71: Bankguthaben | E71: Bilanz Aktiva: Umlaufvermögen | F71: Aktiva | G71: + | H71: ✓
A72: 1210 | B72: 1810 | C72: Bank 2 (z.B. Sparkasse) | D72: Bankguthaben | E72: Bilanz Aktiva: Umlaufvermögen | F72: Aktiva | G72: + | H72: ✓
A73: 1400 | B73: 1200 | C73: Forderungen aus LuL | D73: Forderungen | E73: Bilanz Aktiva: Umlaufvermögen | F73: Aktiva | G73: + | H73: ✓
A74: 1410 | B74: 1210 | C74: Forderungen verbundene Unternehmen | D74: Forderungen | E74: Bilanz Aktiva: Umlaufvermögen | F74: Aktiva | G74: + | H74: ✓
A75: 1460 | B75: 1260 | C75: Geleistete Anzahlungen | D75: Forderungen | E75: Bilanz Aktiva: Umlaufvermögen | F75: Aktiva | G75: + | H75: ✓
A76: 1500 | B76: 1400 | C76: Vorräte / Fertigerzeugnisse | D76: Vorräte | E76: Bilanz Aktiva: Umlaufvermögen | F76: Aktiva | G76: + | H76: ✓
... A78: 1576 | B78: 1576 | C78: Vorsteuer 7% | D78: Vorsteuer | E78: Bilanz Aktiva: Umlaufvermögen | F78: Aktiva | G78: + | H78: ✓
A79: ▶ PASSIVA — Eigenkapital
A80: 2000 | B80: 3000 | C80: Stammkapital / gezeichnetes Kapital | D80: Eigenkapital | E80: Bilanz Passiva: Eigenkapital | F80: Passiva | G80: + | H80: ✓
A81: 2010 | B81: 3010 | C81: Rücklagen | D81: Eigenkapital | E81: Bilanz Passiva: Eigenkapital | F81: Passiva | G81: + | H81: ✓
A82: 2020 | B82: 3020 | C82: Gewinn-/Verlustvortrag | D82: Eigenkapital | E82: Bilanz Passiva: Eigenkapital | F82: Passiva | G82: + | H82: ✓
A83: 2030 | B83: 3030 | C83: Jahresüberschuss / -fehlbetrag | D83: Eigenkapital | E83: Bilanz Passiva: Eigenkapital | F83: Passiva | G83: + | H83: ✓
A84: 2100 | B84: 3500 | C84: Darlehen (langfristig) | D84: Fremdkapital | E84: Bilanz Passiva: Verbindlichkeiten | F84: Passiva | G84: + | H84: ✓
A85: 2110 | B85: 3510 | C85: Darlehen (kurzfristig < 1 Jahr) | D85: Fremdkapital | E85: Bilanz Passiva: Verbindlichkeiten | F85: Passiva | G85: + | H85: ✓
A86: 1600 | B86: 3200 | C86: Verbindlichkeiten aus LuL | D86: Fremdkapital | E86: Bilanz Passiva: Verbindlichkeiten | F86: Passiva | G86: + | H86: ✓
A87: 1700 | B87: 3730 | C87: USt-Zahllast (Umsatzsteuer) | D87: Steuervb. | E87: Bilanz Passiva: Verbindlichkeiten | F87: Passiva | G87: + | H87: ✓
A88: 1740 | B88: 3740 | C88: Lohnsteuer-Verbindlichkeit | D88: Steuervb. | E88: Bilanz Passiva: Verbindlichkeiten | F88: Passiva | G88: + | H88: ✓
A89: 1800 | B89: 3980 | C89: Sonstige Verbindlichkeiten | D89: Fremdkapital | E89: Bilanz Passiva: Verbindlichkeiten | F89: Passiva | G89: + | H89: ✓
A90: 1900 | B90: 3900 | C90: Rückstellungen allgemein | D90: Rückstellungen | E90: Bilanz Passiva: Rückstellungen | F90: Passiva | G90: + | H90: ✓
A91: 1910 | B91: 3910 | C91: Steuerrückstellungen | D91: Rückstellungen | E91: Bilanz Passiva: Rückstellungen | F91: Passiva | G91: + | H91: ✓
A92: 1920 | B92: 3920 | C92: Sozialversicherungsrückstellungen | D92: Rückstellungen | E92: Bilanz Passiva: Rückstellungen | F92: Passiva | G92: + | H92: ✓

Sheet 01_Saldenlisten_Import
A1: 📥 DATEV SALDENLISTEN-IMPORT — Rohdaten (DATEV-CSV Format SKR03/SKR04)
A2: ⚠️ CSV hier einfügen: Monat | Mandant | Konto | Bezeichnung | Betrag | Kostenstelle — Kontenzuordnung erfolgt automatisch per SVERWEIS aus Kontenrahmen-Sheet
A3: Monat (JJJJ-MM) | B3: Mandant | C3: Konto (SKR03) | D3: Konto (SKR04) | E3: Kontobezeichnung | F3: BWA-Gruppe (auto) | G3: Soll-Betrag (€) | H3: Haben-Betrag (€) | I3: Saldo (€) | J3: Netto-Betrag (€) | K3: GuV/Bilanz (auto) | L3: Kostenstelle | M3: Quelle | N3: Status
A4: 2025-01 | B4: Mustermann GmbH | C4: 8000 | D4: 4000 | E4: Umsatzerlöse 19% | F4: =IFERROR(VLOOKUP(C4,'00_Kontenrahmen'!$A$3:$H$200,4,FALSE()),"⚠ Nicht gefunden") -> Umsatz | H4: 92300 | I4: 92300 | J4: 92300 | K4: =IFERROR(VLOOKUP(C4,'00_Kontenrahmen'!$A$3:$H$200,5,FALSE()),"") -> GuV: Umsatzerlöse | L4: Vertrieb | M4: DATEV-CSV | N4: OK
A5: 2025-01 | B5: Mustermann GmbH | C5: 3000 | D5: 5000 | E5: Wareneinkauf 19% | F5: =IFERROR(VLOOKUP(C5,'00_Kontenrahmen'!$A$3:$H$200,4,FALSE()),"⚠ Nicht gefunden") -> Wareneinsatz | G5: 31000 | I5: -31000 | J5: 31000 | K5: =IFERROR(VLOOKUP(C5,'00_Kontenrahmen'!$A$3:$H$200,5,FALSE()),"") -> GuV: Materialaufwand | L5: Einkauf | M5: DATEV-CSV | N5: OK
A6: 2025-01 | B6: Mustermann GmbH | C6: 4100 | D6: 6000 | E6: Löhne und Gehälter | F6: =IFERROR(VLOOKUP(C6,'00_Kontenrahmen'!$A$3:$H$200,4,FALSE()),"⚠ Nicht gefunden") -> Personal | G6: 22000 | I6: -22000 | J6: 22000 | K6: =IFERROR(VLOOKUP(C6,'00_Kontenrahmen'!$A$3:$H$200,5,FALSE()),"") -> GuV: Personalaufwand | L6: Personal | M6: DATEV-CSV | N6: OK
A7: 2025-01 | B7: Mustermann GmbH | C7: 4830 | D7: 6830 | E7: EDV-Kosten & Software | F7: =IFERROR(VLOOKUP(C7,'00_Kontenrahmen'!$A$3:$H$200,4,FALSE()),"⚠ Nicht gefunden") -> Büro & IT | G7: 8500 | I7: -8500 | J7: 8500 | K7: =IFERROR(VLOOKUP(C7,'00_Kontenrahmen'!$A$3:$H$200,5,FALSE()),"") -> GuV: Sonstige betriebliche Aufwände | L7: IT | M7: DATEV-CSV | N7: OK
A8: 2025-01 | B8: Mustermann GmbH | C8: 4210 | D8: 6300 | E8: Miete & Pacht | F8: =IFERROR(VLOOKUP(C8,'00_Kontenrahmen'!$A$3:$H$200,4,FALSE()),"⚠ Nicht gefunden") -> Raumkosten | G8: 4200 | I8: -4200 | J8: 4200 | K8: =IFERROR(VLOOKUP(C8,'00_Kontenrahmen'!$A$3:$H$200,5,FALSE()),"") -> GuV: Sonstige betriebliche Aufwände | L8: Verwaltung | M8: DATEV-CSV | N8: OK
A9: 2025-01 | B9: Mustermann GmbH | C9: 4600 | D9: 6600 | E9: Werbekosten | F9: =IFERROR(VLOOKUP(C9,'00_Kontenrahmen'!$A$3:$H$200,4,FALSE()),"⚠ Nicht gefunden") -> Marketing | G9: 2800 | I9: -2800 | J9: 2800 | K9: =IFERROR(VLOOKUP(C9,'00_Kontenrahmen'!$A$3:$H$200,5,FALSE()),"") -> GuV: Sonstige betriebliche Aufwände | L9: Marketing | M9: DATEV-CSV | N9: OK
A10: 2025-01 | B10: Mustermann GmbH | C10: 4900 | D10: 6980 | E10: Sonstige Betriebskosten | F10: =IFERROR(VLOOKUP(C10,'00_Kontenrahmen'!$A$3:$H$200,4,FALSE()),"⚠ Nicht gefunden") -> Sonstige | G10: 1770 | I10: -1770 | J10: 1770 | K10: =IFERROR(VLOOKUP(C10,'00_Kontenrahmen'!$A$3:$H$200,5,FALSE()),"") -> GuV: Sonstige betriebliche Aufwände | L10: Verwaltung | M10: DATEV-CSV | N10: OK
A11: 2025-01 | B11: Mustermann GmbH | C11: 1200 | D11: 1800 | E11: Bank (Girokonto) | F11: =IFERROR(VLOOKUP(C11,'00_Kontenrahmen'!$A$3:$H$200,4,FALSE()),"⚠ Nicht gefunden") -> Bankguthaben | G11: 24000 | I11: 24000 | J11: 24000 | K11: =IFERROR(VLOOKUP(C11,'00_Kontenrahmen'!$A$3:$H$200,5,FALSE()),"") -> Bilanz Aktiva: Umlaufvermögen | L11: Finance | M11: DATEV-CSV | N11: OK
A12: 2025-01 | B12: Mustermann GmbH | C12: 1400 | D12: 1200 | E12: Forderungen aus LuL | F12: =IFERROR(VLOOKUP(C12,'00_Kontenrahmen'!$A$3:$H$200,4,FALSE()),"⚠ Nicht gefunden") -> Forderungen | G12: 45000 | I12: -45000 | J12: 45000 | K12: =IFERROR(VLOOKUP(C12,'00_Kontenrahmen'!$A$3:$H$200,5,FALSE()),"") -> Bilanz Aktiva: Umlaufvermögen | L12: Finance | M12: DATEV-CSV | N12: OK
A13: 2025-01 | B13: Mustermann GmbH | C13: 1600 | D13: 3200 | E13: Verbindlichkeiten LuL | F13: =IFERROR(VLOOKUP(C13,'00_Kontenrahmen'!$A$3:$H$200,4,FALSE()),"⚠ Nicht gefunden") -> Fremdkapital | H13: 18500 | I13: 18500 | J13: 18500 | K13: =IFERROR(VLOOKUP(C13,'00_Kontenrahmen'!$A$3:$H$200,5,FALSE()),"") -> Bilanz Passiva: Verbindlichkeiten | L13: Finance | M13: DATEV-CSV | N13: OK
A14: 2025-02 | B14: Mustermann GmbH | C14: 8000 | D14: 4000 | E14: Umsatzerlöse 19% | F14: =IFERROR(VLOOKUP(C14,'00_Kontenrahmen'!$A$3:$H$200,4,FALSE()),"⚠ Nicht gefunden") -> Umsatz | H14: 95550 | I14: 95550 | J14: 95550 | K14: =IFERROR(VLOOKUP(C14,'00_Kontenrahmen'!$A$3:$H$200,5,FALSE()),"") -> GuV: Umsatzerlöse | L14: Vertrieb | M14: DATEV-CSV | N14: OK
A15: 2025-02 | B15: Mustermann GmbH | C15: 3000 | D15: 5000 | E15: Wareneinkauf 19% | F15: =IFERROR(VLOOKUP(C15,'00_Kontenrahmen'!$A$3:$H$200,4,FALSE()),"⚠ Nicht gefunden") -> Wareneinsatz | G15: 32000 | I15: -32000 | J15: 32000 | K15: =IFERROR(VLOOKUP(C15,'00_Kontenrahmen'!$A$3:$H$200,5,FALSE()),"") -> GuV: Materialaufwand | L15: Einkauf | M15: DATEV-CSV | N15: OK
A16: 2025-02 | B16: Mustermann GmbH | C16: 4100 | D16: 6000 | E16: Löhne und Gehälter | F16: =IFERROR(VLOOKUP(C16,'00_Kontenrahmen'!$A$3:$H$200,4,FALSE()),"⚠ Nicht gefunden") -> Personal | G16: 22000 | I16: -22000 | J16: 22000 | K16: =IFERROR(VLOOKUP(C16,'00_Kontenrahmen'!$A$3:$H$200,5,FALSE()),"") -> GuV: Personalaufwand | L16: Personal | M16: DATEV-CSV | N16: OK
A17: 2025-02 | B17: Mustermann GmbH | C17: 4830 | D17: 6830 | E17: EDV-Kosten & Software | F17: =IFERROR(VLOOKUP(C17,'00_Kontenrahmen'!$A$3:$H$200,4,FALSE()),"⚠ Nicht gefunden") -> Büro & IT | G17: 9200 | I17: -9200 | J17: 9200 | K17: =IFERROR(VLOOKUP(C17,'00_Kontenrahmen'!$A$3:$H$200,5,FALSE()),"") -> GuV: Sonstige betriebliche Aufwände | L17: IT | M17: DATEV-CSV | N17: OK
A18: 2025-02 | B18: Mustermann GmbH | C18: 4210 | D18: 6300 | E18: Miete & Pacht | F18: =IFERROR(VLOOKUP(C18,'00_Kontenrahmen'!$A$3:$H$200,4,FALSE()),"⚠ Nicht gefunden") -> Raumkosten | G18: 4200 | I18: -4200 | J18: 4200 | K18: =IFERROR(VLOOKUP(C18,'00_Kontenrahmen'!$A$3:$H$200,5,FALSE()),"") -> GuV: Sonstige betriebliche Aufwände | L18: Verwaltung | M18: DATEV-CSV | N18: OK
A19: 2025-02 | B19: Mustermann GmbH | C19: 4900 | D19: 6980 | E19: Sonstige Betriebskosten | F19: =IFERROR(VLOOKUP(C19,'00_Kontenrahmen'!$A$3:$H$200,4,FALSE()),"⚠ Nicht gefunden") -> Sonstige | G19: 6065 | I19: -6065 | J19: 6065 | K19: =IFERROR(VLOOKUP(C19,'00_Kontenrahmen'!$A$3:$H$200,5,FALSE()),"") -> GuV: Sonstige betriebliche Aufwände | L19: Verwaltung | M19: DATEV-CSV | N19: OK
A20: 2025-09 | B20: Mustermann GmbH | C20: 8000 | D20: 4000 | E20: Umsatzerlöse 19% | F20: =IFERROR(VLOOKUP(C20,'00_Kontenrahmen'!$A$3:$H$200,4,FALSE()),"⚠ Nicht gefunden") -> Umsatz | H20: 107070 | I20: 107070 | J20: 107070 | K20: =IFERROR(VLOOKUP(C20,'00_Kontenrahmen'!$A$3:$H$200,5,FALSE()),"") -> GuV: Umsatzerlöse | L20: Vertrieb | M20: DATEV-CSV | N20: OK
A21: 2025-09 | B21: Mustermann GmbH | C21: 3000 | D21: 5000 | E21: Wareneinkauf 19% | F21: =IFERROR(VLOOKUP(C21,'00_Kontenrahmen'!$A$3:$H$200,4,FALSE()),"⚠ Nicht gefunden") -> Wareneinsatz | G21: 36000 | I21: -36000 | J21: 36000 | K21: =IFERROR(VLOOKUP(C21,'00_Kontenrahmen'!$A$3:$H$200,5,FALSE()),"") -> GuV: Materialaufwand | L21: Einkauf | M21: DATEV-CSV | N21: OK
A22: 2025-09 | B22: Mustermann GmbH | C22: 4100 | D22: 6000 | E22: Löhne und Gehälter | F22: =IFERROR(VLOOKUP(C22,'00_Kontenrahmen'!$A$3:$H$200,4,FALSE()),"⚠ Nicht gefunden") -> Personal | G22: 23500 | I22: -23500 | J22: 23500 | K22: =IFERROR(VLOOKUP(C22,'00_Kontenrahmen'!$A$3:$H$200,5,FALSE()),"") -> GuV: Personalaufwand | L22: Personal | M22: DATEV-CSV | N22: OK
A23: 2025-09 | B23: Mustermann GmbH | C23: 4830 | D23: 6830 | E23: EDV-Kosten & Software | F23: =IFERROR(VLOOKUP(C23,'00_Kontenrahmen'!$A$3:$H$200,4,FALSE()),"⚠ Nicht gefunden") -> Büro & IT | G23: 11200 | I23: -11200 | J23: 11200 | K23: =IFERROR(VLOOKUP(C23,'00_Kontenrahmen'!$A$3:$H$200,5,FALSE()),"") -> GuV: Sonstige betriebliche Aufwände | L23: IT | M23: DATEV-CSV | N23: OK
A24: 2025-09 | B24: Mustermann GmbH | C24: 4210 | D24: 6300 | E24: Miete & Pacht | F24: =IFERROR(VLOOKUP(C24,'00_Kontenrahmen'!$A$3:$H$200,4,FALSE()),"⚠ Nicht gefunden") -> Raumkosten | G24: 4500 | I24: -4500 | J24: 4500 | K24: =IFERROR(VLOOKUP(C24,'00_Kontenrahmen'!$A$3:$H$200,5,FALSE()),"") -> GuV: Sonstige betriebliche Aufwände | L24: Verwaltung | M24: DATEV-CSV | N24: OK
A25: 2025-09 | B25: Mustermann GmbH | C25: 4600 | D25: 6600 | E25: Werbekosten | F25: =IFERROR(VLOOKUP(C25,'00_Kontenrahmen'!$A$3:$H$200,4,FALSE()),"⚠ Nicht gefunden") -> Marketing | G25: 4100 | I25: -4100 | J25: 4100 | K25: =IFERROR(VLOOKUP(C25,'00_Kontenrahmen'!$A$3:$H$200,5,FALSE()),"") -> GuV: Sonstige betriebliche Aufwände | L25: Marketing | M25: DATEV-CSV | N25: OK
A26: 2025-09 | B26: Mustermann GmbH | C26: 4900 | D26: 6980 | E26: Sonstige Betriebskosten | F26: =IFERROR(VLOOKUP(C26,'00_Kontenrahmen'!$A$3:$H$200,4,FALSE()),"⚠ Nicht gefunden") -> Sonstige | G26: 5660 | I26: -5660 | J26: 5660 | K26: =IFERROR(VLOOKUP(C26,'00_Kontenrahmen'!$A$3:$H$200,5,FALSE()),"") -> GuV: Sonstige betriebliche Aufwände | L26: Verwaltung | M26: DATEV-CSV | N26: OK
A27: 2025-09 | B27: Beispiel Handel GmbH | C27: 8000 | D27: 4000 | E27: Umsatzerlöse 19% | F27: =IFERROR(VLOOKUP(C27,'00_Kontenrahmen'!$A$3:$H$200,4,FALSE()),"⚠ Nicht gefunden") -> Umsatz | H27: 102000 | I27: 102000 | J27: 102000 | K27: =IFERROR(VLOOKUP(C27,'00_Kontenrahmen'!$A$3:$H$200,5,FALSE()),"") -> GuV: Umsatzerlöse | L27: Vertrieb | M27: DATEV-CSV | N27: OK
A28: 2025-09 | B28: Beispiel Handel GmbH | C28: 3000 | D28: 5000 | E28: Wareneinkauf 19% | F28: =IFERROR(VLOOKUP(C28,'00_Kontenrahmen'!$A$3:$H$200,4,FALSE()),"⚠ Nicht gefunden") -> Wareneinsatz | G28: 61200 | I28: -61200 | J28: 61200 | K28: =IFERROR(VLOOKUP(C28,'00_Kontenrahmen'!$A$3:$H$200,5,FALSE()),"") -> GuV: Materialaufwand | L28: Einkauf | M28: DATEV-CSV | N28: OK
A29: 2025-09 | B29: Beispiel Handel GmbH | C29: 4100 | D29: 6000 | E29: Löhne und Gehälter | F29: =IFERROR(VLOOKUP(C29,'00_Kontenrahmen'!$A$3:$H$200,4,FALSE()),"⚠ Nicht gefunden") -> Personal | G29: 28000 | I29: -28000 | J29: 28000 | K29: =IFERROR(VLOOKUP(C29,'00_Kontenrahmen'!$A$3:$H$200,5,FALSE()),"") -> GuV: Personalaufwand | L29: Personal | M29: DATEV-CSV | N29: OK
A30: 2025-03 | B30: Mustermann GmbH | C30: 8000 | D30: 4000 | E30: Umsatzerlöse 19% | F30: Umsatz | H30: 100100 | I30: 100100 | J30: 100100 | K30: GuV: Umsatzerlöse | L30: Vertrieb | M30: DATEV-CSV | N30: OK
A31: 2025-03 | B31: Mustermann GmbH | C31: 3000 | D31: 5000 | E31: Wareneinkauf 19% | F31: Wareneinsatz | G31: 33500 | I31: -33500 | J31: 33500 | K31: GuV: Materialaufwand | L31: Einkauf | M31: DATEV-CSV | N31: OK
A32: 2025-03 | B32: Mustermann GmbH | C32: 4100 | D32: 6000 | E32: Löhne und Gehälter | F32: Personal | G32: 22500 | I32: -22500 | J32: 22500 | K32: GuV: Personalaufwand | L32: Personal | M32: DATEV-CSV | N32: OK
A33: 2025-03 | B33: Mustermann GmbH | C33: 4210 | D33: 6300 | E33: Miete & Pacht | F33: Raumkosten | G33: 4250 | I33: -4250 | J33: 4250 | K33: GuV: Sonstige betriebliche Aufwände | L33: Verwaltung | M33: DATEV-CSV | N33: OK
A34: 2025-03 | B34: Mustermann GmbH | C34: 4830 | D34: 6830 | E34: EDV-Kosten & Software | F34: Büro & IT | G34: 9500 | I34: -9500 | J34: 9500 | K34: GuV: Sonstige betriebliche Aufwände | L34: IT | M34: DATEV-CSV | N34: OK
A35: 2025-03 | B35: Mustermann GmbH | C35: 4600 | D35: 6600 | E35: Werbekosten | F35: Marketing | G35: 3100 | I35: -3100 | J35: 3100 | K35: GuV: Sonstige betriebliche Aufwände | L35: Marketing | M35: DATEV-CSV | N35: OK
A36: 2025-03 | B36: Mustermann GmbH | C36: 4900 | D36: 6980 | E36: Sonstige Betriebskosten | F36: Sonstige | G36: 6080 | I36: -6080 | J36: 6080 | K36: GuV: Sonstige betriebliche Aufwände | L36: Verwaltung | M36: DATEV-CSV | N36: OK
A37: 2025-04 | B37: Mustermann GmbH | C37: 8000 | D37: 4000 | E37: Umsatzerlöse 19% | F37: Umsatz | H37: 93780 | I37: 93780 | J37: 93780 | K37: GuV: Umsatzerlöse | L37: Vertrieb | M37: DATEV-CSV | N37: OK
A38: 2025-04 | B38: Mustermann GmbH | C38: 3000 | D38: 5000 | E38: Wareneinkauf 19% | F38: Wareneinsatz | G38: 32000 | I38: -32000 | J38: 32000 | K38: GuV: Materialaufwand | L38: Einkauf | M38: DATEV-CSV | N38: OK
A39: 2025-04 | B39: Mustermann GmbH | C39: 4100 | D39: 6000 | E39: Löhne und Gehälter | F39: Personal | G39: 22000 | I39: -22000 | J39: 22000 | K39: GuV: Personalaufwand | L39: Personal | M39: DATEV-CSV | N39: OK
A40: 2025-04 | B40: Mustermann GmbH | C40: 4210 | D40: 6300 | E40: Miete & Pacht | F40: Raumkosten | G40: 4300 | I40: -4300 | J40: 4300 | K40: GuV: Sonstige betriebliche Aufwände | L40: Verwaltung | M40: DATEV-CSV | N40: OK
A41: 2025-04 | B41: Mustermann GmbH | C41: 4830 | D41: 6830 | E41: EDV-Kosten & Software | F41: Büro & IT | G41: 9800 | I41: -9800 | J41: 9800 | K41: GuV: Sonstige betriebliche Aufwände | L41: IT | M41: DATEV-CSV | N41: OK
A42: 2025-04 | B42: Mustermann GmbH | C42: 4600 | D42: 6600 | E42: Werbekosten | F42: Marketing | G42: 3300 | I42: -3300 | J42: 3300 | K42: GuV: Sonstige betriebliche Aufwände | L42: Marketing | M42: DATEV-CSV | N42: OK
A43: 2025-04 | B43: Mustermann GmbH | C43: 4900 | D43: 6980 | E43: Sonstige Betriebskosten | F43: Sonstige | G43: 1032 | I43: -1032 | J43: 1032 | K43: GuV: Sonstige betriebliche Aufwände | L43: Verwaltung | M43: DATEV-CSV | N43: OK
A44: 2025-05 | B44: Mustermann GmbH | C44: 8000 | D44: 4000 | E44: Umsatzerlöse 19% | F44: Umsatz | H44: 100300 | I44: 100300 | J44: 100300 | K44: GuV: Umsatzerlöse | L44: Vertrieb | M44: DATEV-CSV | N44: OK
A45: 2025-05 | B45: Mustermann GmbH | C45: 3000 | D45: 5000 | E45: Wareneinkauf 19% | F45: Wareneinsatz | G45: 34000 | I45: -34000 | J45: 34000 | K45: GuV: Materialaufwand | L45: Einkauf | M45: DATEV-CSV | N45: OK
A46: 2025-05 | B46: Mustermann GmbH | C46: 4100 | D46: 6000 | E46: Löhne und Gehälter | F46: Personal | G46: 22500 | I46: -22500 | J46: 22500 | K46: GuV: Personalaufwand | L46: Personal | M46: DATEV-CSV | N46: OK
A47: 2025-05 | B47: Mustermann GmbH | C47: 4210 | D47: 6300 | E47: Miete & Pacht | F47: Raumkosten | G47: 4300 | I47: -4300 | J47: 4300 | K47: GuV: Sonstige betriebliche Aufwände | L47: Verwaltung | M47: DATEV-CSV | N47: OK
A48: 2025-05 | B48: Mustermann GmbH | C48: 4830 | D48: 6830 | E48: EDV-Kosten & Software | F48: Büro & IT | G48: 10000 | I48: -10000 | J48: 10000 | K48: GuV: Sonstige betriebliche Aufwände | L48: IT | M48: DATEV-CSV | N48: OK
A49: 2025-05 | B49: Mustermann GmbH | C49: 4600 | D49: 6600 | E49: Werbekosten | F49: Marketing | G49: 3500 | I49: -3500 | J49: 3500 | K49: GuV: Sonstige betriebliche Aufwände | L49: Marketing | M49: DATEV-CSV | N49: OK
A50: 2025-05 | B50: Mustermann GmbH | C50: 4900 | D50: 6980 | E50: Sonstige Betriebskosten | F50: Sonstige | G50: 4608 | I50: -4608 | J50: 4608 | K50: GuV: Sonstige betriebliche Aufwände | L50: Verwaltung | M50: DATEV-CSV | N50: OK
A51: 2025-06 | B51: Mustermann GmbH | C51: 8000 | D51: 4000 | E51: Umsatzerlöse 19% | F51: Umsatz | H51: 103600 | I51: 103600 | J51: 103600 | K51: GuV: Umsatzerlöse | L51: Vertrieb | M51: DATEV-CSV | N51: OK
A52: 2025-06 | B52: Mustermann GmbH | C52: 3000 | D52: 5000 | E52: Wareneinkauf 19% | F52: Wareneinsatz | G52: 35000 | I52: -35000 | J52: 35000 | K52: GuV: Materialaufwand | L52: Einkauf | M52: DATEV-CSV | N52: OK
A53: 2025-06 | B53: Mustermann GmbH | C53: 4100 | D53: 6000 | E53: Löhne und Gehälter | F53: Personal | G53: 23000 | I53: -23000 | J53: 23000 | K53: GuV: Personalaufwand | L53: Personal | M53: DATEV-CSV | N53: OK
A54: 2025-06 | B54: Mustermann GmbH | C54: 4210 | D54: 6300 | E54: Miete & Pacht | F54: Raumkosten | G54: 4400 | I54: -4400 | J54: 4400 | K54: GuV: Sonstige betriebliche Aufwände | L54: Verwaltung | M54: DATEV-CSV | N54: OK
A55: 2025-06 | B55: Mustermann GmbH | C55: 4830 | D55: 6830 | E55: EDV-Kosten & Software | F55: Büro & IT | G55: 10300 | I55: -10300 | J55: 10300 | K55: GuV: Sonstige betriebliche Aufwände | L55: IT | M55: DATEV-CSV | N55: OK
A56: 2025-06 | B56: Mustermann GmbH | C56: 4600 | D56: 6600 | E56: Werbekosten | F56: Marketing | G56: 3600 | I56: -3600 | J56: 3600 | K56: GuV: Sonstige betriebliche Aufwände | L56: Marketing | M56: DATEV-CSV | N56: OK
A57: 2025-06 | B57: Mustermann GmbH | C57: 4900 | D57: 6980 | E57: Sonstige Betriebskosten | F57: Sonstige | G57: 5565 | I57: -5565 | J57: 5565 | K57: GuV: Sonstige betriebliche Aufwände | L57: Verwaltung | M57: DATEV-CSV | N57: OK
A58: 2025-07 | B58: Mustermann GmbH | C58: 8000 | D58: 4000 | E58: Umsatzerlöse 19% | F58: Umsatz | H58: 101190 | I58: 101190 | J58: 101190 | K58: GuV: Umsatzerlöse | L58: Vertrieb | M58: DATEV-CSV | N58: OK
A59: 2025-07 | B59: Mustermann GmbH | C59: 3000 | D59: 5000 | E59: Wareneinkauf 19% | F59: Wareneinsatz | G59: 34500 | I59: -34500 | J59: 34500 | K59: GuV: Materialaufwand | L59: Einkauf | M59: DATEV-CSV | N59: OK
A60: 2025-07 | B60: Mustermann GmbH | C60: 4100 | D60: 6000 | E60: Löhne und Gehälter | F60: Personal | G60: 22500 | I60: -22500 | J60: 22500 | K60: GuV: Personalaufwand | L60: Personal | M60: DATEV-CSV | N60: OK
A61: 2025-07 | B61: Mustermann GmbH | C61: 4210 | D61: 6300 | E61: Miete & Pacht | F61: Raumkosten | G61: 4400 | I61: -4400 | J61: 4400 | K61: GuV: Sonstige betriebliche Aufwände | L61: Verwaltung | M61: DATEV-CSV | N61: OK
A62: 2025-07 | B62: Mustermann GmbH | C62: 4830 | D62: 6830 | E62: EDV-Kosten & Software | F62: Büro & IT | G62: 10600 | I62: -10600 | J62: 10600 | K62: GuV: Sonstige betriebliche Aufwände | L62: IT | M62: DATEV-CSV | N62: OK
A63: 2025-07 | B63: Mustermann GmbH | C63: 4600 | D63: 6600 | E63: Werbekosten | F63: Marketing | G63: 3800 | I63: -3800 | J63: 3800 | K63: GuV: Sonstige betriebliche Aufwände | L63: Marketing | M63: DATEV-CSV | N63: OK
A64: 2025-07 | B64: Mustermann GmbH | C64: 4900 | D64: 6980 | E64: Sonstige Betriebskosten | F64: Sonstige | G64: 4227 | I64: -4227 | J64: 4227 | K64: GuV: Sonstige betriebliche Aufwände | L64: Verwaltung | M64: DATEV-CSV | N64: OK
A65: 2025-08 | B65: Mustermann GmbH | C65: 8000 | D65: 4000 | E65: Umsatzerlöse 19% | F65: Umsatz | H65: 104570 | I65: 104570 | J65: 104570 | K65: GuV: Umsatzerlöse | L65: Vertrieb | M65: DATEV-CSV | N65: OK
A66: 2025-08 | B66: Mustermann GmbH | C66: 3000 | D66: 5000 | E66: Wareneinkauf 19% | F66: Wareneinsatz | G66: 35500 | I66: -35500 | J66: 35500 | K66: GuV: Materialaufwand | L66: Einkauf | M66: DATEV-CSV | N66: OK
A67: 2025-08 | B67: Mustermann GmbH | C67: 4100 | D67: 6000 | E67: Löhne und Gehälter | F67: Personal | G67: 23000 | I67: -23000 | J67: 23000 | K67: GuV: Personalaufwand | L67: Personal | M67: DATEV-CSV | N67: OK
A68: 2025-08 | B68: Mustermann GmbH | C68: 4210 | D68: 6300 | E68: Miete & Pacht | F68: Raumkosten | G68: 4500 | I68: -4500 | J68: 4500 | K68: GuV: Sonstige betriebliche Aufwände | L68: Verwaltung | M68: DATEV-CSV | N68: OK
A69: 2025-08 | B69: Mustermann GmbH | C69: 4830 | D69: 6830 | E69: EDV-Kosten & Software | F69: Büro & IT | G69: 10900 | I69: -10900 | J69: 10900 | K69: GuV: Sonstige betriebliche Aufwände | L69: IT | M69: DATEV-CSV | N69: OK
A70: 2025-08 | B70: Mustermann GmbH | C70: 4600 | D70: 6600 | E70: Werbekosten | F70: Marketing | G70: 3900 | I70: -3900 | J70: 3900 | K70: GuV: Sonstige betriebliche Aufwände | L70: Marketing | M70: DATEV-CSV | N70: OK
A71: 2025-08 | B71: Mustermann GmbH | C71: 4900 | D71: 6980 | E71: Sonstige Betriebskosten | F71: Sonstige | G71: 5192 | I71: -5192 | J71: 5192 | K71: GuV: Sonstige betriebliche Aufwände | L71: Verwaltung | M71: DATEV-CSV | N71: OK
A72: 2025-10 | B72: Mustermann GmbH | C72: 8000 | D72: 4000 | E72: Umsatzerlöse 19% | F72: Umsatz | H72: 110000 | I72: 110000 | J72: 110000 | K72: GuV: Umsatzerlöse | L72: Vertrieb | M72: DATEV-CSV | N72: OK
A73: 2025-10 | B73: Mustermann GmbH | C73: 3000 | D73: 5000 | E73: Wareneinkauf 19% | F73: Wareneinsatz | G73: 37000 | I73: -37000 | J73: 37000 | K73: GuV: Materialaufwand | L73: Einkauf | M73: DATEV-CSV | N73: OK
A74: 2025-10 | B74: Mustermann GmbH | C74: 4100 | D74: 6000 | E74: Löhne und Gehälter | F74: Personal | G74: 24000 | I74: -24000 | J74: 24000 | K74: GuV: Personalaufwand | L74: Personal | M74: DATEV-CSV | N74: OK
A75: 2025-10 | B75: Mustermann GmbH | C75: 4210 | D75: 6300 | E75: Miete & Pacht | F75: Raumkosten | G75: 4500 | I75: -4500 | J75: 4500 | K75: GuV: Sonstige betriebliche Aufwände | L75: Verwaltung | M75: DATEV-CSV | N75: OK
A76: 2025-10 | B76: Mustermann GmbH | C76: 4830 | D76: 6830 | E76: EDV-Kosten & Software | F76: Büro & IT | G76: 11500 | I76: -11500 | J76: 11500 | K76: GuV: Sonstige betriebliche Aufwände | L76: IT | M76: DATEV-CSV | N76: OK
A77: 2025-10 | B77: Mustermann GmbH | C77: 4600 | D77: 6600 | E77: Werbekosten | F77: Marketing | G77: 4300 | I77: -4300 | J77: 4300 | K77: GuV: Sonstige betriebliche Aufwände | L77: Marketing | M77: DATEV-CSV | N77: OK
A78: 2025-10 | B78: Mustermann GmbH | C78: 4900 | D78: 6980 | E78: Sonstige Betriebskosten | F78: Sonstige | G78: 6200 | I78: -6200 | J78: 6200 | K78: GuV: Sonstige betriebliche Aufwände | L78: Verwaltung | M78: DATEV-CSV | N78: OK
A79: 2025-11 | B79: Mustermann GmbH | C79: 8000 | D79: 4000 | E79: Umsatzerlöse 19% | F79: Umsatz | H79: 113000 | I79: 113000 | J79: 113000 | K79: GuV: Umsatzerlöse | L79: Vertrieb | M79: DATEV-CSV | N79: OK
A80: 2025-11 | B80: Mustermann GmbH | C80: 3000 | D80: 5000 | E80: Wareneinkauf 19% | F80: Wareneinsatz | G80: 38000 | I80: -38000 | J80: 38000 | K80: GuV: Materialaufwand | L80: Einkauf | M80: DATEV-CSV | N80: OK
A81: 2025-11 | B81: Mustermann GmbH | C81: 4100 | D81: 6000 | E81: Löhne und Gehälter | F81: Personal | G81: 24000 | I81: -24000 | J81: 24000 | K81: GuV: Personalaufwand | L81: Personal | M81: DATEV-CSV | N81: OK
A82: 2025-11 | B82: Mustermann GmbH | C82: 4210 | D82: 6300 | E82: Miete & Pacht | F82: Raumkosten | G82: 4600 | I82: -4600 | J82: 4600 | K82: GuV: Sonstige betriebliche Aufwände | L82: Verwaltung | M82: DATEV-CSV | N82: OK
A83: 2025-11 | B83: Mustermann GmbH | C83: 4830 | D83: 6830 | E83: EDV-Kosten & Software | F83: Büro & IT | G83: 11800 | I83: -11800 | J83: 11800 | K83: GuV: Sonstige betriebliche Aufwände | L83: IT | M83: DATEV-CSV | N83: OK
A84: 2025-11 | B84: Mustermann GmbH | C84: 4600 | D84: 6600 | E84: Werbekosten | F84: Marketing | G84: 4400 | I84: -4400 | J84: 4400 | K84: GuV: Sonstige betriebliche Aufwände | L84: Marketing | M84: DATEV-CSV | N84: OK
A85: 2025-11 | B85: Mustermann GmbH | C85: 4900 | D85: 6980 | E85: Sonstige Betriebskosten | F85: Sonstige | G85: 6200 | I85: -6200 | J85: 6200 | K85: GuV: Sonstige betriebliche Aufwände | L85: Verwaltung | M85: DATEV-CSV | N85: OK
A86: 2025-12 | B86: Mustermann GmbH | C86: 8000 | D86: 4000 | E86: Umsatzerlöse 19% | F86: Umsatz | H86: 118000 | I86: 118000 | J86: 118000 | K86: GuV: Umsatzerlöse | L86: Vertrieb | M86: DATEV-CSV | N86: OK
A87: 2025-12 | B87: Mustermann GmbH | C87: 3000 | D87: 5000 | E87: Wareneinkauf 19% | F87: Wareneinsatz | G87: 40000 | I87: -40000 | J87: 40000 | K87: GuV: Materialaufwand | L87: Einkauf | M87: DATEV-CSV | N87: OK
A88: 2025-12 | B88: Mustermann GmbH | C88: 4100 | D88: 6000 | E88: Löhne und Gehälter | F88: Personal | G88: 24500 | I88: -24500 | J88: 24500 | K88: GuV: Personalaufwand | L88: Personal | M88: DATEV-CSV | N88: OK
A89: 2025-12 | B89: Mustermann GmbH | C89: 4210 | D89: 6300 | E89: Miete & Pacht | F89: Raumkosten | G89: 4600 | I89: -4600 | J89: 4600 | K89: GuV: Sonstige betriebliche Aufwände | L89: Verwaltung | M89: DATEV-CSV | N89: OK
A90: 2025-12 | B90: Mustermann GmbH | C90: 4830 | D90: 6830 | E90: EDV-Kosten & Software | F90: Büro & IT | G90: 12000 | I90: -12000 | J90: 12000 | K90: GuV: Sonstige betriebliche Aufwände | L90: IT | M90: DATEV-CSV | N90: OK
A91: 2025-12 | B91: Mustermann GmbH | C91: 4600 | D91: 6600 | E91: Werbekosten | F91: Marketing | G91: 4600 | I91: -4600 | J91: 4600 | K91: GuV: Sonstige betriebliche Aufwände | L91: Marketing | M91: DATEV-CSV | N91: OK
A92: 2025-12 | B92: Mustermann GmbH | C92: 4900 | D92: 6980 | E92: Sonstige Betriebskosten | F92: Sonstige | G92: 6800 | I92: -6800 | J92: 6800 | K92: GuV: Sonstige betriebliche Aufwände | L92: Verwaltung | M92: DATEV-CSV | N92: OK
A93: 2025-02 | B93: Mustermann GmbH | C93: 1400 | D93: 1200 | E93: Forderungen aus LuL | F93: Forderungen | G93: 46500 | I93: -46500 | J93: 46500 | K93: Bilanz Aktiva: Umlaufvermögen | L93: Finance | M93: DATEV-CSV | N93: OK
A94: 2025-02 | B94: Mustermann GmbH | C94: 1200 | D94: 1800 | E94: Bank (Girokonto) | F94: Bankguthaben | G94: 25000 | I94: -25000 | J94: 25000 | K94: Bilanz Aktiva: Umlaufvermögen | L94: Finance | M94: DATEV-CSV | N94: OK
A95: 2025-02 | B95: Mustermann GmbH | C95: 1600 | D95: 3200 | E95: Verbindlichkeiten LuL | F95: Fremdkapital | H95: 19000 | I95: 19000 | J95: 19000 | K95: Bilanz Passiva: Verbindlichkeiten | L95: Finance | M95: DATEV-CSV | N95: OK
A96: 2025-03 | B96: Mustermann GmbH | C96: 1400 | D96: 1200 | E96: Forderungen aus LuL | F96: Forderungen | G96: 48000 | I96: -48000 | J96: 48000 | K96: Bilanz Aktiva: Umlaufvermögen | L96: Finance | M96: DATEV-CSV | N96: OK
A97: 2025-03 | B97: Mustermann GmbH | C97: 1200 | D97: 1800 | E97: Bank (Girokonto) | F97: Bankguthaben | G97: 27000 | I97: -27000 | J97: 27000 | K97: Bilanz Aktiva: Umlaufvermögen | L97: Finance | M97: DATEV-CSV | N97: OK
A98: 2025-03 | B98: Mustermann GmbH | C98: 1600 | D98: 3200 | E98: Verbindlichkeiten LuL | F98: Fremdkapital | H98: 20000 | I98: 20000 | J98: 20000 | K98: Bilanz Passiva: Verbindlichkeiten | L98: Finance | M98: DATEV-CSV | N98: OK
A99: 2025-04 | B99: Mustermann GmbH | C99: 1400 | D99: 1200 | E99: Forderungen aus LuL | F99: Forderungen | G99: 45000 | I99: -45000 | J99: 45000 | K99: Bilanz Aktiva: Umlaufvermögen | L99: Finance | M99: DATEV-CSV | N99: OK
A100: 2025-04 | B100: Mustermann GmbH | C100: 1200 | D100: 1800 | E100: Bank (Girokonto) | F100: Bankguthaben | G100: 26000 | I100: -26000 | J100: 26000 | K100: Bilanz Aktiva: Umlaufvermögen | L100: Finance | M100: DATEV-CSV | N100: OK
...

Sheet 02_BWA_Import
A1: 📥 DATEV BWA — CSV Import & Rohdaten
A2: Datenbasis für alle Auswertungen. CSV hier einfügen oder per Power Query / manuell befüllen.
A4: Monat | B4: Mandant | C4: Konto | F4: Kontobezeichnung | G4: BWA-Gruppe | H4: Betrag (€) | I4: Kostenstelle | J4: Quelle | K4: Status
A5: 2025-01 | B5: Mustermann GmbH | C5: 8000 | F5: Umsatzerlöse 19% | G5: Umsatz | H5: 92300 | I5: Vertrieb | J5: DATEV-CSV | K5: OK
A6: 2025-01 | B6: Mustermann GmbH | C6: 4000 | F6: Wareneinsatz | G6: Kosten | H6: 31000 | I6: Einkauf | J6: DATEV-CSV | K6: OK
A7: 2025-01 | B7: Mustermann GmbH | C7: 4200 | F7: Personalkosten | G7: Personal | H7: 22000 | I7: Team Gesamt | J7: DATEV-CSV | K7: OK
A8: 2025-01 | B8: Mustermann GmbH | C8: 4300 | F8: Sonstige Kosten | G8: Sonstige | H8: 17270 | I8: Verwaltung | J8: DATEV-CSV | K8: OK
A9: 2025-02 | B9: Mustermann GmbH | C9: 8000 | F9: Umsatzerlöse 19% | G9: Umsatz | H9: 95550 | I9: Vertrieb | J9: DATEV-CSV | K9: OK
A10: 2025-02 | B10: Mustermann GmbH | C10: 4000 | F10: Wareneinsatz | G10: Kosten | H10: 32000 | I10: Einkauf | J10: DATEV-CSV | K10: OK
A11: 2025-02 | B11: Mustermann GmbH | C11: 4200 | F11: Personalkosten | G11: Personal | H11: 22000 | I11: Team Gesamt | J11: DATEV-CSV | K11: OK
A12: 2025-02 | B12: Mustermann GmbH | C12: 4300 | F12: Sonstige Kosten | G12: Sonstige | H12: 19465 | I12: Verwaltung | J12: DATEV-CSV | K12: OK
A13: 2025-03 | B13: Mustermann GmbH | C13: 8000 | F13: Umsatzerlöse 19% | G13: Umsatz | H13: 100100 | I13: Vertrieb | J13: DATEV-CSV | K13: OK
A14: 2025-03 | B14: Mustermann GmbH | C14: 4000 | F14: Wareneinsatz | G14: Kosten | H14: 33500 | I14: Einkauf | J14: DATEV-CSV | K14: OK
A15: 2025-03 | B15: Mustermann GmbH | C15: 4200 | F15: Personalkosten | G15: Personal | H15: 22500 | I15: Team Gesamt | J15: DATEV-CSV | K15: OK
A16: 2025-03 | B16: Mustermann GmbH | C16: 4300 | F16: Sonstige Kosten | G16: Sonstige | H16: 22930 | I16: Verwaltung | J16: DATEV-CSV | K16: OK
... A40: 2025-09 | B40: Mustermann GmbH | C40: 4300 | F40: Sonstige Kosten | G40: Sonstige | H40: 25460 | I40: Verwaltung | J40: DATEV-CSV | K40: OK
A41: SUMME (36 Datensätze / 9 Monate) | H41: =SUM(F5:F40) -> 0

Sheet 03_Mitarbeiter
A1: 👥 Mitarbeiterdaten & Personalkosten
A2: Personalkostenmatrix je Mandant und Kostenstelle — Basis für Personalquoten-Berechnung im Dashboard.
A4: ID | B4: Name | C4: Mandant | D4: Kostenstelle | E4: Team | F4: Monatslohn (€) | G4: Std./Monat | H4: €/Std. | I4: AG-Anteil (20%) | J4: Gesamtkosten
A5: E001 | B5: Anna Schmidt | C5: Mustermann GmbH | D5: IT | E5: Dev | F5: 5200 | G5: 160 | H5: =F5/G5 -> 32.5 | I5: =F5*0.2 -> 1040 | J5: =F5+I5 -> 6240
A6: E002 | B6: Ben Müller | C6: Mustermann GmbH | D6: IT | E6: Support | F6: 4300 | G6: 160 | H6: =F6/G6 -> 26.875 | I6: =F6*0.2 -> 860 | J6: =F6+I6 -> 5160
A7: E003 | B7: Cem Yilmaz | C7: Mustermann GmbH | D7: Sales | E7: Beratung | F7: 6100 | G7: 168 | H7: =F7/G7 -> 36.309524 | I7: =F7*0.2 -> 1220 | J7: =F7+I7 -> 7320
A8: E004 | B8: Dana Weber | C8: Mustermann GmbH | D8: Finance | E8: Buchhaltung | F8: 4800 | G8: 160 | H8: =F8/G8 -> 30 | I8: =F8*0.2 -> 960 | J8: =F8+I8 -> 5760
A9: E101 | B9: Erik Bauer | C9: Beispiel Handel GmbH | D9: Vertrieb | E9: Außendienst | F9: 4900 | G9: 172 | H9: =F9/G9 -> 28.488372 | I9: =F9*0.2 -> 980 | J9: =F9+I9 -> 5880
A10: E102 | B10: Fatma Kaya | C10: Alpha Services UG | D10: Service | E10: Consulting | F10: 5500 | G10: 160 | H10: =F10/G10 -> 34.375 | I10: =F10*0.2 -> 1100 | J10: =F10+I10 -> 6600
A11: GESAMT (6 Mitarbeiter) | F11: =SUM(F5:F10) -> 30800 | I11: =SUM(I5:I10) -> 6160 | J11: =SUM(J5:J10) -> 36960
A13: KOSTENSTELLEN-AUSWERTUNG (Lohnsumme je Kostenstelle)
A14: IT | B14: 2 | C14: 9500 | D14: 30.844156
A15: Sales | B15: 1 | C15: 6100 | D15: 19.805195
A16: Finance | B16: 1 | C16: 4800 | D16: 15.584416
A17: Vertrieb | B17: 1 | C17: 4900 | D17: 15.909091
A18: Service | B18: 1 | C18: 5500 | D18: 17.857143

Sheet 04_Dashboard
A1: 📊 BWA DASHBOARD — Mustermann GmbH | Jan–Sep 2025 | Berichtsmonat: September
A2: Alle Werte in Euro (€) · Quoten in % · Automatische Formelberechnung aus Rohdaten
A4: 📈 Umsatz YTD | C4: 💰 Rohertrag YTD | E4: ✅ EBIT YTD | G4: 💧 Ø Liquidität | I4: ⏱ Cash-Reichweite | K4: 👥 Mitarbeiter | M4: 🎯 EBIT-Marge
A5: 898.460 € | C5: 594.960 € | E5: 194.611 € | G5: 147 % | I5: 44 Tage | K5: 4 | M5: 21.7 %
A6: ▲ +11.1% vs. VJ | C6: ▲ +11.1% vs. VJ | E6: ▲ +11.1% vs. VJ | G6: ▲ +11.4% vs. VJ | I6: ▲ +10.0% vs. VJ | K6: ▼ 0.0% vs. VJ | M6: ▲ +8.5% vs. VJ
A8: Monat | B8: Umsatz | C8: Umsatz VJ | D8: Δ% | E8: Wareneinsatz | F8: Rohertrag | G8: RohE-Quote% | H8: Personal | I8: Personal% | J8: Sonstige | K8: EBIT | L8: EBIT-Marge% | M8: Liquidität% | N8: Reichweite Tage
A9: Jan | B9: 92300 | C9: 84916 | D9: =(B9-C9)/C9*100 -> 8.6956522 | E9: 31000 | F9: 61300 | G9: =F9/B9*100 -> 66.413868 | H9: 22000 | I9: =H9/B9*100 -> 23.83532 | J9: 17270 | K9: 22030 | L9: =K9/B9*100 -> 23.867822 | M9: 128 | N9: 38
A10: Feb | B10: 95550 | C10: 87906 | D10: =(B10-C10)/C10*100 -> 8.6956522 | E10: 32000 | F10: 63550 | G10: =F10/B10*100 -> 66.509681 | H10: 22000 | I10: =H10/B10*100 -> 23.024594 | J10: 19465 | K10: 22085 | L10: =K10/B10*100 -> 23.113553 | M10: 132 | N10: 39
A11: Mär | B11: 100100 | C11: 92092 | D11: =(B11-C11)/C11*100 -> 8.6956522 | E11: 33500 | F11: 66600 | G11: =F11/B11*100 -> 66.533467 | H11: 22500 | I11: =H11/B11*100 -> 22.477522 | J11: 22930 | K11: 21170 | L11: =K11/B11*100 -> 21.148851 | M11: 135 | N11: 40
A12: Apr | B12: 93780 | C12: 86278 | D12: =(B12-C12)/C12*100 -> 8.6951482 | E12: 32000 | F12: 61780 | G12: =F12/B12*100 -> 65.877586 | H12: 22000 | I12: =H12/B12*100 -> 23.45916 | J12: 18432 | K12: 21348 | L12: =K12/B12*100 -> 22.763916 | M12: 136 | N12: 40
A13: Mai | B13: 100300 | C13: 92276 | D13: =(B13-C13)/C13*100 -> 8.6956522 | E13: 34000 | F13: 66300 | G13: =F13/B13*100 -> 66.101695 | H13: 22500 | I13: =H13/B13*100 -> 22.432702 | J13: 22408 | K13: 21392 | L13: =K13/B13*100 -> 21.328016 | M13: 139 | N13: 41
A14: Jun | B14: 103600 | C14: 95312 | D14: =(B14-C14)/C14*100 -> 8.6956522 | E14: 35000 | F14: 68600 | G14: =F14/B14*100 -> 66.216216 | H14: 23000 | I14: =H14/B14*100 -> 22.200772 | J14: 23865 | K14: 21735 | L14: =K14/B14*100 -> 20.97973 | M14: 141 | N14: 42
A15: Jul | B15: 101190 | C15: 93095 | D15: =(B15-C15)/C15*100 -> 8.6954187 | E15: 34500 | F15: 66690 | G15: =F15/B15*100 -> 65.905722 | H15: 22500 | I15: =H15/B15*100 -> 22.235399 | J15: 23027 | K15: 21163 | L15: =K15/B15*100 -> 20.914122 | M15: 143 | N15: 42
A16: Aug | B16: 104570 | C16: 96204 | D16: =(B16-C16)/C16*100 -> 8.6961041 | E16: 35500 | F16: 69070 | G16: =F16/B16*100 -> 66.051449 | H16: 23000 | I16: =H16/B16*100 -> 21.994836 | J16: 24492 | K16: 21578 | L16: =K16/B16*100 -> 20.634981 | M16: 145 | N16: 43
A17: Sep | B17: 107070 | C17: 98504 | D17: =(B17-C17)/C17*100 -> 8.6960936 | E17: 36000 | F17: 71070 | G17: =F17/B17*100 -> 66.377136 | H17: 23500 | I17: =H17/B17*100 -> 21.948258 | J17: 25460 | K17: 22110 | L17: =K17/B17*100 -> 20.650042 | M17: 147 | N17: 44
A18: YTD GESAMT / DURCHSCHNITT | B18: =SUM(B9:B17) -> 898460 | C18: =SUM(C9:C17) -> 826583 | D18: =(B18-C18)/C18*100 -> 8.6956785 | E18: =SUM(E9:E17) -> 303500 | F18: =SUM(F9:F17) -> 594960 | G18: =F18/B18*100 -> 66.219976 | H18: =SUM(H9:H17) -> 203000 | I18: =H18/B18*100 -> 22.594217 | J18: =SUM(J9:J17) -> 197349 | K18: =SUM(K9:K17) -> 194611 | L18: =K18/B18*100 -> 21.660508 | M18: =AVERAGE(M9:M17) -> 138.44444 | N18: =AVERAGE(N9:N17) -> 41

Sheet 05_Kennzahlen
A1: 📐 KENNZAHLEN — Vollständige BWA-Ratios mit Ampelsystem
A3: Kennzahl | B3: Wert Akt. | C3: Wert VJ | D3: Δ Abs. | E3: Δ % | F3: Zielwert | G3: Ampel | H3: Interpretation & Handlungsempfehlung
A4: Rohertragsquote | B4: 67.1 | C4: 64.2 | D4: =B4-C4 -> 2.9 | E4: =(B4-C4)/C4*100 -> 4.517134 | F4: 65 | G4: 🟢 | H4: Anteil Rohertrag am Umsatz. >65% = stabil für Dienstleister.
A5: EBIT-Marge | B5: 25.8 | C5: 22.1 | D5: =B5-C5 -> 3.7 | E5: =(B5-C5)/C5*100 -> 16.742081 | F5: 18 | G5: 🟢 | H5: Operativer Gewinn vor Zinsen & Steuern. >18% = Zielkorridor erreicht.
A6: Liquidität 1. Grades | B6: 147.4 | C6: 131 | D6: =B6-C6 -> 16.4 | E6: =(B6-C6)/C6*100 -> 12.519084 | F6: 120 | G6: 🟢 | H6: Barmittel zu kurzfristigen Verbindlichkeiten. >100% = solvent.
A7: Liquidität 2. Grades | B7: 234.7 | C7: 198 | D7: =B7-C7 -> 36.7 | E7: =(B7-C7)/C7*100 -> 18.535354 | F7: 150 | G7: 🟢 | H7: Einschl. kurzfristige Forderungen. >150% = komfortabel.
A8: Cash-Reichweite | B8: 43.8 | C8: 38 | D8: =B8-C8 -> 5.8 | E8: =(B8-C8)/C8*100 -> 15.263158 | F8: 30 | G8: 🟢 | H8: Wie viele Tage können laufende Kosten aus Kassenbestand gedeckt werden?
A9: Personalquote | B9: 23.1 | C9: 24.3 | D9: =B9-C9 -> -1.2 | E9: =(B9-C9)/C9*100 -> -4.9382716 | F9: 25 | G9: 🟢 | H9: Personalkosten / Umsatz. <25% = effizient. Tendenz sinkend = gut.
A10: Materialquote | B10: 32.9 | C10: 34.1 | D10: =B10-C10 -> -1.2 | E10: =(B10-C10)/C10*100 -> -3.5190616 | F10: 35 | G10: 🟢 | H10: Wareneinsatz / Umsatz. <35% = Normbereich. Einkauf prüfen.
A11: Sonstigenquote | B11: 23.8 | C11: 20.1 | D11: =B11-C11 -> 3.7 | E11: =(B11-C11)/C11*100 -> 18.40796 | F11: 20 | G11: 🔴 | H11: Sonstige Kosten / Umsatz. Anstieg von +3,7 PP gegenüber VJ – Ursache klären!
A12: Rentabilität (RoS) | B12: 27.4 | C12: 24 | D12: =B12-C12 -> 3.4 | E12: =(B12-C12)/C12*100 -> 14.166667 | F12: 20 | G12: 🟢 | H12: Reingewinn / Umsatz (vereinfacht EBIT-basiert). >20% = attraktiv.
A13: Umsatz je Mitarbeiter | B13: 26767 | C13: 23500 | D13: =B13-C13 -> 3267 | E13: =(B13-C13)/C13*100 -> 13.902128 | F13: 25000 | G13: 🟢 | H13: Umsatz YTD / (MA-Anzahl × Monate). Produktivitätsindikator.
A14: EBIT je Mitarbeiter | B14: 6930 | C14: 5700 | D14: =B14-C14 -> 1230 | E14: =(B14-C14)/C14*100 -> 21.578947 | F14: 5000 | G14: 🟢 | H14: EBIT YTD / (MA-Anzahl × Monate). Ertragseffizienz je Kopf.
A15: Deckungsbeitrag DB I | B15: 594960 | C15: 523565 | D15: =B15-C15 -> 71395 | E15: =(B15-C15)/C15*100 -> 13.63632 | F15: — | G15: ⚪ | H15: Rohertrag gesamt YTD.
A16: Wachstum vs. VJ | B16: 15.2 | C16: — | D16: — | E16: — | F16: 10 | G16: 🟢 | H16: Umsatzwachstum gegenüber Vorjahreszeitraum (simuliert).

Sheet 06_Mandantenbericht
A1: 📋 EXECUTIVE REPORT — Mustermann GmbH | September 2025
A2: Monatsbericht · Vertraulich · Erstellt mit DATEV BWA Reporting Master · thinkhub360 controllhub360
A4: Umsatz Sep | C4: Rohertrag | E4: EBIT | G4: Liquidität | I4: Reichweite | K4: Personal
A5: 107.070 € | C5: 71.070 € | E5: 22.110 € | G5: 147 % | I5: 44 Tage | K5: 23.500 €
A6: stärkster Monat | C6: stabile Marge | E6: klar positiv | G6: stark | I6: komfortabel | K6: kontrolliert
A8: Monat | B8: Umsatz | C8: VJ-Umsatz | D8: Δ% | E8: Wareneinsatz | F8: Rohertrag | G8: RohE-% | H8: Personal | I8: EBIT | J8: EBIT-% | K8: Liquidität% | L8: KI-Kommentar / Analyse
A9: Jan | B9: 92300 | C9: 84916 | D9: =(B9-C9)/C9*100 -> 8.6956522 | E9: 31000 | F9: 61300 | G9: =F9/B9*100 -> 66.413868 | H9: 22000 | I9: 22030 | J9: =I9/B9*100 -> 23.867822 | K9: 128 | L9: Solider Jahresstart. Umsatz im unteren Jahreskorridor – Wareneinsatz gut kontrolliert. Personalquote 23,8% – Watch-Level.
A10: Feb | B10: 95550 | C10: 87906 | D10: =(B10-C10)/C10*100 -> 8.6956522 | E10: 32000 | F10: 63550 | G10: =F10/B10*100 -> 66.509681 | H10: 22000 | I10: 22085 | J10: =I10/B10*100 -> 23.113553 | K10: 132 | L10: Leichter Umsatzanstieg (+3,5%). Sonstige Kosten +12,7% gegenüber Jan – Ursache klären (Einmalige oder Dauerposten?).
A11: Mär | B11: 100100 | C11: 92092 | D11: =(B11-C11)/C11*100 -> 8.6956522 | E11: 33500 | F11: 66600 | G11: =F11/B11*100 -> 66.533467 | H11: 22500 | I11: 21170 | J11: =I11/B11*100 -> 21.148851 | K11: 135 | L11: Stärkstes Q1-Ergebnis. EBIT dennoch unter Jan/Feb durch Sonstigenanstieg. Kostenstellen IT und Sales prüfen.
A12: Apr | B12: 93780 | C12: 86278 | D12: =(B12-C12)/C12*100 -> 8.6951482 | E12: 32000 | F12: 61780 | G12: =F12/B12*100 -> 65.877586 | H12: 22000 | I12: 21348 | J12: =I12/B12*100 -> 22.763916 | K12: 136 | L12: Apr: Umsatzdelle -6,3%. Personal und Wareneinsatz anteilig stabil – EBIT bleibt positiv. Typischer Saisoneffekt?
A13: Mai | B13: 100300 | C13: 92276 | D13: =(B13-C13)/C13*100 -> 8.6956522 | E13: 34000 | F13: 66300 | G13: =F13/B13*100 -> 66.101695 | H13: 22500 | I13: 21392 | J13: =I13/B13*100 -> 21.328016 | K13: 139 | L13: Erholung bestätigt. Umsatz +7% vs. Apr. Sonstige wieder erhöht – dauerhafte Kostenstrukturveränderung möglich.
A14: Jun | B14: 103600 | C14: 95312 | D14: =(B14-C14)/C14*100 -> 8.6956522 | E14: 35000 | F14: 68600 | G14: =F14/B14*100 -> 66.216216 | H14: 23000 | I14: 21735 | J14: =I14/B14*100 -> 20.97973 | K14: 141 | L14: Bester Monat H1. EBIT-Marge 21,0%. Liquidität erstmals >140% – Handlungsspielraum für Investitionen gegeben.
A15: Jul | B15: 101190 | C15: 93095 | D15: =(B15-C15)/C15*100 -> 8.6954187 | E15: 34500 | F15: 66690 | G15: =F15/B15*100 -> 65.905722 | H15: 22500 | I15: 21163 | J15: =I15/B15*100 -> 20.914122 | K15: 143 | L15: Leichter Rückgang vs. Jun (-2,3%). Feriensaison? Rohertragsmarge stabil bei 66,0%. Personal effizient.
A16: Aug | B16: 104570 | C16: 96204 | D16: =(B16-C16)/C16*100 -> 8.6961041 | E16: 35500 | F16: 69070 | G16: =F16/B16*100 -> 66.051449 | H16: 23000 | I16: 21578 | J16: =I16/B16*100 -> 20.634981 | K16: 145 | L16: Aufwärtstrend bestätigt. Umsatz +3,3% vs. Jul. EBIT wächst moderat. Liquidität 145% – komfortable Pufferlage.
A17: Sep | B17: 107070 | C17: 98504 | D17: =(B17-C17)/C17*100 -> 8.6960936 | E17: 36000 | F17: 71070 | G17: =F17/B17*100 -> 66.377136 | H17: 23500 | I17: 22110 | J17: =I17/B17*100 -> 20.650042 | K17: 147 | L17: Stärkstes Monatsergebnis YTD. Umsatz 107.070€, EBIT 22.110€ (20,7% Marge). Zielpfad Q4 liegt im grünen Bereich.
A18: YTD GESAMT (Jan–Sep 2025) | B18: =SUM(B9:B17) -> 898460 | C18: =SUM(C9:C17) -> 826583 | D18: =(B18-C18)/C18*100 -> 8.6956785 | E18: =SUM(E9:E17) -> 303500 | F18: =SUM(F9:F17) -> 594960 | G18: =F18/B18*100 -> 66.219976 | H18: =SUM(H9:H17) -> 203000 | I18: =SUM(I9:I17) -> 194611 | J18: =I18/B18*100 -> 21.660508 | K18: =AVERAGE(K9:K17) -> 138.44444
A20: 🤖 KI-AUSWERTUNG & MANAGEMENTKOMMENTAR — September 2025
A21: 1. Geschäftsentwicklung | C21: September 2025 ist der stärkste Berichtsmonat YTD mit 107.070€ Umsatz (+15,9% vs. Januar). Der Wachstumspfad ist konsistent – kein Monat unter dem Vormonat ohne erklärbaren Saisoneffekt. Die Geschäftsbasis wirkt stabil und operativ beherrschbar.
A22: 2. Ertragslage | C22: Rohertrag 71.070€ (66,4% Quote), EBIT 22.110€ (20,7% Marge). Beide Werte liegen im grünen Korridor. Die EBIT-Qualität ist hoch, da kein Einmalergebnis erkennbar. Wareneinsatz entwickelt sich proportional zum Umsatz – kein Margendruck von der Beschaffungsseite.
A23: 3. Kostenbewertung | C23: Wareneinsatz Sep: 36.000€ (33,6% Quote – stabil). Personal: 23.500€ (22,0% Quote – leicht steigend). KRITISCH: Sonstige Kosten 25.460€ (+47,4% vs. Jan) – dieser Block wächst schneller als der Umsatz. Kostenstellen-Drill-down zwingend erforderlich für Q4-Planung.
A24: 4. Liquidität & Finanzlage | C24: Liquidität 1. Grades 147% – deutlich über Minimum. Cash-Reichweite 44 Tage – komfortabler Puffer. Ab ca. 60 Tagen Reichweite wäre eine Festgeld-/Anlage-Überlegung sinnvoll. Keine Anzeichen von Liquiditätsdruck erkennbar.
A25: 5. Personalentwicklung | C25: 4 Mitarbeiter Mustermann GmbH, Gesamtlohn 20.400€ netto (inkl. AG-Anteil ~24.480€). Gebuchter Personalaufwand 23.500€ – Differenz ca. 980€ prüfen (Aushilfen? Projektkosten?). Sales/Beratung (Cem Yilmaz, 6.100€) erzielt höchsten Umsatzbeitrag je Kopf – effizienter Einsatz.
A26: 6. Ausblick & Empfehlung Q4 | C26: Auf Basis der positiven Entwicklung Jan–Sep 2025: Jahresumsatz ca. 1,15–1,18 Mio € realistisch (bei gleichbleibendem Wachstumspfad). EBIT-Jahreswert ca. 295–310K€ (ca. 25,5–26,5% Marge). Empfehlungen: (1) Sonstigenkosten analysieren, (2) Personal-Soll/Ist-Abgleich, (3) Liquiditätsüberschuss in Q4 strukturieren.

Sheet 07_KI_Auswertung
A1: 🤖 KI-AUSWERTUNG — Tiefenanalyse nach Bereichen
A3: Bereich | B3: Ampel | C3: Bewertung | D3: Trend vs. VJ | E3: Maßnahme (Kurzfristig) | F3: KI-Tiefenanalyse
A4: EBIT | B4: 🟢 | C4: über Ziel | D4: ▲ +16,7% | E4: weiter eng überwachen | F4: Die EBIT-Entwicklung über Jan–Sep zeigt einen robusten Aufwärtstrend mit einer Spanne von 21.163€ bis 22.110€. Die Marge liegt konstant zwischen 20-22% und übertrifft den Branchendurchschnitt (Ø 15-17%). Risiko: Kostenstruktur der Sonstigen Kosten – hier fehlt noch eine Kostenstellen-tiefe Analyse.
A5: Rohertrag | B5: 🟢 | C5: stark & stabil | D5: ▲ +12,4% | E5: Wareneinsatz monatlich prüfen | F5: Rohertrag entwickelt sich von 61.300€ (Jan) auf 71.070€ (Sep) – ein organisches Wachstum von +15,9% in 9 Monaten. Die Rohertragsquote lag stabil zwischen 64-67%. Wareneinsatzquote zeigt keine negativen Ausreißer. Empfehlung: Lieferantenkonditionen Q4 neu verhandeln.
A6: Liquidität | B6: 🟢 | C6: hoch & wachsend | D6: ▲ +12,5% | E6: Reserve sichern | F6: Liquidität 1. Grades von 128% (Jan) auf 147% (Sep) – durchgehend über der kritischen Marke von 100%. Kein Monat im Roten Bereich. Cash-Reichweite von 44 Tagen ist solide für die Betriebsgröße. Empfehlung: Ggf. Festgeldrücklage ab Q4 prüfen.
A7: Rentabilität | B7: 🟢 | C7: gesund | D7: ▲ +14,2% | E7: Marge verteidigen | F7: Gesamtrentabilität YTD 27,4% – für ein KMU herausragend. Kapitalrendite (vereinfacht) deutet auf gesundes Wachstum ohne Substanzverzehr hin. Cashflow-Qualität erscheint hoch, jedoch fehlt noch Abschreibungs-/Investitionsrechnung für vollständiges Bild.
A8: Personal | B8: 🟡 | C8: unter Beobachtung | D8: ▼ -5,0% | E8: Std./Teamquote analysieren | F8: Personalquote schwankt zwischen 21-22%. Aktuell 4 MA (Mustermann GmbH) mit Gesamtlohn 20.400€/Monat – leicht unter dem gebuchten Wert (23.500€). Differenz prüfen: Aushilfen? Arbeitgeberanteile? Team-Effizienz (Vertrieb) erscheint hoch – Sales/Beratung erzielt höchste Umsatzpro-Kopf-Quote.
A9: Sonstiges | B9: 🔴 | C9: kritisch wachsend | D9: ▼ -23,6% | E9: Kostenblock aufschlüsseln | F9: Sonstige Kosten stiegen von 17.270€ (Jan) auf 25.460€ (Sep) – ein Anstieg von +47,4%. Ohne Gegenrechnung ist dies der kritischste Kostenblock. Empfehlung: Aufschlüsselung nach Kostenstellen dringend für Oktober. Mögliche Treiber: Marketing, Software-Lizenzen, externe Dienstleister.

Sheet 08_Kumuliert_Final
A1: 🏢 KUMULIERTE & FINALE DARSTELLUNG — Alle Mandanten
A2: Gesamtübersicht aller Mandanten in drei Sichten: Einzeln · Kumuliert · Finalbericht
A4: Darstellung / Mandant | B4: Selektion | C4: Umsatz YTD | D4: Rohertrag YTD | E4: EBIT YTD | F4: EBIT-% | G4: Liquidität Ø | H4: Kommentar
A5: Einzeln – Mustermann GmbH | B5: Aktiver Mandant | C5: 865020 | D5: 580020 | E5: 223220 | F5: 25.8 | G5: 147.4 | H5: Fokus-Mandant aus Einstellungsseite
A6: Kumuliert – alle aktiven Firmen | B6: Kum=Ja | C6: 2450000 | D6: 1580000 | E6: 612000 | F6: 25 | G6: 139 | H6: Gesamtkanzlei / Holdingblick
A7: Final – freigegebene Firmen | B7: Final=Ja | C7: 2310000 | D7: 1495000 | E7: 590000 | F7: 25.5 | G7: 141.2 | H7: Management- und Bankbericht
A10: MANDANTENVERGLEICH — Einzelergebnisse Jan–Sep 2025
A11: Mandant | B11: Status | C11: Umsatz | D11: Rohertrag | E11: RohE-% | F11: EBIT | G11: EBIT-% | H11: Ø Liquidität
A12: Mustermann GmbH | B12: ✓ Aktiv | C12: 865020 | D12: 580020 | E12: 67.1 | F12: 223220 | G12: 25.8 | H12: 147.4
A13: Beispiel Handel GmbH | B13: ✓ Aktiv | C13: 920000 | D13: 560000 | E13: 60.9 | F13: 210000 | G13: 22.8 | H13: 132
A14: Alpha Services UG | B14: ✓ Aktiv | C14: 665000 | D14: 440000 | E14: 66.2 | F14: 178780 | G14: 26.9 | H14: 138.5
A15: Beta Technik GmbH | B15: ✓ Aktiv | C15: 450000 | D15: 265000 | E15: 58.9 | F15: 120000 | G15: 26.7 | H15: 128
A16: Gamma Holding GmbH | B16: ✗ Inaktiv | C16: – | D16: – | E16: – | F16: – | G16: – | H16: –
A17: GESAMT KUMULIERT (aktive Mandanten) | C17: =SUM(C12:C16) -> 2900020 | D17: =SUM(D12:D16) -> 1845020 | E17: — | F17: =SUM(F12:F16) -> 732000 | G17: — | H17: —

Sheet 09_Planung
A1: 📅 PLANUNG & FORECAST — Q4 2025 & Gesamtjahr 2025
A2: Hochrechnung auf Basis IST Jan–Sep · Planwerte für Okt–Dez · Dynamische Formelberechnung
A4: Monat | B4: Typ | C4: Umsatz | D4: Plan Umsatz | E4: Δ Plan% | F4: Wareneinsatz | G4: Rohertrag | H4: RohE-% | I4: Personal | J4: Sonstige | K4: EBIT | L4: EBIT-% | M4: Liquidität% | N4: Status | O4: Kommentar | P4: Szenario
A5: Jan | B5: IST | C5: 92300 | D5: 103376 | E5: =(C5-D5)/D5*100 -> -10.714286 | F5: 31000 | G5: =C5-F5 -> 61300 | H5: =G5/C5*100 -> 66.413868 | I5: 22000 | J5: 17270 | K5: =G5-I5-J5 -> 22030 | L5: =K5/C5*100 -> 23.867822 | M5: 128 | N5: ✓ Final | O5: Solider Jahresstart. Umsatz im unteren Jahreskorridor – Wareneinsatz gut kontrolliert. Personalquote 23,8% – Watch-Level. | P5: IST
A6: Feb | B6: IST | C6: 95550 | D6: 107016 | E6: =(C6-D6)/D6*100 -> -10.714286 | F6: 32000 | G6: =C6-F6 -> 63550 | H6: =G6/C6*100 -> 66.509681 | I6: 22000 | J6: 19465 | K6: =G6-I6-J6 -> 22085 | L6: =K6/C6*100 -> 23.113553 | M6: 132 | N6: ✓ Final | O6: Leichter Umsatzanstieg (+3,5%). Sonstige Kosten +12,7% gegenüber Jan – Ursache klären (Einmalige oder Dauerposten?). | P6: IST
A7: Mär | B7: IST | C7: 100100 | D7: 112112 | E7: =(C7-D7)/D7*100 -> -10.714286 | F7: 33500 | G7: =C7-F7 -> 66600 | H7: =G7/C7*100 -> 66.533467 | I7: 22500 | J7: 22930 | K7: =G7-I7-J7 -> 21170 | L7: =K7/C7*100 -> 21.148851 | M7: 135 | N7: ✓ Final | O7: Stärkstes Q1-Ergebnis. EBIT dennoch unter Jan/Feb durch Sonstigenanstieg. Kostenstellen IT und Sales prüfen. | P7: IST
A8: Apr | B8: IST | C8: 93780 | D8: 105034 | E8: =(C8-D8)/D8*100 -> -10.714626 | F8: 32000 | G8: =C8-F8 -> 61780 | H8: =G8/C8*100 -> 65.877586 | I8: 22000 | J8: 18432 | K8: =G8-I8-J8 -> 21348 | L8: =K8/C8*100 -> 22.763916 | M8: 136 | N8: ✓ Final | O8: Apr: Umsatzdelle -6,3%. Personal und Wareneinsatz anteilig stabil – EBIT bleibt positiv. Typischer Saisoneffekt? | P8: IST
A9: Mai | B9: IST | C9: 100300 | D9: 112336 | E9: =(C9-D9)/D9*100 -> -10.714286 | F9: 34000 | G9: =C9-F9 -> 66300 | H9: =G9/C9*100 -> 66.101695 | I9: 22500 | J9: 22408 | K9: =G9-I9-J9 -> 21392 | L9: =K9/C9*100 -> 21.328016 | M9: 139 | N9: ✓ Final | O9: Erholung bestätigt. Umsatz +7% vs. Apr. Sonstige wieder erhöht – dauerhafte Kostenstrukturveränderung möglich. | P9: IST
A10: Jun | B10: IST | C10: 103600 | D10: 116032 | E10: =(C10-D10)/D10*100 -> -10.714286 | F10: 35000 | G10: =C10-F10 -> 68600 | H10: =G10/C10*100 -> 66.216216 | I10: 23000 | J10: 23865 | K10: =G10-I10-J10 -> 21735 | L10: =K10/C10*100 -> 20.97973 | M10: 141 | N10: ✓ Final | O10: Bester Monat H1. EBIT-Marge 21,0%. Liquidität erstmals >140% – Handlungsspielraum für Investitionen gegeben. | P10: IST
A11: Jul | B11: IST | C11: 101190 | D11: 113333 | E11: =(C11-D11)/D11*100 -> -10.714443 | F11: 34500 | G11: =C11-F11 -> 66690 | H11: =G11/C11*100 -> 65.905722 | I11: 22500 | J11: 23027 | K11: =G11-I11-J11 -> 21163 | L11: =K11/C11*100 -> 20.914122 | M11: 143 | N11: ✓ Final | O11: Leichter Rückgang vs. Jun (-2,3%). Feriensaison? Rohertragsmarge stabil bei 66,0%. Personal effizient. | P11: IST
A12: Aug | B12: IST | C12: 104570 | D12: 117118 | E12: =(C12-D12)/D12*100 -> -10.713981 | F12: 35500 | G12: =C12-F12 -> 69070 | H12: =G12/C12*100 -> 66.051449 | I12: 23000 | J12: 24492 | K12: =G12-I12-J12 -> 21578 | L12: =K12/C12*100 -> 20.634981 | M12: 145 | N12: ✓ Final | O12: Aufwärtstrend bestätigt. Umsatz +3,3% vs. Jul. EBIT wächst moderat. Liquidität 145% – komfortable Pufferlage. | P12: IST
A13: Sep | B13: IST | C13: 107070 | D13: 119918 | E13: =(C13-D13)/D13*100 -> -10.713988 | F13: 36000 | G13: =C13-F13 -> 71070 | H13: =G13/C13*100 -> 66.377136 | I13: 23500 | J13: 25460 | K13: =G13-I13-J13 -> 22110 | L13: =K13/C13*100 -> 20.650042 | M13: 147 | N13: ✓ Final | O13: Stärkstes Monatsergebnis YTD. Umsatz 107.070€, EBIT 22.110€ (20,7% Marge). Zielpfad Q4 liegt im grünen Bereich. | P13: IST
A14: Okt | B14: PLAN | C14: 110000 | D14: 123200 | E14: =(C14-D14)/D14*100 -> -10.714286 | F14: 37000 | G14: =C14-F14 -> 73000 | H14: =G14/C14*100 -> 66.363636 | I14: 24000 | J14: 26500 | K14: =G14-I14-J14 -> 22500 | L14: =K14/C14*100 -> 20.454545 | M14: 142 | N14: ⚡ Plan | O14: Planwert Basis-Szenario: 2.7% Wachstum vs. Vormonat. | P14: Basis
A15: Nov | B15: PLAN | C15: 113000 | D15: 126560 | E15: =(C15-D15)/D15*100 -> -10.714286 | F15: 38000 | G15: =C15-F15 -> 75000 | H15: =G15/C15*100 -> 66.371681 | I15: 24000 | J15: 27000 | K15: =G15-I15-J15 -> 24000 | L15: =K15/C15*100 -> 21.238938 | M15: 144 | N15: ⚡ Plan | O15: Planwert Basis-Szenario: 2.7% Wachstum vs. Vormonat. | P15: Basis
A16: Dez | B16: PLAN | C16: 118000 | D16: 132160 | E16: =(C16-D16)/D16*100 -> -10.714286 | F16: 40000 | G16: =C16-F16 -> 78000 | H16: =G16/C16*100 -> 66.101695 | I16: 24500 | J16: 28000 | K16: =G16-I16-J16 -> 25500 | L16: =K16/C16*100 -> 21.610169 | M16: 146 | N16: ⚡ Plan | O16: Planwert Basis-Szenario: 4.4% Wachstum vs. Vormonat. | P16: Basis
A17: JAHRES-GESAMT 2025 (IST + PLAN) | C17: =SUM(C5:C16) -> 1239460 | D17: =SUM(D5:D16) -> 1388195 | F17: =SUM(F5:F16) -> 418500 | G17: =SUM(G5:G16) -> 820960 | H17: =G17/C17*100 -> 66.235296 | I17: =SUM(I5:I16) -> 275500 | J17: =SUM(J5:J16) -> 278849 | K17: =SUM(K5:K16) -> 266611 | L17: =K17/C17*100 -> 21.510254

Sheet 10_Kostenstruktur
A1: 💸 KOSTENSTRUKTUR — Analyse nach Kostenart, Kostenstelle & Monat
A3: KOSTENARTEN — Monatliche Entwicklung (€ und % vom Umsatz)
A4: Monat | B4: Umsatz | C4: Wareneinsatz | D4: WE-% | E4: Personal | F4: Pers-% | G4: Sonstige | H4: Sons-% | I4: Gesamtkosten | J4: Gesamtkostenquote%
A5: Jan | B5: 92300 | C5: 31000 | D5: =C5/B5*100 -> 33.586132 | E5: 22000 | F5: =E5/B5*100 -> 23.83532 | G5: 17270 | H5: =G5/B5*100 -> 18.710726 | I5: =C5+E5+G5 -> 70270 | J5: =I5/B5*100 -> 76.132178
A6: Feb | B6: 95550 | C6: 32000 | D6: =C6/B6*100 -> 33.490319 | E6: 22000 | F6: =E6/B6*100 -> 23.024594 | G6: 19465 | H6: =G6/B6*100 -> 20.371533 | I6: =C6+E6+G6 -> 73465 | J6: =I6/B6*100 -> 76.886447
A7: Mär | B7: 100100 | C7: 33500 | D7: =C7/B7*100 -> 33.466533 | E7: 22500 | F7: =E7/B7*100 -> 22.477522 | G7: 22930 | H7: =G7/B7*100 -> 22.907093 | I7: =C7+E7+G7 -> 78930 | J7: =I7/B7*100 -> 78.851149
A8: Apr | B8: 93780 | C8: 32000 | D8: =C8/B8*100 -> 34.122414 | E8: 22000 | F8: =E8/B8*100 -> 23.45916 | G8: 18432 | H8: =G8/B8*100 -> 19.654511 | I8: =C8+E8+G8 -> 72432 | J8: =I8/B8*100 -> 77.236084
A9: Mai | B9: 100300 | C9: 34000 | D9: =C9/B9*100 -> 33.898305 | E9: 22500 | F9: =E9/B9*100 -> 22.432702 | G9: 22408 | H9: =G9/B9*100 -> 22.340977 | I9: =C9+E9+G9 -> 78908 | J9: =I9/B9*100 -> 78.671984
A10: Jun | B10: 103600 | C10: 35000 | D10: =C10/B10*100 -> 33.783784 | E10: 23000 | F10: =E10/B10*100 -> 22.200772 | G10: 23865 | H10: =G10/B10*100 -> 23.035714 | I10: =C10+E10+G10 -> 81865 | J10: =I10/B10*100 -> 79.02027
A11: Jul | B11: 101190 | C11: 34500 | D11: =C11/B11*100 -> 34.094278 | E11: 22500 | F11: =E11/B11*100 -> 22.235399 | G11: 23027 | H11: =G11/B11*100 -> 22.756201 | I11: =C11+E11+G11 -> 80027 | J11: =I11/B11*100 -> 79.085878
A12: Aug | B12: 104570 | C12: 35500 | D12: =C12/B12*100 -> 33.948551 | E12: 23000 | F12: =E12/B12*100 -> 21.994836 | G12: 24492 | H12: =G12/B12*100 -> 23.421631 | I12: =C12+E12+G12 -> 82992 | J12: =I12/B12*100 -> 79.365019
A13: Sep | B13: 107070 | C13: 36000 | D13: =C13/B13*100 -> 33.622864 | E13: 23500 | F13: =E13/B13*100 -> 21.948258 | G13: 25460 | H13: =G13/B13*100 -> 23.778836 | I13: =C13+E13+G13 -> 84960 | J13: =I13/B13*100 -> 79.349958
A14: GESAMT YTD | B14: =SUM(B5:B13) -> 898460 | C14: =SUM(C5:C13) -> 303500 | D14: =C14/B14*100 -> 33.780024 | E14: =SUM(E5:E13) -> 203000 | F14: =E14/B14*100 -> 22.594217 | G14: =SUM(G5:G13) -> 197349 | H14: =G14/B14*100 -> 21.965252 | I14: =SUM(I5:I13) -> 703849 | J14: =I14/B14*100 -> 78.339492
A16: KOSTENSTELLEN-ANALYSE — Monat September 2025
A17: Kostenstelle | B17: Team | C17: Personalkosten | D17: Anteil% | E17: Umsatzbeitrag (est.) | F17: Deckungs-Beitrag est. | G17: Effizienz-Score | H17: Trend | I17: KI-Bewertung | J17: Priorität
A18: IT | B18: Dev + Support | C18: 9500 | D18: 41.3 | E18: 38000 | F18: 28500 | G18: Mittel | H18: ➡ Stabil | I18: Stabile Kostenbasis. Support-Auslastung prüfen. | J18: 🟡
A19: Sales | B19: Beratung | C19: 6100 | D19: 26.5 | E19: 55000 | F19: 48900 | G19: Hoch | H19: ▲ Wachsend | I19: Höchste Umsatzeffizienz. Kapazität skalieren? | J19: 🟢
A20: Finance | B20: Buchhaltung | C20: 4800 | D20: 20.9 | E20: 0 | F20: -4800 | G20: Intern | H20: ➡ Stabil | I20: Cost Center. Prozess-Automatisierung prüfen. | J20: 🟡
A21: Extern | B21: Dienstleister | C21: 3100 | D21: 13.5 | E21: 14070 | F21: 10970 | G21: Mittel | H21: ▲ Steigend | I21: Anstieg Sonstigenkosten – Vertrag analysieren. | J21: 🔴

Sheet GuV_Struktur
A1: 📊 GEWINN- UND VERLUSTRECHNUNG (GuV) — SUMIFS aus Rohdaten-Import · Mustermann GmbH · 2025
A2: # | B2: GuV-Position | C2: Jan | D2: Feb | E2: Mär | F2: Apr | G2: Mai | H2: Jun | I2: Jul | J2: Aug | K2: Sep | L2: Okt | M2: Nov | N2: Dez | O2: YTD 2025
A3: 1 | B3: Umsatzerlöse | C3: =IFERROR(SUMIFS('01_Saldenlisten_Import'!$J:$J,'01_Saldenlisten_Import'!$A:$A,"2025-01",'01_Saldenlisten_Import'!$B:$B,"Mustermann GmbH",'01_Saldenlisten_Import'!$F:$F,"Umsatz"),0) -> 92300 | D3: =IFERROR(SUMIFS('01_Saldenlisten_Import'!$J:$J,'01_Saldenlisten_Import'!$A:$A,"2025-02",'01_Saldenlisten_Import'!$B:$B,"Mustermann GmbH",'01_Saldenlisten_Import'!$F:$F,"Umsatz"),0) -> 95550 | E3: =IFERROR(SUMIFS('01_Saldenlisten_Import'!$J:$J,'01_Saldenlisten_Import'!$A:$A,"2025-03",'01_Saldenlisten_Import'!$B:$B,"Mustermann GmbH",'01_Saldenlisten_Import'!$F:$F,"Umsatz"),0) -> 100100 | F3: =IFERROR(SUMIFS('01_Saldenlisten_Import'!$J:$J,'01_Saldenlisten_Import'!$A:$A,"2025-04",'01_Saldenlisten_Import'!$B:$B,"Mustermann GmbH",'01_Saldenlisten_Import'!$F:$F,"Umsatz"),0) -> 93780 | G3: =IFERROR(SUMIFS('01_Saldenlisten_Import'!$J:$J,'01_Saldenlisten_Import'!$A:$A,"2025-05",'01_Saldenlisten_Import'!$B:$B,"Mustermann GmbH",'01_Saldenlisten_Import'!$F:$F,"Umsatz"),0) -> 100300 | H3: =IFERROR(SUMIFS('01_Saldenlisten_Import'!$J:$J,'01_Saldenlisten_Import'!$A:$A,"2025-06",'01_Saldenlisten_Import'!$B:$B,"Mustermann GmbH",'01_Saldenlisten_Import'!$F:$F,"Umsatz"),0) -> 103600 | I3: =IFERROR(SUMIFS('01_Saldenlisten_Import'!$J:$J,'01_Saldenlisten_Import'!$A:$A,"2025-07",'01_Saldenlisten_Import'!$B:$B,"Mustermann GmbH",'01_Saldenlisten_Import'!$F:$F,"Umsatz"),0) -> 101190 | J3: =IFERROR(SUMIFS('01_Saldenlisten_Import'!$J:$J,'01_Saldenlisten_Import'!$A:$A,"2025-08",'01_Saldenlisten_Import'!$B:$B,"Mustermann GmbH",'01_Saldenlisten_Import'!$F:$F,"Umsatz"),0) -> 104570 | K3: =IFERROR(SUMIFS('01_Saldenlisten_Import'!$J:$J,'01_Saldenlisten_Import'!$A:$A,"2025-09",'01_Saldenlisten_Import'!$B:$B,"Mustermann GmbH",'01_Saldenlisten_Import'!$F:$F,"Umsatz"),0) -> 107070 | L3: =IFERROR(SUMIFS('01_Saldenlisten_Import'!$J:$J,'01_Saldenlisten_Import'!$A:$A,"2025-10",'01_Saldenlisten_Import'!$B:$B,"Mustermann GmbH",'01_Saldenlisten_Import'!$F:$F,"Umsatz"),0) -> 110000 | M3: =IFERROR(SUMIFS('01_Saldenlisten_Import'!$J:$J,'01_Saldenlisten_Import'!$A:$A,"2025-11",'01_Saldenlisten_Import'!$B:$B,"Mustermann GmbH",'01_Saldenlisten_Import'!$F:$F,"Umsatz"),0) -> 113000 | N3: =IFERROR(SUMIFS('01_Saldenlisten_Import'!$J:$J,'01_Saldenlisten_Import'!$A:$A,"2025-12",'01_Saldenlisten_Import'!$B:$B,"Mustermann GmbH",'01_Saldenlisten_Import'!$F:$F,"Umsatz"),0) -> 118000 | O3: =IFERROR(SUM(C3:N3),0) -> 1239460
A4: 1a | B4: + Sonstige Erlöse | C4: =IFERROR(SUMIFS('01_Saldenlisten_Import'!$J:$J,'01_Saldenlisten_Import'!$A:$A,"2025-01",'01_Saldenlisten_Import'!$B:$B,"Mustermann GmbH",'01_Saldenlisten_Import'!$F:$F,"Sonstige Erlöse"),0) -> 0 | D4: =IFERROR(SUMIFS('01_Saldenlisten_Import'!$J:$J,'01_Saldenlisten_Import'!$A:$A,"2025-02",'01_Saldenlisten_Import'!$B:$B,"Mustermann GmbH",'01_Saldenlisten_Import'!$F:$F,"Sonstige Erlöse"),0) -> 0 | E4: =IFERROR(SUMIFS('01_Saldenlisten_Import'!$J:$J,'01_Saldenlisten_Import'!$A:$A,"2025-03",'01_Saldenlisten_Import'!$B:$B,"Mustermann GmbH",'01_Saldenlisten_Import'!$F:$F,"Sonstige Erlöse"),0) -> 0 | F4: =IFERROR(SUMIFS('01_Saldenlisten_Import'!$J:$J,'01_Saldenlisten_Import'!$A:$A,"2025-04",'01_Saldenlisten_Import'!$B:$B,"Mustermann GmbH",'01_Saldenlisten_Import'!$F:$F,"Sonstige Erlöse"),0) -> 0 | G4: =IFERROR(SUMIFS('01_Saldenlisten_Import'!$J:$J,'01_Saldenlisten_Import'!$A:$A,"2025-05",'01_Saldenlisten_Import'!$B:$B,"Mustermann GmbH",'01_Saldenlisten_Import'!$F:$F,"Sonstige Erlöse"),0) -> 0 | H4: =IFERROR(SUMIFS('01_Saldenlisten_Import'!$J:$J,'01_Saldenlisten_Import'!$A:$A,"2025-06",'01_Saldenlisten_Import'!$B:$B,"Mustermann GmbH",'01_Saldenlisten_Import'!$F:$F,"Sonstige Erlöse"),0) -> 0 | I4: =IFERROR(SUMIFS('01_Saldenlisten_Import'!$J:$J,'01_Saldenlisten_Import'!$A:$A,"2025-07",'01_Saldenlisten_Import'!$B:$B,"Mustermann GmbH",'01_Saldenlisten_Import'!$F:$F,"Sonstige Erlöse"),0) -> 0 | J4: =IFERROR(SUMIFS('01_Saldenlisten_Import'!$J:$J,'01_Saldenlisten_Import'!$A:$A,"2025-08",'01_Saldenlisten_Import'!$B:$B,"Mustermann GmbH",'01_Saldenlisten_Import'!$F:$F,"Sonstige Erlöse"),0) -> 0 | K4: =IFERROR(SUMIFS('01_Saldenlisten_Import'!$J:$J,'01_Saldenlisten_Import'!$A:$A,"2025-09",'01_Saldenlisten_Import'!$B:$B,"Mustermann GmbH",'01_Saldenlisten_Import'!$F:$F,"Sonstige Erlöse"),0) -> 0 | L4: =IFERROR(SUMIFS('01_Saldenlisten_Import'!$J:$J,'01_Saldenlisten_Import'!$A:$A,"2025-10",'01_Saldenlisten_Import'!$B:$B,"Mustermann GmbH",'01_Saldenlisten_Import'!$F:$F,"Sonstige Erlöse"),0) -> 0 | M4: =IFERROR(SUMIFS('01_Saldenlisten_Import'!$J:$J,'01_Saldenlisten_Import'!$A:$A,"2025-11",'01_Saldenlisten_Import'!$B:$B,"Mustermann GmbH",'01_Saldenlisten_Import'!$F:$F,"Sonstige Erlöse"),0) -> 0 | N4: =IFERROR(SUMIFS('01_Saldenlisten_Import'!$J:$J,'01_Saldenlisten_Import'!$A:$A,"2025-12",'01_Saldenlisten_Import'!$B:$B,"Mustermann GmbH",'01_Saldenlisten_Import'!$F:$F,"Sonstige Erlöse"),0) -> 0 | O4: =IFERROR(SUM(C4:N4),0) -> 0
A5: 1b | B5: = Gesamtleistung | C5: =C3+C4 -> 92300 | D5: =D3+D4 -> 95550 | E5: =E3+E4 -> 100100 | F5: =F3+F4 -> 93780 | G5: =G3+G4 -> 100300 | H5: =H3+H4 -> 103600 | I5: =I3+I4 -> 101190 | J5: =J3+J4 -> 104570 | ... N5: =N3+N4 -> 118000 | O5: =IFERROR(SUM(C5:N5),0) -> 1239460
A7: 2 | B7: - Wareneinsatz / Materialeinsatz | C7: =IFERROR(SUMIFS('01_Saldenlisten_Import'!$J:$J,'01_Saldenlisten_Import'!$A:$A,"2025-01",'01_Saldenlisten_Import'!$B:$B,"Mustermann GmbH",'01_Saldenlisten_Import'!$F:$F,"Wareneinsatz"),0) -> 31000 | D7: =IFERROR(SUMIFS('01_Saldenlisten_Import'!$J:$J,'01_Saldenlisten_Import'!$A:$A,"2025-02",'01_Saldenlisten_Import'!$B:$B,"Mustermann GmbH",'01_Saldenlisten_Import'!$F:$F,"Wareneinsatz"),0) -> 32000 | E7: =IFERROR(SUMIFS('01_Saldenlisten_Import'!$J:$J,'01_Saldenlisten_Import'!$A:$A,"2025-03",'01_Saldenlisten_Import'!$B:$B,"Mustermann GmbH",'01_Saldenlisten_Import'!$F:$F,"Wareneinsatz"),0) -> 33500 | F7: =IFERROR(SUMIFS('01_Saldenlisten_Import'!$J:$J,'01_Saldenlisten_Import'!$A:$A,"2025-04",'01_Saldenlisten_Import'!$B:$B,"Mustermann GmbH",'01_Saldenlisten_Import'!$F:$F,"Wareneinsatz"),0) -> 32000 | G7: =IFERROR(SUMIFS('01_Saldenlisten_Import'!$J:$J,'01_Saldenlisten_Import'!$A:$A,"2025-05",'01_Saldenlisten_Import'!$B:$B,"Mustermann GmbH",'01_Saldenlisten_Import'!$F:$F,"Wareneinsatz"),0) -> 34000 | H7: =IFERROR(SUMIFS('01_Saldenlisten_Import'!$J:$J,'01_Saldenlisten_Import'!$A:$A,"2025-06",'01_Saldenlisten_Import'!$B:$B,"Mustermann GmbH",'01_Saldenlisten_Import'!$F:$F,"Wareneinsatz"),0) -> 35000 | I7: =IFERROR(SUMIFS('01_Saldenlisten_Import'!$J:$J,'01_Saldenlisten_Import'!$A:$A,"2025-07",'01_Saldenlisten_Import'!$B:$B,"Mustermann GmbH",'01_Saldenlisten_Import'!$F:$F,"Wareneinsatz"),0) -> 34500 | J7: =IFERROR(SUMIFS('01_Saldenlisten_Import'!$J:$J,'01_Saldenlisten_Import'!$A:$A,"2025-08",'01_Saldenlisten_Import'!$B:$B,"Mustermann GmbH",'01_Saldenlisten_Import'!$F:$F,"Wareneinsatz"),0) -> 35500 | K7: =IFERROR(SUMIFS('01_Saldenlisten_Import'!$J:$J,'01_Saldenlisten_Import'!$A:$A,"2025-09",'01_Saldenlisten_Import'!$B:$B,"Mustermann GmbH",'01_Saldenlisten_Import'!$F:$F,"Wareneinsatz"),0) -> 36000 | L7: =IFERROR(SUMIFS('01_Saldenlisten_Import'!$J:$J,'01_Saldenlisten_Import'!$A:$A,"2025-10",'01_Saldenlisten_Import'!$B:$B,"Mustermann GmbH",'01_Saldenlisten_Import'!$F:$F,"Wareneinsatz"),0) -> 37000 | M7: =IFERROR(SUMIFS('01_Saldenlisten_Import'!$J:$J,'01_Saldenlisten_Import'!$A:$A,"2025-11",'01_Saldenlisten_Import'!$B:$B,"Mustermann GmbH",'01_Saldenlisten_Import'!$F:$F,"Wareneinsatz"),0) -> 38000 | N7: =IFERROR(SUMIFS('01_Saldenlisten_Import'!$J:$J,'01_Saldenlisten_Import'!$A:$A,"2025-12",'01_Saldenlisten_Import'!$B:$B,"Mustermann GmbH",'01_Saldenlisten_Import'!$F:$F,"Wareneinsatz"),0) -> 40000 | O7: =IFERROR(SUM(C7:N7),0) -> 418500
A8: 2a | B8: - Fremdleistungen | C8: =IFERROR(SUMIFS('01_Saldenlisten_Import'!$J:$J,'01_Saldenlisten_Import'!$A:$A,"2025-01",'01_Saldenlisten_Import'!$B:$B,"Mustermann GmbH",'01_Saldenlisten_Import'!$F:$F,"Fremdleistungen"),0) -> 0 | D8: =IFERROR(SUMIFS('01_Saldenlisten_Import'!$J:$J,'01_Saldenlisten_Import'!$A:$A,"2025-02",'01_Saldenlisten_Import'!$B:$B,"Mustermann GmbH",'01_Saldenlisten_Import'!$F:$F,"Fremdleistungen"),0) -> 0 | E8: =IFERROR(SUMIFS('01_Saldenlisten_Import'!$J:$J,'01_Saldenlisten_Import'!$A:$A,"2025-03",'01_Saldenlisten_Import'!$B:$B,"Mustermann GmbH",'01_Saldenlisten_Import'!$F:$F,"Fremdleistungen"),0) -> 0 | F8: =IFERROR(SUMIFS('01_Saldenlisten_Import'!$J:$J,'01_Saldenlisten_Import'!$A:$A,"2025-04",'01_Saldenlisten_Import'!$B:$B,"Mustermann GmbH",'01_Saldenlisten_Import'!$F:$F,"Fremdleistungen"),0) -> 0 | G8: =IFERROR(SUMIFS('01_Saldenlisten_Import'!$J:$J,'01_Saldenlisten_Import'!$A:$A,"2025-05",'01_Saldenlisten_Import'!$B:$B,"Mustermann GmbH",'01_Saldenlisten_Import'!$F:$F,"Fremdleistungen"),0) -> 0 | H8: =IFERROR(SUMIFS('01_Saldenlisten_Import'!$J:$J,'01_Saldenlisten_Import'!$A:$A,"2025-06",'01_Saldenlisten_Import'!$B:$B,"Mustermann GmbH",'01_Saldenlisten_Import'!$F:$F,"Fremdleistungen"),0) -> 0 | I8: =IFERROR(SUMIFS('01_Saldenlisten_Import'!$J:$J,'01_Saldenlisten_Import'!$A:$A,"2025-07",'01_Saldenlisten_Import'!$B:$B,"Mustermann GmbH",'01_Saldenlisten_Import'!$F:$F,"Fremdleistungen"),0) -> 0 | J8: =IFERROR(SUMIFS('01_Saldenlisten_Import'!$J:$J,'01_Saldenlisten_Import'!$A:$A,"2025-08",'01_Saldenlisten_Import'!$B:$B,"Mustermann GmbH",'01_Saldenlisten_Import'!$F:$F,"Fremdleistungen"),0) -> 0 | K8: =IFERROR(SUMIFS('01_Saldenlisten_Import'!$J:$J,'01_Saldenlisten_Import'!$A:$A,"2025-09",'01_Saldenlisten_Import'!$B:$B,"Mustermann GmbH",'01_Saldenlisten_Import'!$F:$F,"Fremdleistungen"),0) -> 0 | L8: =IFERROR(SUMIFS('01_Saldenlisten_Import'!$J:$J,'01_Saldenlisten_Import'!$A:$A,"2025-10",'01_Saldenlisten_Import'!$B:$B,"Mustermann GmbH",'01_Saldenlisten_Import'!$F:$F,"Fremdleistungen"),0) -> 0 | M8: =IFERROR(SUMIFS('01_Saldenlisten_Import'!$J:$J,'01_Saldenlisten_Import'!$A:$A,"2025-11",'01_Saldenlisten_Import'!$B:$B,"Mustermann GmbH",'01_Saldenlisten_Import'!$F:$F,"Fremdleistungen"),0) -> 0 | N8: =IFERROR(SUMIFS('01_Saldenlisten_Import'!$J:$J,'01_Saldenlisten_Import'!$A:$A,"2025-12",'01_Saldenlisten_Import'!$B:$B,"Mustermann GmbH",'01_Saldenlisten_Import'!$F:$F,"Fremdleistungen"),0) -> 0 | O8: =IFERROR(SUM(C8:N8),0) -> 0
B9: = Rohertrag (DB I) | C9: =C5-C7-C8 -> 61300 | D9: =D5-D7-D8 -> 63550 | E9: =E5-E7-E8 -> 66600 | F9: =F5-F7-F8 -> 61780 | G9: =G5-G7-G8 -> 66300 | H9: =H5-H7-H8 -> 68600 | I9: =I5-I7-I8 -> 66690 | J9: =J5-J7-J8 -> 69070 | ... N9: =N5-N7-N8 -> 78000 | O9: =IFERROR(SUM(C9:N9),0) -> 820960
A11: 3 | B11: - Personalaufwand | C11: =IFERROR(SUMIFS('01_Saldenlisten_Import'!$J:$J,'01_Saldenlisten_Import'!$A:$A,"2025-01",'01_Saldenlisten_Import'!$B:$B,"Mustermann GmbH",'01_Saldenlisten_Import'!$F:$F,"Personal"),0) -> 22000 | D11: =IFERROR(SUMIFS('01_Saldenlisten_Import'!$J:$J,'01_Saldenlisten_Import'!$A:$A,"2025-02",'01_Saldenlisten_Import'!$B:$B,"Mustermann GmbH",'01_Saldenlisten_Import'!$F:$F,"Personal"),0) -> 22000 | E11: =IFERROR(SUMIFS('01_Saldenlisten_Import'!$J:$J,'01_Saldenlisten_Import'!$A:$A,"2025-03",'01_Saldenlisten_Import'!$B:$B,"Mustermann GmbH",'01_Saldenlisten_Import'!$F:$F,"Personal"),0) -> 22500 | F11: =IFERROR(SUMIFS('01_Saldenlisten_Import'!$J:$J,'01_Saldenlisten_Import'!$A:$A,"2025-04",'01_Saldenlisten_Import'!$B:$B,"Mustermann GmbH",'01_Saldenlisten_Import'!$F:$F,"Personal"),0) -> 22000 | G11: =IFERROR(SUMIFS('01_Saldenlisten_Import'!$J:$J,'01_Saldenlisten_Import'!$A:$A,"2025-05",'01_Saldenlisten_Import'!$B:$B,"Mustermann GmbH",'01_Saldenlisten_Import'!$F:$F,"Personal"),0) -> 22500 | H11: =IFERROR(SUMIFS('01_Saldenlisten_Import'!$J:$J,'01_Saldenlisten_Import'!$A:$A,"2025-06",'01_Saldenlisten_Import'!$B:$B,"Mustermann GmbH",'01_Saldenlisten_Import'!$F:$F,"Personal"),0) -> 23000 | I11: =IFERROR(SUMIFS('01_Saldenlisten_Import'!$J:$J,'01_Saldenlisten_Import'!$A:$A,"2025-07",'01_Saldenlisten_Import'!$B:$B,"Mustermann GmbH",'01_Saldenlisten_Import'!$F:$F,"Personal"),0) -> 22500 | J11: =IFERROR(SUMIFS('01_Saldenlisten_Import'!$J:$J,'01_Saldenlisten_Import'!$A:$A,"2025-08",'01_Saldenlisten_Import'!$B:$B,"Mustermann GmbH",'01_Saldenlisten_Import'!$F:$F,"Personal"),0) -> 23000 | K11: =IFERROR(SUMIFS('01_Saldenlisten_Import'!$J:$J,'01_Saldenlisten_Import'!$A:$A,"2025-09",'01_Saldenlisten_Import'!$B:$B,"Mustermann GmbH",'01_Saldenlisten_Import'!$F:$F,"Personal"),0) -> 23500 | L11: =IFERROR(SUMIFS('01_Saldenlisten_Import'!$J:$J,'01_Saldenlisten_Import'!$A:$A,"2025-10",'01_Saldenlisten_Import'!$B:$B,"Mustermann GmbH",'01_Saldenlisten_Import'!$F:$F,"Personal"),0) -> 24000 | M11: =IFERROR(SUMIFS('01_Saldenlisten_Import'!$J:$J,'01_Saldenlisten_Import'!$A:$A,"2025-11",'01_Saldenlisten_Import'!$B:$B,"Mustermann GmbH",'01_Saldenlisten_Import'!$F:$F,"Personal"),0) -> 24000 | N11: =IFERROR(SUMIFS('01_Saldenlisten_Import'!$J:$J,'01_Saldenlisten_Import'!$A:$A,"2025-12",'01_Saldenlisten_Import'!$B:$B,"Mustermann GmbH",'01_Saldenlisten_Import'!$F:$F,"Personal"),0) -> 24500 | O11: =IFERROR(SUM(C11:N11),0) -> 275500
A12: 4 | B12: - Raumkosten | C12: =IFERROR(SUMIFS('01_Saldenlisten_Import'!$J:$J,'01_Saldenlisten_Import'!$A:$A,"2025-01",'01_Saldenlisten_Import'!$B:$B,"Mustermann GmbH",'01_Saldenlisten_Import'!$F:$F,"Raumkosten"),0) -> 4200 | D12: =IFERROR(SUMIFS('01_Saldenlisten_Import'!$J:$J,'01_Saldenlisten_Import'!$A:$A,"2025-02",'01_Saldenlisten_Import'!$B:$B,"Mustermann GmbH",'01_Saldenlisten_Import'!$F:$F,"Raumkosten"),0) -> 4200 | E12: =IFERROR(SUMIFS('01_Saldenlisten_Import'!$J:$J,'01_Saldenlisten_Import'!$A:$A,"2025-03",'01_Saldenlisten_Import'!$B:$B,"Mustermann GmbH",'01_Saldenlisten_Import'!$F:$F,"Raumkosten"),0) -> 4250 | F12: =IFERROR(SUMIFS('01_Saldenlisten_Import'!$J:$J,'01_Saldenlisten_Import'!$A:$A,"2025-04",'01_Saldenlisten_Import'!$B:$B,"Mustermann GmbH",'01_Saldenlisten_Import'!$F:$F,"Raumkosten"),0) -> 4300 | G12: =IFERROR(SUMIFS('01_Saldenlisten_Import'!$J:$J,'01_Saldenlisten_Import'!$A:$A,"2025-05",'01_Saldenlisten_Import'!$B:$B,"Mustermann GmbH",'01_Saldenlisten_Import'!$F:$F,"Raumkosten"),0) -> 4300 | H12: =IFERROR(SUMIFS('01_Saldenlisten_Import'!$J:$J,'01_Saldenlisten_Import'!$A:$A,"2025-06",'01_Saldenlisten_Import'!$B:$B,"Mustermann GmbH",'01_Saldenlisten_Import'!$F:$F,"Raumkosten"),0) -> 4400 | I12: =IFERROR(SUMIFS('01_Saldenlisten_Import'!$J:$J,'01_Saldenlisten_Import'!$A:$A,"2025-07",'01_Saldenlisten_Import'!$B:$B,"Mustermann GmbH",'01_Saldenlisten_Import'!$F:$F,"Raumkosten"),0) -> 4400 | J12: =IFERROR(SUMIFS('01_Saldenlisten_Import'!$J:$J,'01_Saldenlisten_Import'!$A:$A,"2025-08",'01_Saldenlisten_Import'!$B:$B,"Mustermann GmbH",'01_Saldenlisten_Import'!$F:$F,"Raumkosten"),0) -> 4500 | K12: =IFERROR(SUMIFS('01_Saldenlisten_Import'!$J:$J,'01_Saldenlisten_Import'!$A:$A,"2025-09",'01_Saldenlisten_Import'!$B:$B,"Mustermann GmbH",'01_Saldenlisten_Import'!$F:$F,"Raumkosten"),0) -> 4500 | L12: =IFERROR(SUMIFS('01_Saldenlisten_Import'!$J:$J,'01_Saldenlisten_Import'!$A:$A,"2025-10",'01_Saldenlisten_Import'!$B:$B,"Mustermann GmbH",'01_Saldenlisten_Import'!$F:$F,"Raumkosten"),0) -> 4500 | M12: =IFERROR(SUMIFS('01_Saldenlisten_Import'!$J:$J,'01_Saldenlisten_Import'!$A:$A,"2025-11",'01_Saldenlisten_Import'!$B:$B,"Mustermann GmbH",'01_Saldenlisten_Import'!$F:$F,"Raumkosten"),0) -> 4600 | N12: =IFERROR(SUMIFS('01_Saldenlisten_Import'!$J:$J,'01_Saldenlisten_Import'!$A:$A,"2025-12",'01_Saldenlisten_Import'!$B:$B,"Mustermann GmbH",'01_Saldenlisten_Import'!$F:$F,"Raumkosten"),0) -> 4600 | O12: =IFERROR(SUM(C12:N12),0) -> 52750
A13: 5 | B13: - Kfz-Kosten | C13: =IFERROR(SUMIFS('01_Saldenlisten_Import'!$J:$J,'01_Saldenlisten_Import'!$A:$A,"2025-01",'01_Saldenlisten_Import'!$B:$B,"Mustermann GmbH",'01_Saldenlisten_Import'!$F:$F,"Kfz-Kosten"),0) -> 0 | D13: =IFERROR(SUMIFS('01_Saldenlisten_Import'!$J:$J,'01_Saldenlisten_Import'!$A:$A,"2025-02",'01_Saldenlisten_Import'!$B:$B,"Mustermann GmbH",'01_Saldenlisten_Import'!$F:$F,"Kfz-Kosten"),0) -> 0 | E13: =IFERROR(SUMIFS('01_Saldenlisten_Import'!$J:$J,'01_Saldenlisten_Import'!$A:$A,"2025-03",'01_Saldenlisten_Import'!$B:$B,"Mustermann GmbH",'01_Saldenlisten_Import'!$F:$F,"Kfz-Kosten"),0) -> 0 | F13: =IFERROR(SUMIFS('01_Saldenlisten_Import'!$J:$J,'01_Saldenlisten_Import'!$A:$A,"2025-04",'01_Saldenlisten_Import'!$B:$B,"Mustermann GmbH",'01_Saldenlisten_Import'!$F:$F,"Kfz-Kosten"),0) -> 0 | G13: =IFERROR(SUMIFS('01_Saldenlisten_Import'!$J:$J,'01_Saldenlisten_Import'!$A:$A,"2025-05",'01_Saldenlisten_Import'!$B:$B,"Mustermann GmbH",'01_Saldenlisten_Import'!$F:$F,"Kfz-Kosten"),0) -> 0 | H13: =IFERROR(SUMIFS('01_Saldenlisten_Import'!$J:$J,'01_Saldenlisten_Import'!$A:$A,"2025-06",'01_Saldenlisten_Import'!$B:$B,"Mustermann GmbH",'01_Saldenlisten_Import'!$F:$F,"Kfz-Kosten"),0) -> 0 | I13: =IFERROR(SUMIFS('01_Saldenlisten_Import'!$J:$J,'01_Saldenlisten_Import'!$A:$A,"2025-07",'01_Saldenlisten_Import'!$B:$B,"Mustermann GmbH",'01_Saldenlisten_Import'!$F:$F,"Kfz-Kosten"),0) -> 0 | J13: =IFERROR(SUMIFS('01_Saldenlisten_Import'!$J:$J,'01_Saldenlisten_Import'!$A:$A,"2025-08",'01_Saldenlisten_Import'!$B:$B,"Mustermann GmbH",'01_Saldenlisten_Import'!$F:$F,"Kfz-Kosten"),0) -> 0 | K13: =IFERROR(SUMIFS('01_Saldenlisten_Import'!$J:$J,'01_Saldenlisten_Import'!$A:$A,"2025-09",'01_Saldenlisten_Import'!$B:$B,"Mustermann GmbH",'01_Saldenlisten_Import'!$F:$F,"Kfz-Kosten"),0) -> 0 | L13: =IFERROR(SUMIFS('01_Saldenlisten_Import'!$J:$J,'01_Saldenlisten_Import'!$A:$A,"2025-10",'01_Saldenlisten_Import'!$B:$B,"Mustermann GmbH",'01_Saldenlisten_Import'!$F:$F,"Kfz-Kosten"),0) -> 0 | M13: =IFERROR(SUMIFS('01_Saldenlisten_Import'!$J:$J,'01_Saldenlisten_Import'!$A:$A,"2025-11",'01_Saldenlisten_Import'!$B:$B,"Mustermann GmbH",'01_Saldenlisten_Import'!$F:$F,"Kfz-Kosten"),0) -> 0 | N13: =IFERROR(SUMIFS('01_Saldenlisten_Import'!$J:$J,'01_Saldenlisten_Import'!$A:$A,"2025-12",'01_Saldenlisten_Import'!$B:$B,"Mustermann GmbH",'01_Saldenlisten_Import'!$F:$F,"Kfz-Kosten"),0) -> 0 | O13: =IFERROR(SUM(C13:N13),0) -> 0
A14: 6 | B14: - Marketing & Werbung | C14: =IFERROR(SUMIFS('01_Saldenlisten_Import'!$J:$J,'01_Saldenlisten_Import'!$A:$A,"2025-01",'01_Saldenlisten_Import'!$B:$B,"Mustermann GmbH",'01_Saldenlisten_Import'!$F:$F,"Marketing"),0) -> 2800 | D14: =IFERROR(SUMIFS('01_Saldenlisten_Import'!$J:$J,'01_Saldenlisten_Import'!$A:$A,"2025-02",'01_Saldenlisten_Import'!$B:$B,"Mustermann GmbH",'01_Saldenlisten_Import'!$F:$F,"Marketing"),0) -> 0 | E14: =IFERROR(SUMIFS('01_Saldenlisten_Import'!$J:$J,'01_Saldenlisten_Import'!$A:$A,"2025-03",'01_Saldenlisten_Import'!$B:$B,"Mustermann GmbH",'01_Saldenlisten_Import'!$F:$F,"Marketing"),0) -> 3100 | F14: =IFERROR(SUMIFS('01_Saldenlisten_Import'!$J:$J,'01_Saldenlisten_Import'!$A:$A,"2025-04",'01_Saldenlisten_Import'!$B:$B,"Mustermann GmbH",'01_Saldenlisten_Import'!$F:$F,"Marketing"),0) -> 3300 | G14: =IFERROR(SUMIFS('01_Saldenlisten_Import'!$J:$J,'01_Saldenlisten_Import'!$A:$A,"2025-05",'01_Saldenlisten_Import'!$B:$B,"Mustermann GmbH",'01_Saldenlisten_Import'!$F:$F,"Marketing"),0) -> 3500 | H14: =IFERROR(SUMIFS('01_Saldenlisten_Import'!$J:$J,'01_Saldenlisten_Import'!$A:$A,"2025-06",'01_Saldenlisten_Import'!$B:$B,"Mustermann GmbH",'01_Saldenlisten_Import'!$F:$F,"Marketing"),0) -> 3600 | I14: =IFERROR(SUMIFS('01_Saldenlisten_Import'!$J:$J,'01_Saldenlisten_Import'!$A:$A,"2025-07",'01_Saldenlisten_Import'!$B:$B,"Mustermann GmbH",'01_Saldenlisten_Import'!$F:$F,"Marketing"),0) -> 3800 | J14: =IFERROR(SUMIFS('01_Saldenlisten_Import'!$J:$J,'01_Saldenlisten_Import'!$A:$A,"2025-08",'01_Saldenlisten_Import'!$B:$B,"Mustermann GmbH",'01_Saldenlisten_Import'!$F:$F,"Marketing"),0) -> 3900 | K14: =IFERROR(SUMIFS('01_Saldenlisten_Import'!$J:$J,'01_Saldenlisten_Import'!$A:$A,"2025-09",'01_Saldenlisten_Import'!$B:$B,"Mustermann GmbH",'01_Saldenlisten_Import'!$F:$F,"Marketing"),0) -> 4100 | L14: =IFERROR(SUMIFS('01_Saldenlisten_Import'!$J:$J,'01_Saldenlisten_Import'!$A:$A,"2025-10",'01_Saldenlisten_Import'!$B:$B,"Mustermann GmbH",'01_Saldenlisten_Import'!$F:$F,"Marketing"),0) -> 4300 | M14: =IFERROR(SUMIFS('01_Saldenlisten_Import'!$J:$J,'01_Saldenlisten_Import'!$A:$A,"2025-11",'01_Saldenlisten_Import'!$B:$B,"Mustermann GmbH",'01_Saldenlisten_Import'!$F:$F,"Marketing"),0) -> 4400 | N14: =IFERROR(SUMIFS('01_Saldenlisten_Import'!$J:$J,'01_Saldenlisten_Import'!$A:$A,"2025-12",'01_Saldenlisten_Import'!$B:$B,"Mustermann GmbH",'01_Saldenlisten_Import'!$F:$F,"Marketing"),0) -> 4600 | O14: =IFERROR(SUM(C14:N14),0) -> 41400
A15: 7 | B15: - Reisekosten | C15: =IFERROR(SUMIFS('01_Saldenlisten_Import'!$J:$J,'01_Saldenlisten_Import'!$A:$A,"2025-01",'01_Saldenlisten_Import'!$B:$B,"Mustermann GmbH",'01_Saldenlisten_Import'!$F:$F,"Reisekosten"),0) -> 0 | D15: =IFERROR(SUMIFS('01_Saldenlisten_Import'!$J:$J,'01_Saldenlisten_Import'!$A:$A,"2025-02",'01_Saldenlisten_Import'!$B:$B,"Mustermann GmbH",'01_Saldenlisten_Import'!$F:$F,"Reisekosten"),0) -> 0 | E15: =IFERROR(SUMIFS('01_Saldenlisten_Import'!$J:$J,'01_Saldenlisten_Import'!$A:$A,"2025-03",'01_Saldenlisten_Import'!$B:$B,"Mustermann GmbH",'01_Saldenlisten_Import'!$F:$F,"Reisekosten"),0) -> 0 | F15: =IFERROR(SUMIFS('01_Saldenlisten_Import'!$J:$J,'01_Saldenlisten_Import'!$A:$A,"2025-04",'01_Saldenlisten_Import'!$B:$B,"Mustermann GmbH",'01_Saldenlisten_Import'!$F:$F,"Reisekosten"),0) -> 0 | G15: =IFERROR(SUMIFS('01_Saldenlisten_Import'!$J:$J,'01_Saldenlisten_Import'!$A:$A,"2025-05",'01_Saldenlisten_Import'!$B:$B,"Mustermann GmbH",'01_Saldenlisten_Import'!$F:$F,"Reisekosten"),0) -> 0 | H15: =IFERROR(SUMIFS('01_Saldenlisten_Import'!$J:$J,'01_Saldenlisten_Import'!$A:$A,"2025-06",'01_Saldenlisten_Import'!$B:$B,"Mustermann GmbH",'01_Saldenlisten_Import'!$F:$F,"Reisekosten"),0) -> 0 | I15: =IFERROR(SUMIFS('01_Saldenlisten_Import'!$J:$J,'01_Saldenlisten_Import'!$A:$A,"2025-07",'01_Saldenlisten_Import'!$B:$B,"Mustermann GmbH",'01_Saldenlisten_Import'!$F:$F,"Reisekosten"),0) -> 0 | J15: =IFERROR(SUMIFS('01_Saldenlisten_Import'!$J:$J,'01_Saldenlisten_Import'!$A:$A,"2025-08",'01_Saldenlisten_Import'!$B:$B,"Mustermann GmbH",'01_Saldenlisten_Import'!$F:$F,"Reisekosten"),0) -> 0 | K15: =IFERROR(SUMIFS('01_Saldenlisten_Import'!$J:$J,'01_Saldenlisten_Import'!$A:$A,"2025-09",'01_Saldenlisten_Import'!$B:$B,"Mustermann GmbH",'01_Saldenlisten_Import'!$F:$F,"Reisekosten"),0) -> 0 | L15: =IFERROR(SUMIFS('01_Saldenlisten_Import'!$J:$J,'01_Saldenlisten_Import'!$A:$A,"2025-10",'01_Saldenlisten_Import'!$B:$B,"Mustermann GmbH",'01_Saldenlisten_Import'!$F:$F,"Reisekosten"),0) -> 0 | M15: =IFERROR(SUMIFS('01_Saldenlisten_Import'!$J:$J,'01_Saldenlisten_Import'!$A:$A,"2025-11",'01_Saldenlisten_Import'!$B:$B,"Mustermann GmbH",'01_Saldenlisten_Import'!$F:$F,"Reisekosten"),0) -> 0 | N15: =IFERROR(SUMIFS('01_Saldenlisten_Import'!$J:$J,'01_Saldenlisten_Import'!$A:$A,"2025-12",'01_Saldenlisten_Import'!$B:$B,"Mustermann GmbH",'01_Saldenlisten_Import'!$F:$F,"Reisekosten"),0) -> 0 | O15: =IFERROR(SUM(C15:N15),0) -> 0
A16: 8 | B16: - IT & Bürokosten | C16: =IFERROR(SUMIFS('01_Saldenlisten_Import'!$J:$J,'01_Saldenlisten_Import'!$A:$A,"2025-01",'01_Saldenlisten_Import'!$B:$B,"Mustermann GmbH",'01_Saldenlisten_Import'!$F:$F,"Büro & IT"),0) -> 8500 | D16: =IFERROR(SUMIFS('01_Saldenlisten_Import'!$J:$J,'01_Saldenlisten_Import'!$A:$A,"2025-02",'01_Saldenlisten_Import'!$B:$B,"Mustermann GmbH",'01_Saldenlisten_Import'!$F:$F,"Büro & IT"),0) -> 9200 | E16: =IFERROR(SUMIFS('01_Saldenlisten_Import'!$J:$J,'01_Saldenlisten_Import'!$A:$A,"2025-03",'01_Saldenlisten_Import'!$B:$B,"Mustermann GmbH",'01_Saldenlisten_Import'!$F:$F,"Büro & IT"),0) -> 9500 | F16: =IFERROR(SUMIFS('01_Saldenlisten_Import'!$J:$J,'01_Saldenlisten_Import'!$A:$A,"2025-04",'01_Saldenlisten_Import'!$B:$B,"Mustermann GmbH",'01_Saldenlisten_Import'!$F:$F,"Büro & IT"),0) -> 9800 | G16: =IFERROR(SUMIFS('01_Saldenlisten_Import'!$J:$J,'01_Saldenlisten_Import'!$A:$A,"2025-05",'01_Saldenlisten_Import'!$B:$B,"Mustermann GmbH",'01_Saldenlisten_Import'!$F:$F,"Büro & IT"),0) -> 10000 | H16: =IFERROR(SUMIFS('01_Saldenlisten_Import'!$J:$J,'01_Saldenlisten_Import'!$A:$A,"2025-06",'01_Saldenlisten_Import'!$B:$B,"Mustermann GmbH",'01_Saldenlisten_Import'!$F:$F,"Büro & IT"),0) -> 10300 | I16: =IFERROR(SUMIFS('01_Saldenlisten_Import'!$J:$J,'01_Saldenlisten_Import'!$A:$A,"2025-07",'01_Saldenlisten_Import'!$B:$B,"Mustermann GmbH",'01_Saldenlisten_Import'!$F:$F,"Büro & IT"),0) -> 10600 | J16: =IFERROR(SUMIFS('01_Saldenlisten_Import'!$J:$J,'01_Saldenlisten_Import'!$A:$A,"2025-08",'01_Saldenlisten_Import'!$B:$B,"Mustermann GmbH",'01_Saldenlisten_Import'!$F:$F,"Büro & IT"),0) -> 10900 | K16: =IFERROR(SUMIFS('01_Saldenlisten_Import'!$J:$J,'01_Saldenlisten_Import'!$A:$A,"2025-09",'01_Saldenlisten_Import'!$B:$B,"Mustermann GmbH",'01_Saldenlisten_Import'!$F:$F,"Büro & IT"),0) -> 11200 | L16: =IFERROR(SUMIFS('01_Saldenlisten_Import'!$J:$J,'01_Saldenlisten_Import'!$A:$A,"2025-10",'01_Saldenlisten_Import'!$B:$B,"Mustermann GmbH",'01_Saldenlisten_Import'!$F:$F,"Büro & IT"),0) -> 11500 | M16: =IFERROR(SUMIFS('01_Saldenlisten_Import'!$J:$J,'01_Saldenlisten_Import'!$A:$A,"2025-11",'01_Saldenlisten_Import'!$B:$B,"Mustermann GmbH",'01_Saldenlisten_Import'!$F:$F,"Büro & IT"),0) -> 11800 | N16: =IFERROR(SUMIFS('01_Saldenlisten_Import'!$J:$J,'01_Saldenlisten_Import'!$A:$A,"2025-12",'01_Saldenlisten_Import'!$B:$B,"Mustermann GmbH",'01_Saldenlisten_Import'!$F:$F,"Büro & IT"),0) -> 12000 | O16: =IFERROR(SUM(C16:N16),0) -> 125300
A17: 9 | B17: - Versicherungen & Beiträge | C17: =IFERROR(SUMIFS('01_Saldenlisten_Import'!$J:$J,'01_Saldenlisten_Import'!$A:$A,"2025-01",'01_Saldenlisten_Import'!$B:$B,"Mustermann GmbH",'01_Saldenlisten_Import'!$F:$F,"Versicherungen"),0) -> 0 | D17: =IFERROR(SUMIFS('01_Saldenlisten_Import'!$J:$J,'01_Saldenlisten_Import'!$A:$A,"2025-02",'01_Saldenlisten_Import'!$B:$B,"Mustermann GmbH",'01_Saldenlisten_Import'!$F:$F,"Versicherungen"),0) -> 0 | E17: =IFERROR(SUMIFS('01_Saldenlisten_Import'!$J:$J,'01_Saldenlisten_Import'!$A:$A,"2025-03",'01_Saldenlisten_Import'!$B:$B,"Mustermann GmbH",'01_Saldenlisten_Import'!$F:$F,"Versicherungen"),0) -> 0 | F17: =IFERROR(SUMIFS('01_Saldenlisten_Import'!$J:$J,'01_Saldenlisten_Import'!$A:$A,"2025-04",'01_Saldenlisten_Import'!$B:$B,"Mustermann GmbH",'01_Saldenlisten_Import'!$F:$F,"Versicherungen"),0) -> 0 | G17: =IFERROR(SUMIFS('01_Saldenlisten_Import'!$J:$J,'01_Saldenlisten_Import'!$A:$A,"2025-05",'01_Saldenlisten_Import'!$B:$B,"Mustermann GmbH",'01_Saldenlisten_Import'!$F:$F,"Versicherungen"),0) -> 0 | H17: =IFERROR(SUMIFS('01_Saldenlisten_Import'!$J:$J,'01_Saldenlisten_Import'!$A:$A,"2025-06",'01_Saldenlisten_Import'!$B:$B,"Mustermann GmbH",'01_Saldenlisten_Import'!$F:$F,"Versicherungen"),0) -> 0 | I17: =IFERROR(SUMIFS('01_Saldenlisten_Import'!$J:$J,'01_Saldenlisten_Import'!$A:$A,"2025-07",'01_Saldenlisten_Import'!$B:$B,"Mustermann GmbH",'01_Saldenlisten_Import'!$F:$F,"Versicherungen"),0) -> 0 | J17: =IFERROR(SUMIFS('01_Saldenlisten_Import'!$J:$J,'01_Saldenlisten_Import'!$A:$A,"2025-08",'01_Saldenlisten_Import'!$B:$B,"Mustermann GmbH",'01_Saldenlisten_Import'!$F:$F,"Versicherungen"),0) -> 0 | K17: =IFERROR(SUMIFS('01_Saldenlisten_Import'!$J:$J,'01_Saldenlisten_Import'!$A:$A,"2025-09",'01_Saldenlisten_Import'!$B:$B,"Mustermann GmbH",'01_Saldenlisten_Import'!$F:$F,"Versicherungen"),0) -> 0 | L17: =IFERROR(SUMIFS('01_Saldenlisten_Import'!$J:$J,'01_Saldenlisten_Import'!$A:$A,"2025-10",'01_Saldenlisten_Import'!$B:$B,"Mustermann GmbH",'01_Saldenlisten_Import'!$F:$F,"Versicherungen"),0) -> 0 | M17: =IFERROR(SUMIFS('01_Saldenlisten_Import'!$J:$J,'01_Saldenlisten_Import'!$A:$A,"2025-11",'01_Saldenlisten_Import'!$B:$B,"Mustermann GmbH",'01_Saldenlisten_Import'!$F:$F,"Versicherungen"),0) -> 0 | N17: =IFERROR(SUMIFS('01_Saldenlisten_Import'!$J:$J,'01_Saldenlisten_Import'!$A:$A,"2025-12",'01_Saldenlisten_Import'!$B:$B,"Mustermann GmbH",'01_Saldenlisten_Import'!$F:$F,"Versicherungen"),0) -> 0 | O17: =IFERROR(SUM(C17:N17),0) -> 0
A18: 10 | B18: - Sonstige Betriebskosten | C18: =IFERROR(SUMIFS('01_Saldenlisten_Import'!$J:$J,'01_Saldenlisten_Import'!$A:$A,"2025-01",'01_Saldenlisten_Import'!$B:$B,"Mustermann GmbH",'01_Saldenlisten_Import'!$F:$F,"Sonstige"),0) -> 1770 | D18: =IFERROR(SUMIFS('01_Saldenlisten_Import'!$J:$J,'01_Saldenlisten_Import'!$A:$A,"2025-02",'01_Saldenlisten_Import'!$B:$B,"Mustermann GmbH",'01_Saldenlisten_Import'!$F:$F,"Sonstige"),0) -> 6065 | E18: =IFERROR(SUMIFS('01_Saldenlisten_Import'!$J:$J,'01_Saldenlisten_Import'!$A:$A,"2025-03",'01_Saldenlisten_Import'!$B:$B,"Mustermann GmbH",'01_Saldenlisten_Import'!$F:$F,"Sonstige"),0) -> 6080 | F18: =IFERROR(SUMIFS('01_Saldenlisten_Import'!$J:$J,'01_Saldenlisten_Import'!$A:$A,"2025-04",'01_Saldenlisten_Import'!$B:$B,"Mustermann GmbH",'01_Saldenlisten_Import'!$F:$F,"Sonstige"),0) -> 1032 | G18: =IFERROR(SUMIFS('01_Saldenlisten_Import'!$J:$J,'01_Saldenlisten_Import'!$A:$A,"2025-05",'01_Saldenlisten_Import'!$B:$B,"Mustermann GmbH",'01_Saldenlisten_Import'!$F:$F,"Sonstige"),0) -> 4608 | H18: =IFERROR(SUMIFS('01_Saldenlisten_Import'!$J:$J,'01_Saldenlisten_Import'!$A:$A,"2025-06",'01_Saldenlisten_Import'!$B:$B,"Mustermann GmbH",'01_Saldenlisten_Import'!$F:$F,"Sonstige"),0) -> 5565 | I18: =IFERROR(SUMIFS('01_Saldenlisten_Import'!$J:$J,'01_Saldenlisten_Import'!$A:$A,"2025-07",'01_Saldenlisten_Import'!$B:$B,"Mustermann GmbH",'01_Saldenlisten_Import'!$F:$F,"Sonstige"),0) -> 4227 | J18: =IFERROR(SUMIFS('01_Saldenlisten_Import'!$J:$J,'01_Saldenlisten_Import'!$A:$A,"2025-08",'01_Saldenlisten_Import'!$B:$B,"Mustermann GmbH",'01_Saldenlisten_Import'!$F:$F,"Sonstige"),0) -> 5192 | K18: =IFERROR(SUMIFS('01_Saldenlisten_Import'!$J:$J,'01_Saldenlisten_Import'!$A:$A,"2025-09",'01_Saldenlisten_Import'!$B:$B,"Mustermann GmbH",'01_Saldenlisten_Import'!$F:$F,"Sonstige"),0) -> 5660 | L18: =IFERROR(SUMIFS('01_Saldenlisten_Import'!$J:$J,'01_Saldenlisten_Import'!$A:$A,"2025-10",'01_Saldenlisten_Import'!$B:$B,"Mustermann GmbH",'01_Saldenlisten_Import'!$F:$F,"Sonstige"),0) -> 6200 | M18: =IFERROR(SUMIFS('01_Saldenlisten_Import'!$J:$J,'01_Saldenlisten_Import'!$A:$A,"2025-11",'01_Saldenlisten_Import'!$B:$B,"Mustermann GmbH",'01_Saldenlisten_Import'!$F:$F,"Sonstige"),0) -> 6200 | N18: =IFERROR(SUMIFS('01_Saldenlisten_Import'!$J:$J,'01_Saldenlisten_Import'!$A:$A,"2025-12",'01_Saldenlisten_Import'!$B:$B,"Mustermann GmbH",'01_Saldenlisten_Import'!$F:$F,"Sonstige"),0) -> 6800 | O18: =IFERROR(SUM(C18:N18),0) -> 59399
B19: = EBITDA | C19: =C9-(C11+C12+C13+C14+C15+C16+C17+C18) -> 22030 | D19: =D9-(D11+D12+D13+D14+D15+D16+D17+D18) -> 22085 | E19: =E9-(E11+E12+E13+E14+E15+E16+E17+E18) -> 21170 | F19: =F9-(F11+F12+F13+F14+F15+F16+F17+F18) -> 21348 | G19: =G9-(G11+G12+G13+G14+G15+G16+G17+G18) -> 21392 | H19: =H9-(H11+H12+H13+H14+H15+H16+H17+H18) -> 21735 | I19: =I9-(I11+I12+I13+I14+I15+I16+I17+I18) -> 21163 | J19: =J9-(J11+J12+J13+J14+J15+J16+J17+J18) -> 21578 | ... N19: =N9-(N11+N12+N13+N14+N15+N16+N17+N18) -> 25500 | O19: =IFERROR(SUM(C19:N19),0) -> 266611
A21: 11 | B21: - Abschreibungen (AfA) | C21: =IFERROR(SUMIFS('01_Saldenlisten_Import'!$J:$J,'01_Saldenlisten_Import'!$A:$A,"2025-01",'01_Saldenlisten_Import'!$B:$B,"Mustermann GmbH",'01_Saldenlisten_Import'!$F:$F,"Abschreibungen"),0) -> 0 | D21: =IFERROR(SUMIFS('01_Saldenlisten_Import'!$J:$J,'01_Saldenlisten_Import'!$A:$A,"2025-02",'01_Saldenlisten_Import'!$B:$B,"Mustermann GmbH",'01_Saldenlisten_Import'!$F:$F,"Abschreibungen"),0) -> 0 | E21: =IFERROR(SUMIFS('01_Saldenlisten_Import'!$J:$J,'01_Saldenlisten_Import'!$A:$A,"2025-03",'01_Saldenlisten_Import'!$B:$B,"Mustermann GmbH",'01_Saldenlisten_Import'!$F:$F,"Abschreibungen"),0) -> 0 | F21: =IFERROR(SUMIFS('01_Saldenlisten_Import'!$J:$J,'01_Saldenlisten_Import'!$A:$A,"2025-04",'01_Saldenlisten_Import'!$B:$B,"Mustermann GmbH",'01_Saldenlisten_Import'!$F:$F,"Abschreibungen"),0) -> 0 | G21: =IFERROR(SUMIFS('01_Saldenlisten_Import'!$J:$J,'01_Saldenlisten_Import'!$A:$A,"2025-05",'01_Saldenlisten_Import'!$B:$B,"Mustermann GmbH",'01_Saldenlisten_Import'!$F:$F,"Abschreibungen"),0) -> 0 | H21: =IFERROR(SUMIFS('01_Saldenlisten_Import'!$J:$J,'01_Saldenlisten_Import'!$A:$A,"2025-06",'01_Saldenlisten_Import'!$B:$B,"Mustermann GmbH",'01_Saldenlisten_Import'!$F:$F,"Abschreibungen"),0) -> 0 | I21: =IFERROR(SUMIFS('01_Saldenlisten_Import'!$J:$J,'01_Saldenlisten_Import'!$A:$A,"2025-07",'01_Saldenlisten_Import'!$B:$B,"Mustermann GmbH",'01_Saldenlisten_Import'!$F:$F,"Abschreibungen"),0) -> 0 | J21: =IFERROR(SUMIFS('01_Saldenlisten_Import'!$J:$J,'01_Saldenlisten_Import'!$A:$A,"2025-08",'01_Saldenlisten_Import'!$B:$B,"Mustermann GmbH",'01_Saldenlisten_Import'!$F:$F,"Abschreibungen"),0) -> 0 | K21: =IFERROR(SUMIFS('01_Saldenlisten_Import'!$J:$J,'01_Saldenlisten_Import'!$A:$A,"2025-09",'01_Saldenlisten_Import'!$B:$B,"Mustermann GmbH",'01_Saldenlisten_Import'!$F:$F,"Abschreibungen"),0) -> 0 | L21: =IFERROR(SUMIFS('01_Saldenlisten_Import'!$J:$J,'01_Saldenlisten_Import'!$A:$A,"2025-10",'01_Saldenlisten_Import'!$B:$B,"Mustermann GmbH",'01_Saldenlisten_Import'!$F:$F,"Abschreibungen"),0) -> 0 | M21: =IFERROR(SUMIFS('01_Saldenlisten_Import'!$J:$J,'01_Saldenlisten_Import'!$A:$A,"2025-11",'01_Saldenlisten_Import'!$B:$B,"Mustermann GmbH",'01_Saldenlisten_Import'!$F:$F,"Abschreibungen"),0) -> 0 | N21: =IFERROR(SUMIFS('01_Saldenlisten_Import'!$J:$J,'01_Saldenlisten_Import'!$A:$A,"2025-12",'01_Saldenlisten_Import'!$B:$B,"Mustermann GmbH",'01_Saldenlisten_Import'!$F:$F,"Abschreibungen"),0) -> 0 | O21: =IFERROR(SUM(C21:N21),0) -> 0
B22: = EBIT (Betriebsergebnis) | C22: =C19-C21 -> 22030 | D22: =D19-D21 -> 22085 | E22: =E19-E21 -> 21170 | F22: =F19-F21 -> 21348 | G22: =G19-G21 -> 21392 | H22: =H19-H21 -> 21735 | I22: =I19-I21 -> 21163 | J22: =J19-J21 -> 21578 | ... N22: =N19-N21 -> 25500 | O22: =IFERROR(SUM(C22:N22),0) -> 266611
A24: 12 | B24: +/- Finanzergebnis | C24: =IFERROR(SUMIFS('01_Saldenlisten_Import'!$J:$J,'01_Saldenlisten_Import'!$A:$A,"2025-01",'01_Saldenlisten_Import'!$B:$B,"Mustermann GmbH",'01_Saldenlisten_Import'!$F:$F,"Finanzergebnis"),0) -> 0 | D24: =IFERROR(SUMIFS('01_Saldenlisten_Import'!$J:$J,'01_Saldenlisten_Import'!$A:$A,"2025-02",'01_Saldenlisten_Import'!$B:$B,"Mustermann GmbH",'01_Saldenlisten_Import'!$F:$F,"Finanzergebnis"),0) -> 0 | E24: =IFERROR(SUMIFS('01_Saldenlisten_Import'!$J:$J,'01_Saldenlisten_Import'!$A:$A,"2025-03",'01_Saldenlisten_Import'!$B:$B,"Mustermann GmbH",'01_Saldenlisten_Import'!$F:$F,"Finanzergebnis"),0) -> 0 | F24: =IFERROR(SUMIFS('01_Saldenlisten_Import'!$J:$J,'01_Saldenlisten_Import'!$A:$A,"2025-04",'01_Saldenlisten_Import'!$B:$B,"Mustermann GmbH",'01_Saldenlisten_Import'!$F:$F,"Finanzergebnis"),0) -> 0 | G24: =IFERROR(SUMIFS('01_Saldenlisten_Import'!$J:$J,'01_Saldenlisten_Import'!$A:$A,"2025-05",'01_Saldenlisten_Import'!$B:$B,"Mustermann GmbH",'01_Saldenlisten_Import'!$F:$F,"Finanzergebnis"),0) -> 0 | H24: =IFERROR(SUMIFS('01_Saldenlisten_Import'!$J:$J,'01_Saldenlisten_Import'!$A:$A,"2025-06",'01_Saldenlisten_Import'!$B:$B,"Mustermann GmbH",'01_Saldenlisten_Import'!$F:$F,"Finanzergebnis"),0) -> 0 | I24: =IFERROR(SUMIFS('01_Saldenlisten_Import'!$J:$J,'01_Saldenlisten_Import'!$A:$A,"2025-07",'01_Saldenlisten_Import'!$B:$B,"Mustermann GmbH",'01_Saldenlisten_Import'!$F:$F,"Finanzergebnis"),0) -> 0 | J24: =IFERROR(SUMIFS('01_Saldenlisten_Import'!$J:$J,'01_Saldenlisten_Import'!$A:$A,"2025-08",'01_Saldenlisten_Import'!$B:$B,"Mustermann GmbH",'01_Saldenlisten_Import'!$F:$F,"Finanzergebnis"),0) -> 0 | K24: =IFERROR(SUMIFS('01_Saldenlisten_Import'!$J:$J,'01_Saldenlisten_Import'!$A:$A,"2025-09",'01_Saldenlisten_Import'!$B:$B,"Mustermann GmbH",'01_Saldenlisten_Import'!$F:$F,"Finanzergebnis"),0) -> 0 | L24: =IFERROR(SUMIFS('01_Saldenlisten_Import'!$J:$J,'01_Saldenlisten_Import'!$A:$A,"2025-10",'01_Saldenlisten_Import'!$B:$B,"Mustermann GmbH",'01_Saldenlisten_Import'!$F:$F,"Finanzergebnis"),0) -> 0 | M24: =IFERROR(SUMIFS('01_Saldenlisten_Import'!$J:$J,'01_Saldenlisten_Import'!$A:$A,"2025-11",'01_Saldenlisten_Import'!$B:$B,"Mustermann GmbH",'01_Saldenlisten_Import'!$F:$F,"Finanzergebnis"),0) -> 0 | N24: =IFERROR(SUMIFS('01_Saldenlisten_Import'!$J:$J,'01_Saldenlisten_Import'!$A:$A,"2025-12",'01_Saldenlisten_Import'!$B:$B,"Mustermann GmbH",'01_Saldenlisten_Import'!$F:$F,"Finanzergebnis"),0) -> 0 | O24: =IFERROR(SUM(C24:N24),0) -> 0
B25: = EBT (Ergebnis vor Steuern) | C25: =C22+C24 -> 22030 | D25: =D22+D24 -> 22085 | E25: =E22+E24 -> 21170 | F25: =F22+F24 -> 21348 | G25: =G22+G24 -> 21392 | H25: =H22+H24 -> 21735 | I25: =I22+I24 -> 21163 | J25: =J22+J24 -> 21578 | ... N25: =N22+N24 -> 25500 | O25: =IFERROR(SUM(C25:N25),0) -> 266611
A27: 13 | B27: - Steuern | C27: =IFERROR(SUMIFS('01_Saldenlisten_Import'!$J:$J,'01_Saldenlisten_Import'!$A:$A,"2025-01",'01_Saldenlisten_Import'!$B:$B,"Mustermann GmbH",'01_Saldenlisten_Import'!$F:$F,"Steuern"),0) -> 0 | D27: =IFERROR(SUMIFS('01_Saldenlisten_Import'!$J:$J,'01_Saldenlisten_Import'!$A:$A,"2025-02",'01_Saldenlisten_Import'!$B:$B,"Mustermann GmbH",'01_Saldenlisten_Import'!$F:$F,"Steuern"),0) -> 0 | E27: =IFERROR(SUMIFS('01_Saldenlisten_Import'!$J:$J,'01_Saldenlisten_Import'!$A:$A,"2025-03",'01_Saldenlisten_Import'!$B:$B,"Mustermann GmbH",'01_Saldenlisten_Import'!$F:$F,"Steuern"),0) -> 0 | F27: =IFERROR(SUMIFS('01_Saldenlisten_Import'!$J:$J,'01_Saldenlisten_Import'!$A:$A,"2025-04",'01_Saldenlisten_Import'!$B:$B,"Mustermann GmbH",'01_Saldenlisten_Import'!$F:$F,"Steuern"),0) -> 0 | G27: =IFERROR(SUMIFS('01_Saldenlisten_Import'!$J:$J,'01_Saldenlisten_Import'!$A:$A,"2025-05",'01_Saldenlisten_Import'!$B:$B,"Mustermann GmbH",'01_Saldenlisten_Import'!$F:$F,"Steuern"),0) -> 0 | H27: =IFERROR(SUMIFS('01_Saldenlisten_Import'!$J:$J,'01_Saldenlisten_Import'!$A:$A,"2025-06",'01_Saldenlisten_Import'!$B:$B,"Mustermann GmbH",'01_Saldenlisten_Import'!$F:$F,"Steuern"),0) -> 0 | I27: =IFERROR(SUMIFS('01_Saldenlisten_Import'!$J:$J,'01_Saldenlisten_Import'!$A:$A,"2025-07",'01_Saldenlisten_Import'!$B:$B,"Mustermann GmbH",'01_Saldenlisten_Import'!$F:$F,"Steuern"),0) -> 0 | J27: =IFERROR(SUMIFS('01_Saldenlisten_Import'!$J:$J,'01_Saldenlisten_Import'!$A:$A,"2025-08",'01_Saldenlisten_Import'!$B:$B,"Mustermann GmbH",'01_Saldenlisten_Import'!$F:$F,"Steuern"),0) -> 0 | K27: =IFERROR(SUMIFS('01_Saldenlisten_Import'!$J:$J,'01_Saldenlisten_Import'!$A:$A,"2025-09",'01_Saldenlisten_Import'!$B:$B,"Mustermann GmbH",'01_Saldenlisten_Import'!$F:$F,"Steuern"),0) -> 0 | L27: =IFERROR(SUMIFS('01_Saldenlisten_Import'!$J:$J,'01_Saldenlisten_Import'!$A:$A,"2025-10",'01_Saldenlisten_Import'!$B:$B,"Mustermann GmbH",'01_Saldenlisten_Import'!$F:$F,"Steuern"),0) -> 0 | M27: =IFERROR(SUMIFS('01_Saldenlisten_Import'!$J:$J,'01_Saldenlisten_Import'!$A:$A,"2025-11",'01_Saldenlisten_Import'!$B:$B,"Mustermann GmbH",'01_Saldenlisten_Import'!$F:$F,"Steuern"),0) -> 0 | N27: =IFERROR(SUMIFS('01_Saldenlisten_Import'!$J:$J,'01_Saldenlisten_Import'!$A:$A,"2025-12",'01_Saldenlisten_Import'!$B:$B,"Mustermann GmbH",'01_Saldenlisten_Import'!$F:$F,"Steuern"),0) -> 0 | O27: =IFERROR(SUM(C27:N27),0) -> 0
B28: = JAHRESÜBERSCHUSS / -FEHLBETRAG | C28: =C25-C27 -> 22030 | D28: =D25-D27 -> 22085 | E28: =E25-E27 -> 21170 | F28: =F25-F27 -> 21348 | G28: =G25-G27 -> 21392 | H28: =H25-H27 -> 21735 | I28: =I25-I27 -> 21163 | J28: =J25-J27 -> 21578 | ... N28: =N25-N27 -> 25500 | O28: =IFERROR(SUM(C28:N28),0) -> 266611

Sheet Bilanz_Struktur
A1: 🏦 BILANZ-STRUKTUR — SUMIFS aus Saldenlisten-Import · Mustermann GmbH · Stand: Sep 2025
A2: # | B2: Position | C2: Jan | D2: Feb | E2: Mär | F2: Apr | G2: Mai | H2: Jun | I2: Jul | J2: Aug | K2: Sep | L2: YTD
A3: ─── AKTIVA ───────────────────────────
A4: A1 | B4: I. Anlagevermögen | C4: =IFERROR(SUMIFS('01_Saldenlisten_Import'!$J:$J,'01_Saldenlisten_Import'!$A:$A,"2025-01",'01_Saldenlisten_Import'!$B:$B,"Mustermann GmbH",'01_Saldenlisten_Import'!$F:$F,"Anlagevermögen"),0) -> 0 | D4: =IFERROR(SUMIFS('01_Saldenlisten_Import'!$J:$J,'01_Saldenlisten_Import'!$A:$A,"2025-02",'01_Saldenlisten_Import'!$B:$B,"Mustermann GmbH",'01_Saldenlisten_Import'!$F:$F,"Anlagevermögen"),0) -> 0 | E4: =IFERROR(SUMIFS('01_Saldenlisten_Import'!$J:$J,'01_Saldenlisten_Import'!$A:$A,"2025-03",'01_Saldenlisten_Import'!$B:$B,"Mustermann GmbH",'01_Saldenlisten_Import'!$F:$F,"Anlagevermögen"),0) -> 0 | F4: =IFERROR(SUMIFS('01_Saldenlisten_Import'!$J:$J,'01_Saldenlisten_Import'!$A:$A,"2025-04",'01_Saldenlisten_Import'!$B:$B,"Mustermann GmbH",'01_Saldenlisten_Import'!$F:$F,"Anlagevermögen"),0) -> 0 | G4: =IFERROR(SUMIFS('01_Saldenlisten_Import'!$J:$J,'01_Saldenlisten_Import'!$A:$A,"2025-05",'01_Saldenlisten_Import'!$B:$B,"Mustermann GmbH",'01_Saldenlisten_Import'!$F:$F,"Anlagevermögen"),0) -> 0 | H4: =IFERROR(SUMIFS('01_Saldenlisten_Import'!$J:$J,'01_Saldenlisten_Import'!$A:$A,"2025-06",'01_Saldenlisten_Import'!$B:$B,"Mustermann GmbH",'01_Saldenlisten_Import'!$F:$F,"Anlagevermögen"),0) -> 0 | I4: =IFERROR(SUMIFS('01_Saldenlisten_Import'!$J:$J,'01_Saldenlisten_Import'!$A:$A,"2025-07",'01_Saldenlisten_Import'!$B:$B,"Mustermann GmbH",'01_Saldenlisten_Import'!$F:$F,"Anlagevermögen"),0) -> 0 | J4: =IFERROR(SUMIFS('01_Saldenlisten_Import'!$J:$J,'01_Saldenlisten_Import'!$A:$A,"2025-08",'01_Saldenlisten_Import'!$B:$B,"Mustermann GmbH",'01_Saldenlisten_Import'!$F:$F,"Anlagevermögen"),0) -> 0 | K4: =IFERROR(SUMIFS('01_Saldenlisten_Import'!$J:$J,'01_Saldenlisten_Import'!$A:$A,"2025-09",'01_Saldenlisten_Import'!$B:$B,"Mustermann GmbH",'01_Saldenlisten_Import'!$F:$F,"Anlagevermögen"),0) -> 0 | L4: =IFERROR(SUM(C4:K4),0) -> 0
A5: A2 | B5: davon: Sachanlagen | C5: =IFERROR(SUMIFS('01_Saldenlisten_Import'!$J:$J,'01_Saldenlisten_Import'!$A:$A,"2025-01",'01_Saldenlisten_Import'!$B:$B,"Mustermann GmbH",'01_Saldenlisten_Import'!$F:$F,"Anlagevermögen"),0) -> 0 | D5: =IFERROR(SUMIFS('01_Saldenlisten_Import'!$J:$J,'01_Saldenlisten_Import'!$A:$A,"2025-02",'01_Saldenlisten_Import'!$B:$B,"Mustermann GmbH",'01_Saldenlisten_Import'!$F:$F,"Anlagevermögen"),0) -> 0 | E5: =IFERROR(SUMIFS('01_Saldenlisten_Import'!$J:$J,'01_Saldenlisten_Import'!$A:$A,"2025-03",'01_Saldenlisten_Import'!$B:$B,"Mustermann GmbH",'01_Saldenlisten_Import'!$F:$F,"Anlagevermögen"),0) -> 0 | F5: =IFERROR(SUMIFS('01_Saldenlisten_Import'!$J:$J,'01_Saldenlisten_Import'!$A:$A,"2025-04",'01_Saldenlisten_Import'!$B:$B,"Mustermann GmbH",'01_Saldenlisten_Import'!$F:$F,"Anlagevermögen"),0) -> 0 | G5: =IFERROR(SUMIFS('01_Saldenlisten_Import'!$J:$J,'01_Saldenlisten_Import'!$A:$A,"2025-05",'01_Saldenlisten_Import'!$B:$B,"Mustermann GmbH",'01_Saldenlisten_Import'!$F:$F,"Anlagevermögen"),0) -> 0 | H5: =IFERROR(SUMIFS('01_Saldenlisten_Import'!$J:$J,'01_Saldenlisten_Import'!$A:$A,"2025-06",'01_Saldenlisten_Import'!$B:$B,"Mustermann GmbH",'01_Saldenlisten_Import'!$F:$F,"Anlagevermögen"),0) -> 0 | I5: =IFERROR(SUMIFS('01_Saldenlisten_Import'!$J:$J,'01_Saldenlisten_Import'!$A:$A,"2025-07",'01_Saldenlisten_Import'!$B:$B,"Mustermann GmbH",'01_Saldenlisten_Import'!$F:$F,"Anlagevermögen"),0) -> 0 | J5: =IFERROR(SUMIFS('01_Saldenlisten_Import'!$J:$J,'01_Saldenlisten_Import'!$A:$A,"2025-08",'01_Saldenlisten_Import'!$B:$B,"Mustermann GmbH",'01_Saldenlisten_Import'!$F:$F,"Anlagevermögen"),0) -> 0 | K5: =IFERROR(SUMIFS('01_Saldenlisten_Import'!$J:$J,'01_Saldenlisten_Import'!$A:$A,"2025-09",'01_Saldenlisten_Import'!$B:$B,"Mustermann GmbH",'01_Saldenlisten_Import'!$F:$F,"Anlagevermögen"),0) -> 0 | L5: =IFERROR(SUM(C5:K5),0) -> 0
A6: A3 | B6: davon: Software / immaterielle WG | C6: =IFERROR(SUMIFS('01_Saldenlisten_Import'!$J:$J,'01_Saldenlisten_Import'!$A:$A,"2025-01",'01_Saldenlisten_Import'!$B:$B,"Mustermann GmbH",'01_Saldenlisten_Import'!$F:$F,"Anlagevermögen"),0) -> 0 | D6: =IFERROR(SUMIFS('01_Saldenlisten_Import'!$J:$J,'01_Saldenlisten_Import'!$A:$A,"2025-02",'01_Saldenlisten_Import'!$B:$B,"Mustermann GmbH",'01_Saldenlisten_Import'!$F:$F,"Anlagevermögen"),0) -> 0 | E6: =IFERROR(SUMIFS('01_Saldenlisten_Import'!$J:$J,'01_Saldenlisten_Import'!$A:$A,"2025-03",'01_Saldenlisten_Import'!$B:$B,"Mustermann GmbH",'01_Saldenlisten_Import'!$F:$F,"Anlagevermögen"),0) -> 0 | F6: =IFERROR(SUMIFS('01_Saldenlisten_Import'!$J:$J,'01_Saldenlisten_Import'!$A:$A,"2025-04",'01_Saldenlisten_Import'!$B:$B,"Mustermann GmbH",'01_Saldenlisten_Import'!$F:$F,"Anlagevermögen"),0) -> 0 | G6: =IFERROR(SUMIFS('01_Saldenlisten_Import'!$J:$J,'01_Saldenlisten_Import'!$A:$A,"2025-05",'01_Saldenlisten_Import'!$B:$B,"Mustermann GmbH",'01_Saldenlisten_Import'!$F:$F,"Anlagevermögen"),0) -> 0 | H6: =IFERROR(SUMIFS('01_Saldenlisten_Import'!$J:$J,'01_Saldenlisten_Import'!$A:$A,"2025-06",'01_Saldenlisten_Import'!$B:$B,"Mustermann GmbH",'01_Saldenlisten_Import'!$F:$F,"Anlagevermögen"),0) -> 0 | I6: =IFERROR(SUMIFS('01_Saldenlisten_Import'!$J:$J,'01_Saldenlisten_Import'!$A:$A,"2025-07",'01_Saldenlisten_Import'!$B:$B,"Mustermann GmbH",'01_Saldenlisten_Import'!$F:$F,"Anlagevermögen"),0) -> 0 | J6: =IFERROR(SUMIFS('01_Saldenlisten_Import'!$J:$J,'01_Saldenlisten_Import'!$A:$A,"2025-08",'01_Saldenlisten_Import'!$B:$B,"Mustermann GmbH",'01_Saldenlisten_Import'!$F:$F,"Anlagevermögen"),0) -> 0 | K6: =IFERROR(SUMIFS('01_Saldenlisten_Import'!$J:$J,'01_Saldenlisten_Import'!$A:$A,"2025-09",'01_Saldenlisten_Import'!$B:$B,"Mustermann GmbH",'01_Saldenlisten_Import'!$F:$F,"Anlagevermögen"),0) -> 0 | L6: =IFERROR(SUM(C6:K6),0) -> 0
B7: = A. ANLAGEVERMÖGEN GESAMT | C7: =IFERROR(SUM(C4:C6),0) -> 0 | D7: =IFERROR(SUM(D4:D6),0) -> 0 | E7: =IFERROR(SUM(E4:E6),0) -> 0 | F7: =IFERROR(SUM(F4:F6),0) -> 0 | G7: =IFERROR(SUM(G4:G6),0) -> 0 | H7: =IFERROR(SUM(H4:H6),0) -> 0 | I7: =IFERROR(SUM(I4:I6),0) -> 0 | J7: =IFERROR(SUM(J4:J6),0) -> 0 | ... L7: =IFERROR(SUM(L4:L6),0) -> 0
A9: A4a | B9: 1. Vorräte | C9: =IFERROR(SUMIFS('01_Saldenlisten_Import'!$J:$J,'01_Saldenlisten_Import'!$A:$A,"2025-01",'01_Saldenlisten_Import'!$B:$B,"Mustermann GmbH",'01_Saldenlisten_Import'!$F:$F,"Vorräte"),0) -> 0 | D9: =IFERROR(SUMIFS('01_Saldenlisten_Import'!$J:$J,'01_Saldenlisten_Import'!$A:$A,"2025-02",'01_Saldenlisten_Import'!$B:$B,"Mustermann GmbH",'01_Saldenlisten_Import'!$F:$F,"Vorräte"),0) -> 0 | E9: =IFERROR(SUMIFS('01_Saldenlisten_Import'!$J:$J,'01_Saldenlisten_Import'!$A:$A,"2025-03",'01_Saldenlisten_Import'!$B:$B,"Mustermann GmbH",'01_Saldenlisten_Import'!$F:$F,"Vorräte"),0) -> 0 | F9: =IFERROR(SUMIFS('01_Saldenlisten_Import'!$J:$J,'01_Saldenlisten_Import'!$A:$A,"2025-04",'01_Saldenlisten_Import'!$B:$B,"Mustermann GmbH",'01_Saldenlisten_Import'!$F:$F,"Vorräte"),0) -> 0 | G9: =IFERROR(SUMIFS('01_Saldenlisten_Import'!$J:$J,'01_Saldenlisten_Import'!$A:$A,"2025-05",'01_Saldenlisten_Import'!$B:$B,"Mustermann GmbH",'01_Saldenlisten_Import'!$F:$F,"Vorräte"),0) -> 0 | H9: =IFERROR(SUMIFS('01_Saldenlisten_Import'!$J:$J,'01_Saldenlisten_Import'!$A:$A,"2025-06",'01_Saldenlisten_Import'!$B:$B,"Mustermann GmbH",'01_Saldenlisten_Import'!$F:$F,"Vorräte"),0) -> 0 | I9: =IFERROR(SUMIFS('01_Saldenlisten_Import'!$J:$J,'01_Saldenlisten_Import'!$A:$A,"2025-07",'01_Saldenlisten_Import'!$B:$B,"Mustermann GmbH",'01_Saldenlisten_Import'!$F:$F,"Vorräte"),0) -> 0 | J9: =IFERROR(SUMIFS('01_Saldenlisten_Import'!$J:$J,'01_Saldenlisten_Import'!$A:$A,"2025-08",'01_Saldenlisten_Import'!$B:$B,"Mustermann GmbH",'01_Saldenlisten_Import'!$F:$F,"Vorräte"),0) -> 0 | K9: =IFERROR(SUMIFS('01_Saldenlisten_Import'!$J:$J,'01_Saldenlisten_Import'!$A:$A,"2025-09",'01_Saldenlisten_Import'!$B:$B,"Mustermann GmbH",'01_Saldenlisten_Import'!$F:$F,"Vorräte"),0) -> 0 | L9: =IFERROR(SUM(C9:K9),0) -> 0
A10: A4b | B10: 2. Forderungen aus LuL | C10: =IFERROR(SUMIFS('01_Saldenlisten_Import'!$J:$J,'01_Saldenlisten_Import'!$A:$A,"2025-01",'01_Saldenlisten_Import'!$B:$B,"Mustermann GmbH",'01_Saldenlisten_Import'!$F:$F,"Forderungen"),0) -> 45000 | D10: =IFERROR(SUMIFS('01_Saldenlisten_Import'!$J:$J,'01_Saldenlisten_Import'!$A:$A,"2025-02",'01_Saldenlisten_Import'!$B:$B,"Mustermann GmbH",'01_Saldenlisten_Import'!$F:$F,"Forderungen"),0) -> 46500 | E10: =IFERROR(SUMIFS('01_Saldenlisten_Import'!$J:$J,'01_Saldenlisten_Import'!$A:$A,"2025-03",'01_Saldenlisten_Import'!$B:$B,"Mustermann GmbH",'01_Saldenlisten_Import'!$F:$F,"Forderungen"),0) -> 48000 | F10: =IFERROR(SUMIFS('01_Saldenlisten_Import'!$J:$J,'01_Saldenlisten_Import'!$A:$A,"2025-04",'01_Saldenlisten_Import'!$B:$B,"Mustermann GmbH",'01_Saldenlisten_Import'!$F:$F,"Forderungen"),0) -> 45000 | G10: =IFERROR(SUMIFS('01_Saldenlisten_Import'!$J:$J,'01_Saldenlisten_Import'!$A:$A,"2025-05",'01_Saldenlisten_Import'!$B:$B,"Mustermann GmbH",'01_Saldenlisten_Import'!$F:$F,"Forderungen"),0) -> 48500 | H10: =IFERROR(SUMIFS('01_Saldenlisten_Import'!$J:$J,'01_Saldenlisten_Import'!$A:$A,"2025-06",'01_Saldenlisten_Import'!$B:$B,"Mustermann GmbH",'01_Saldenlisten_Import'!$F:$F,"Forderungen"),0) -> 50000 | I10: =IFERROR(SUMIFS('01_Saldenlisten_Import'!$J:$J,'01_Saldenlisten_Import'!$A:$A,"2025-07",'01_Saldenlisten_Import'!$B:$B,"Mustermann GmbH",'01_Saldenlisten_Import'!$F:$F,"Forderungen"),0) -> 49000 | J10: =IFERROR(SUMIFS('01_Saldenlisten_Import'!$J:$J,'01_Saldenlisten_Import'!$A:$A,"2025-08",'01_Saldenlisten_Import'!$B:$B,"Mustermann GmbH",'01_Saldenlisten_Import'!$F:$F,"Forderungen"),0) -> 51000 | K10: =IFERROR(SUMIFS('01_Saldenlisten_Import'!$J:$J,'01_Saldenlisten_Import'!$A:$A,"2025-09",'01_Saldenlisten_Import'!$B:$B,"Mustermann GmbH",'01_Saldenlisten_Import'!$F:$F,"Forderungen"),0) -> 52000 | L10: =IFERROR(SUM(C10:K10),0) -> 435000
A11: A4c | B11: 3. Bankguthaben | C11: =IFERROR(SUMIFS('01_Saldenlisten_Import'!$J:$J,'01_Saldenlisten_Import'!$A:$A,"2025-01",'01_Saldenlisten_Import'!$B:$B,"Mustermann GmbH",'01_Saldenlisten_Import'!$F:$F,"Bankguthaben"),0) -> 24000 | D11: =IFERROR(SUMIFS('01_Saldenlisten_Import'!$J:$J,'01_Saldenlisten_Import'!$A:$A,"2025-02",'01_Saldenlisten_Import'!$B:$B,"Mustermann GmbH",'01_Saldenlisten_Import'!$F:$F,"Bankguthaben"),0) -> 25000 | E11: =IFERROR(SUMIFS('01_Saldenlisten_Import'!$J:$J,'01_Saldenlisten_Import'!$A:$A,"2025-03",'01_Saldenlisten_Import'!$B:$B,"Mustermann GmbH",'01_Saldenlisten_Import'!$F:$F,"Bankguthaben"),0) -> 27000 | F11: =IFERROR(SUMIFS('01_Saldenlisten_Import'!$J:$J,'01_Saldenlisten_Import'!$A:$A,"2025-04",'01_Saldenlisten_Import'!$B:$B,"Mustermann GmbH",'01_Saldenlisten_Import'!$F:$F,"Bankguthaben"),0) -> 26000 | G11: =IFERROR(SUMIFS('01_Saldenlisten_Import'!$J:$J,'01_Saldenlisten_Import'!$A:$A,"2025-05",'01_Saldenlisten_Import'!$B:$B,"Mustermann GmbH",'01_Saldenlisten_Import'!$F:$F,"Bankguthaben"),0) -> 28500 | H11: =IFERROR(SUMIFS('01_Saldenlisten_Import'!$J:$J,'01_Saldenlisten_Import'!$A:$A,"2025-06",'01_Saldenlisten_Import'!$B:$B,"Mustermann GmbH",'01_Saldenlisten_Import'!$F:$F,"Bankguthaben"),0) -> 29500 | I11: =IFERROR(SUMIFS('01_Saldenlisten_Import'!$J:$J,'01_Saldenlisten_Import'!$A:$A,"2025-07",'01_Saldenlisten_Import'!$B:$B,"Mustermann GmbH",'01_Saldenlisten_Import'!$F:$F,"Bankguthaben"),0) -> 29500 | J11: =IFERROR(SUMIFS('01_Saldenlisten_Import'!$J:$J,'01_Saldenlisten_Import'!$A:$A,"2025-08",'01_Saldenlisten_Import'!$B:$B,"Mustermann GmbH",'01_Saldenlisten_Import'!$F:$F,"Bankguthaben"),0) -> 31000 | K11: =IFERROR(SUMIFS('01_Saldenlisten_Import'!$J:$J,'01_Saldenlisten_Import'!$A:$A,"2025-09",'01_Saldenlisten_Import'!$B:$B,"Mustermann GmbH",'01_Saldenlisten_Import'!$F:$F,"Bankguthaben"),0) -> 31500 | L11: =IFERROR(SUM(C11:K11),0) -> 252000
A12: A4d | B12: 4. Kasse | C12: =IFERROR(SUMIFS('01_Saldenlisten_Import'!$J:$J,'01_Saldenlisten_Import'!$A:$A,"2025-01",'01_Saldenlisten_Import'!$B:$B,"Mustermann GmbH",'01_Saldenlisten_Import'!$F:$F,"Kassenbestand"),0) -> 0 | D12: =IFERROR(SUMIFS('01_Saldenlisten_Import'!$J:$J,'01_Saldenlisten_Import'!$A:$A,"2025-02",'01_Saldenlisten_Import'!$B:$B,"Mustermann GmbH",'01_Saldenlisten_Import'!$F:$F,"Kassenbestand"),0) -> 0 | E12: =IFERROR(SUMIFS('01_Saldenlisten_Import'!$J:$J,'01_Saldenlisten_Import'!$A:$A,"2025-03",'01_Saldenlisten_Import'!$B:$B,"Mustermann GmbH",'01_Saldenlisten_Import'!$F:$F,"Kassenbestand"),0) -> 0 | F12: =IFERROR(SUMIFS('01_Saldenlisten_Import'!$J:$J,'01_Saldenlisten_Import'!$A:$A,"2025-04",'01_Saldenlisten_Import'!$B:$B,"Mustermann GmbH",'01_Saldenlisten_Import'!$F:$F,"Kassenbestand"),0) -> 0 | G12: =IFERROR(SUMIFS('01_Saldenlisten_Import'!$J:$J,'01_Saldenlisten_Import'!$A:$A,"2025-05",'01_Saldenlisten_Import'!$B:$B,"Mustermann GmbH",'01_Saldenlisten_Import'!$F:$F,"Kassenbestand"),0) -> 0 | H12: =IFERROR(SUMIFS('01_Saldenlisten_Import'!$J:$J,'01_Saldenlisten_Import'!$A:$A,"2025-06",'01_Saldenlisten_Import'!$B:$B,"Mustermann GmbH",'01_Saldenlisten_Import'!$F:$F,"Kassenbestand"),0) -> 0 | I12: =IFERROR(SUMIFS('01_Saldenlisten_Import'!$J:$J,'01_Saldenlisten_Import'!$A:$A,"2025-07",'01_Saldenlisten_Import'!$B:$B,"Mustermann GmbH",'01_Saldenlisten_Import'!$F:$F,"Kassenbestand"),0) -> 0 | J12: =IFERROR(SUMIFS('01_Saldenlisten_Import'!$J:$J,'01_Saldenlisten_Import'!$A:$A,"2025-08",'01_Saldenlisten_Import'!$B:$B,"Mustermann GmbH",'01_Saldenlisten_Import'!$F:$F,"Kassenbestand"),0) -> 0 | K12: =IFERROR(SUMIFS('01_Saldenlisten_Import'!$J:$J,'01_Saldenlisten_Import'!$A:$A,"2025-09",'01_Saldenlisten_Import'!$B:$B,"Mustermann GmbH",'01_Saldenlisten_Import'!$F:$F,"Kassenbestand"),0) -> 0 | L12: =IFERROR(SUM(C12:K12),0) -> 0
A13: A4e | B13: 5. Vorsteuer | C13: =IFERROR(SUMIFS('01_Saldenlisten_Import'!$J:$J,'01_Saldenlisten_Import'!$A:$A,"2025-01",'01_Saldenlisten_Import'!$B:$B,"Mustermann GmbH",'01_Saldenlisten_Import'!$F:$F,"Vorsteuer"),0) -> 0 | D13: =IFERROR(SUMIFS('01_Saldenlisten_Import'!$J:$J,'01_Saldenlisten_Import'!$A:$A,"2025-02",'01_Saldenlisten_Import'!$B:$B,"Mustermann GmbH",'01_Saldenlisten_Import'!$F:$F,"Vorsteuer"),0) -> 0 | E13: =IFERROR(SUMIFS('01_Saldenlisten_Import'!$J:$J,'01_Saldenlisten_Import'!$A:$A,"2025-03",'01_Saldenlisten_Import'!$B:$B,"Mustermann GmbH",'01_Saldenlisten_Import'!$F:$F,"Vorsteuer"),0) -> 0 | F13: =IFERROR(SUMIFS('01_Saldenlisten_Import'!$J:$J,'01_Saldenlisten_Import'!$A:$A,"2025-04",'01_Saldenlisten_Import'!$B:$B,"Mustermann GmbH",'01_Saldenlisten_Import'!$F:$F,"Vorsteuer"),0) -> 0 | G13: =IFERROR(SUMIFS('01_Saldenlisten_Import'!$J:$J,'01_Saldenlisten_Import'!$A:$A,"2025-05",'01_Saldenlisten_Import'!$B:$B,"Mustermann GmbH",'01_Saldenlisten_Import'!$F:$F,"Vorsteuer"),0) -> 0 | H13: =IFERROR(SUMIFS('01_Saldenlisten_Import'!$J:$J,'01_Saldenlisten_Import'!$A:$A,"2025-06",'01_Saldenlisten_Import'!$B:$B,"Mustermann GmbH",'01_Saldenlisten_Import'!$F:$F,"Vorsteuer"),0) -> 0 | I13: =IFERROR(SUMIFS('01_Saldenlisten_Import'!$J:$J,'01_Saldenlisten_Import'!$A:$A,"2025-07",'01_Saldenlisten_Import'!$B:$B,"Mustermann GmbH",'01_Saldenlisten_Import'!$F:$F,"Vorsteuer"),0) -> 0 | J13: =IFERROR(SUMIFS('01_Saldenlisten_Import'!$J:$J,'01_Saldenlisten_Import'!$A:$A,"2025-08",'01_Saldenlisten_Import'!$B:$B,"Mustermann GmbH",'01_Saldenlisten_Import'!$F:$F,"Vorsteuer"),0) -> 0 | K13: =IFERROR(SUMIFS('01_Saldenlisten_Import'!$J:$J,'01_Saldenlisten_Import'!$A:$A,"2025-09",'01_Saldenlisten_Import'!$B:$B,"Mustermann GmbH",'01_Saldenlisten_Import'!$F:$F,"Vorsteuer"),0) -> 0 | L13: =IFERROR(SUM(C13:K13),0) -> 0
B14: = B. UMLAUFVERMÖGEN GESAMT | C14: =IFERROR(SUM(C9:C13),0) -> 69000 | D14: =IFERROR(SUM(D9:D13),0) -> 71500 | E14: =IFERROR(SUM(E9:E13),0) -> 75000 | F14: =IFERROR(SUM(F9:F13),0) -> 71000 | G14: =IFERROR(SUM(G9:G13),0) -> 77000 | H14: =IFERROR(SUM(H9:H13),0) -> 79500 | I14: =IFERROR(SUM(I9:I13),0) -> 78500 | J14: =IFERROR(SUM(J9:J13),0) -> 82000 | ... L14: =IFERROR(SUM(L9:L13),0) -> 687000
B15: = BILANZSUMME AKTIVA | C15: =IFERROR(C7+C14,0) -> 69000 | D15: =IFERROR(D7+D14,0) -> 71500 | E15: =IFERROR(E7+E14,0) -> 75000 | F15: =IFERROR(F7+F14,0) -> 71000 | G15: =IFERROR(G7+G14,0) -> 77000 | H15: =IFERROR(H7+H14,0) -> 79500 | I15: =IFERROR(I7+I14,0) -> 78500 | J15: =IFERROR(J7+J14,0) -> 82000 | ... L15: =IFERROR(L7+L14,0) -> 687000
A16: ─── PASSIVA ──────────────────────────
A17: P1 | B17: I. Eigenkapital (Stammkapital+Rücklagen) | C17: =IFERROR(SUMIFS('01_Saldenlisten_Import'!$J:$J,'01_Saldenlisten_Import'!$A:$A,"2025-01",'01_Saldenlisten_Import'!$B:$B,"Mustermann GmbH",'01_Saldenlisten_Import'!$F:$F,"Eigenkapital"),0) -> 0 | D17: =IFERROR(SUMIFS('01_Saldenlisten_Import'!$J:$J,'01_Saldenlisten_Import'!$A:$A,"2025-02",'01_Saldenlisten_Import'!$B:$B,"Mustermann GmbH",'01_Saldenlisten_Import'!$F:$F,"Eigenkapital"),0) -> 0 | E17: =IFERROR(SUMIFS('01_Saldenlisten_Import'!$J:$J,'01_Saldenlisten_Import'!$A:$A,"2025-03",'01_Saldenlisten_Import'!$B:$B,"Mustermann GmbH",'01_Saldenlisten_Import'!$F:$F,"Eigenkapital"),0) -> 0 | F17: =IFERROR(SUMIFS('01_Saldenlisten_Import'!$J:$J,'01_Saldenlisten_Import'!$A:$A,"2025-04",'01_Saldenlisten_Import'!$B:$B,"Mustermann GmbH",'01_Saldenlisten_Import'!$F:$F,"Eigenkapital"),0) -> 0 | G17: =IFERROR(SUMIFS('01_Saldenlisten_Import'!$J:$J,'01_Saldenlisten_Import'!$A:$A,"2025-05",'01_Saldenlisten_Import'!$B:$B,"Mustermann GmbH",'01_Saldenlisten_Import'!$F:$F,"Eigenkapital"),0) -> 0 | H17: =IFERROR(SUMIFS('01_Saldenlisten_Import'!$J:$J,'01_Saldenlisten_Import'!$A:$A,"2025-06",'01_Saldenlisten_Import'!$B:$B,"Mustermann GmbH",'01_Saldenlisten_Import'!$F:$F,"Eigenkapital"),0) -> 0 | I17: =IFERROR(SUMIFS('01_Saldenlisten_Import'!$J:$J,'01_Saldenlisten_Import'!$A:$A,"2025-07",'01_Saldenlisten_Import'!$B:$B,"Mustermann GmbH",'01_Saldenlisten_Import'!$F:$F,"Eigenkapital"),0) -> 0 | J17: =IFERROR(SUMIFS('01_Saldenlisten_Import'!$J:$J,'01_Saldenlisten_Import'!$A:$A,"2025-08",'01_Saldenlisten_Import'!$B:$B,"Mustermann GmbH",'01_Saldenlisten_Import'!$F:$F,"Eigenkapital"),0) -> 0 | K17: =IFERROR(SUMIFS('01_Saldenlisten_Import'!$J:$J,'01_Saldenlisten_Import'!$A:$A,"2025-09",'01_Saldenlisten_Import'!$B:$B,"Mustermann GmbH",'01_Saldenlisten_Import'!$F:$F,"Eigenkapital"),0) -> 0 | L17: =IFERROR(SUM(C17:K17),0) -> 0
B18: = A. EIGENKAPITAL GESAMT | C18: =IFERROR(C17,0) -> 0 | D18: =IFERROR(D17,0) -> 0 | E18: =IFERROR(E17,0) -> 0 | F18: =IFERROR(F17,0) -> 0 | G18: =IFERROR(G17,0) -> 0 | H18: =IFERROR(H17,0) -> 0 | I18: =IFERROR(I17,0) -> 0 | J18: =IFERROR(J17,0) -> 0 | ... L18: =IFERROR(L17,0) -> 0
A19: P2 | B19: II. Verbindlichkeiten aus LuL | C19: =IFERROR(SUMIFS('01_Saldenlisten_Import'!$J:$J,'01_Saldenlisten_Import'!$A:$A,"2025-01",'01_Saldenlisten_Import'!$B:$B,"Mustermann GmbH",'01_Saldenlisten_Import'!$F:$F,"Fremdkapital"),0) -> 18500 | D19: =IFERROR(SUMIFS('01_Saldenlisten_Import'!$J:$J,'01_Saldenlisten_Import'!$A:$A,"2025-02",'01_Saldenlisten_Import'!$B:$B,"Mustermann GmbH",'01_Saldenlisten_Import'!$F:$F,"Fremdkapital"),0) -> 19000 | E19: =IFERROR(SUMIFS('01_Saldenlisten_Import'!$J:$J,'01_Saldenlisten_Import'!$A:$A,"2025-03",'01_Saldenlisten_Import'!$B:$B,"Mustermann GmbH",'01_Saldenlisten_Import'!$F:$F,"Fremdkapital"),0) -> 20000 | F19: =IFERROR(SUMIFS('01_Saldenlisten_Import'!$J:$J,'01_Saldenlisten_Import'!$A:$A,"2025-04",'01_Saldenlisten_Import'!$B:$B,"Mustermann GmbH",'01_Saldenlisten_Import'!$F:$F,"Fremdkapital"),0) -> 19000 | G19: =IFERROR(SUMIFS('01_Saldenlisten_Import'!$J:$J,'01_Saldenlisten_Import'!$A:$A,"2025-05",'01_Saldenlisten_Import'!$B:$B,"Mustermann GmbH",'01_Saldenlisten_Import'!$F:$F,"Fremdkapital"),0) -> 20300 | H19: =IFERROR(SUMIFS('01_Saldenlisten_Import'!$J:$J,'01_Saldenlisten_Import'!$A:$A,"2025-06",'01_Saldenlisten_Import'!$B:$B,"Mustermann GmbH",'01_Saldenlisten_Import'!$F:$F,"Fremdkapital"),0) -> 21000 | I19: =IFERROR(SUMIFS('01_Saldenlisten_Import'!$J:$J,'01_Saldenlisten_Import'!$A:$A,"2025-07",'01_Saldenlisten_Import'!$B:$B,"Mustermann GmbH",'01_Saldenlisten_Import'!$F:$F,"Fremdkapital"),0) -> 20600 | J19: =IFERROR(SUMIFS('01_Saldenlisten_Import'!$J:$J,'01_Saldenlisten_Import'!$A:$A,"2025-08",'01_Saldenlisten_Import'!$B:$B,"Mustermann GmbH",'01_Saldenlisten_Import'!$F:$F,"Fremdkapital"),0) -> 21200 | K19: =IFERROR(SUMIFS('01_Saldenlisten_Import'!$J:$J,'01_Saldenlisten_Import'!$A:$A,"2025-09",'01_Saldenlisten_Import'!$B:$B,"Mustermann GmbH",'01_Saldenlisten_Import'!$F:$F,"Fremdkapital"),0) -> 21500 | L19: =IFERROR(SUM(C19:K19),0) -> 181100
A20: P3 | B20: Steuerverbindlichkeiten | C20: =IFERROR(SUMIFS('01_Saldenlisten_Import'!$J:$J,'01_Saldenlisten_Import'!$A:$A,"2025-01",'01_Saldenlisten_Import'!$B:$B,"Mustermann GmbH",'01_Saldenlisten_Import'!$F:$F,"Steuervb."),0) -> 0 | D20: =IFERROR(SUMIFS('01_Saldenlisten_Import'!$J:$J,'01_Saldenlisten_Import'!$A:$A,"2025-02",'01_Saldenlisten_Import'!$B:$B,"Mustermann GmbH",'01_Saldenlisten_Import'!$F:$F,"Steuervb."),0) -> 0 | E20: =IFERROR(SUMIFS('01_Saldenlisten_Import'!$J:$J,'01_Saldenlisten_Import'!$A:$A,"2025-03",'01_Saldenlisten_Import'!$B:$B,"Mustermann GmbH",'01_Saldenlisten_Import'!$F:$F,"Steuervb."),0) -> 0 | F20: =IFERROR(SUMIFS('01_Saldenlisten_Import'!$J:$J,'01_Saldenlisten_Import'!$A:$A,"2025-04",'01_Saldenlisten_Import'!$B:$B,"Mustermann GmbH",'01_Saldenlisten_Import'!$F:$F,"Steuervb."),0) -> 0 | G20: =IFERROR(SUMIFS('01_Saldenlisten_Import'!$J:$J,'01_Saldenlisten_Import'!$A:$A,"2025-05",'01_Saldenlisten_Import'!$B:$B,"Mustermann GmbH",'01_Saldenlisten_Import'!$F:$F,"Steuervb."),0) -> 0 | H20: =IFERROR(SUMIFS('01_Saldenlisten_Import'!$J:$J,'01_Saldenlisten_Import'!$A:$A,"2025-06",'01_Saldenlisten_Import'!$B:$B,"Mustermann GmbH",'01_Saldenlisten_Import'!$F:$F,"Steuervb."),0) -> 0 | I20: =IFERROR(SUMIFS('01_Saldenlisten_Import'!$J:$J,'01_Saldenlisten_Import'!$A:$A,"2025-07",'01_Saldenlisten_Import'!$B:$B,"Mustermann GmbH",'01_Saldenlisten_Import'!$F:$F,"Steuervb."),0) -> 0 | J20: =IFERROR(SUMIFS('01_Saldenlisten_Import'!$J:$J,'01_Saldenlisten_Import'!$A:$A,"2025-08",'01_Saldenlisten_Import'!$B:$B,"Mustermann GmbH",'01_Saldenlisten_Import'!$F:$F,"Steuervb."),0) -> 0 | K20: =IFERROR(SUMIFS('01_Saldenlisten_Import'!$J:$J,'01_Saldenlisten_Import'!$A:$A,"2025-09",'01_Saldenlisten_Import'!$B:$B,"Mustermann GmbH",'01_Saldenlisten_Import'!$F:$F,"Steuervb."),0) -> 0 | L20: =IFERROR(SUM(C20:K20),0) -> 0
A21: P4 | B21: Darlehen & sonstige VB | C21: =IFERROR(SUMIFS('01_Saldenlisten_Import'!$J:$J,'01_Saldenlisten_Import'!$A:$A,"2025-01",'01_Saldenlisten_Import'!$B:$B,"Mustermann GmbH",'01_Saldenlisten_Import'!$F:$F,"Fremdkapital"),0) -> 18500 | D21: =IFERROR(SUMIFS('01_Saldenlisten_Import'!$J:$J,'01_Saldenlisten_Import'!$A:$A,"2025-02",'01_Saldenlisten_Import'!$B:$B,"Mustermann GmbH",'01_Saldenlisten_Import'!$F:$F,"Fremdkapital"),0) -> 19000 | E21: =IFERROR(SUMIFS('01_Saldenlisten_Import'!$J:$J,'01_Saldenlisten_Import'!$A:$A,"2025-03",'01_Saldenlisten_Import'!$B:$B,"Mustermann GmbH",'01_Saldenlisten_Import'!$F:$F,"Fremdkapital"),0) -> 20000 | F21: =IFERROR(SUMIFS('01_Saldenlisten_Import'!$J:$J,'01_Saldenlisten_Import'!$A:$A,"2025-04",'01_Saldenlisten_Import'!$B:$B,"Mustermann GmbH",'01_Saldenlisten_Import'!$F:$F,"Fremdkapital"),0) -> 19000 | G21: =IFERROR(SUMIFS('01_Saldenlisten_Import'!$J:$J,'01_Saldenlisten_Import'!$A:$A,"2025-05",'01_Saldenlisten_Import'!$B:$B,"Mustermann GmbH",'01_Saldenlisten_Import'!$F:$F,"Fremdkapital"),0) -> 20300 | H21: =IFERROR(SUMIFS('01_Saldenlisten_Import'!$J:$J,'01_Saldenlisten_Import'!$A:$A,"2025-06",'01_Saldenlisten_Import'!$B:$B,"Mustermann GmbH",'01_Saldenlisten_Import'!$F:$F,"Fremdkapital"),0) -> 21000 | I21: =IFERROR(SUMIFS('01_Saldenlisten_Import'!$J:$J,'01_Saldenlisten_Import'!$A:$A,"2025-07",'01_Saldenlisten_Import'!$B:$B,"Mustermann GmbH",'01_Saldenlisten_Import'!$F:$F,"Fremdkapital"),0) -> 20600 | J21: =IFERROR(SUMIFS('01_Saldenlisten_Import'!$J:$J,'01_Saldenlisten_Import'!$A:$A,"2025-08",'01_Saldenlisten_Import'!$B:$B,"Mustermann GmbH",'01_Saldenlisten_Import'!$F:$F,"Fremdkapital"),0) -> 21200 | K21: =IFERROR(SUMIFS('01_Saldenlisten_Import'!$J:$J,'01_Saldenlisten_Import'!$A:$A,"2025-09",'01_Saldenlisten_Import'!$B:$B,"Mustermann GmbH",'01_Saldenlisten_Import'!$F:$F,"Fremdkapital"),0) -> 21500 | L21: =IFERROR(SUM(C21:K21),0) -> 181100
B22: = B. VERBINDLICHKEITEN GESAMT | C22: =IFERROR(SUM(C19:C21),0) -> 37000 | D22: =IFERROR(SUM(D19:D21),0) -> 38000 | E22: =IFERROR(SUM(E19:E21),0) -> 40000 | F22: =IFERROR(SUM(F19:F21),0) -> 38000 | G22: =IFERROR(SUM(G19:G21),0) -> 40600 | H22: =IFERROR(SUM(H19:H21),0) -> 42000 | I22: =IFERROR(SUM(I19:I21),0) -> 41200 | J22: =IFERROR(SUM(J19:J21),0) -> 42400 | ... L22: =IFERROR(SUM(L19:L21),0) -> 362200
A23: P5 | B23: III. Rückstellungen | C23: =IFERROR(SUMIFS('01_Saldenlisten_Import'!$J:$J,'01_Saldenlisten_Import'!$A:$A,"2025-01",'01_Saldenlisten_Import'!$B:$B,"Mustermann GmbH",'01_Saldenlisten_Import'!$F:$F,"Rückstellungen"),0) -> 0 | D23: =IFERROR(SUMIFS('01_Saldenlisten_Import'!$J:$J,'01_Saldenlisten_Import'!$A:$A,"2025-02",'01_Saldenlisten_Import'!$B:$B,"Mustermann GmbH",'01_Saldenlisten_Import'!$F:$F,"Rückstellungen"),0) -> 0 | E23: =IFERROR(SUMIFS('01_Saldenlisten_Import'!$J:$J,'01_Saldenlisten_Import'!$A:$A,"2025-03",'01_Saldenlisten_Import'!$B:$B,"Mustermann GmbH",'01_Saldenlisten_Import'!$F:$F,"Rückstellungen"),0) -> 0 | F23: =IFERROR(SUMIFS('01_Saldenlisten_Import'!$J:$J,'01_Saldenlisten_Import'!$A:$A,"2025-04",'01_Saldenlisten_Import'!$B:$B,"Mustermann GmbH",'01_Saldenlisten_Import'!$F:$F,"Rückstellungen"),0) -> 0 | G23: =IFERROR(SUMIFS('01_Saldenlisten_Import'!$J:$J,'01_Saldenlisten_Import'!$A:$A,"2025-05",'01_Saldenlisten_Import'!$B:$B,"Mustermann GmbH",'01_Saldenlisten_Import'!$F:$F,"Rückstellungen"),0) -> 0 | H23: =IFERROR(SUMIFS('01_Saldenlisten_Import'!$J:$J,'01_Saldenlisten_Import'!$A:$A,"2025-06",'01_Saldenlisten_Import'!$B:$B,"Mustermann GmbH",'01_Saldenlisten_Import'!$F:$F,"Rückstellungen"),0) -> 0 | I23: =IFERROR(SUMIFS('01_Saldenlisten_Import'!$J:$J,'01_Saldenlisten_Import'!$A:$A,"2025-07",'01_Saldenlisten_Import'!$B:$B,"Mustermann GmbH",'01_Saldenlisten_Import'!$F:$F,"Rückstellungen"),0) -> 0 | J23: =IFERROR(SUMIFS('01_Saldenlisten_Import'!$J:$J,'01_Saldenlisten_Import'!$A:$A,"2025-08",'01_Saldenlisten_Import'!$B:$B,"Mustermann GmbH",'01_Saldenlisten_Import'!$F:$F,"Rückstellungen"),0) -> 0 | K23: =IFERROR(SUMIFS('01_Saldenlisten_Import'!$J:$J,'01_Saldenlisten_Import'!$A:$A,"2025-09",'01_Saldenlisten_Import'!$B:$B,"Mustermann GmbH",'01_Saldenlisten_Import'!$F:$F,"Rückstellungen"),0) -> 0 | L23: =IFERROR(SUM(C23:K23),0) -> 0
B24: = BILANZSUMME PASSIVA | C24: =IFERROR(C18+C22+C23,0) -> 37000 | D24: =IFERROR(D18+D22+D23,0) -> 38000 | E24: =IFERROR(E18+E22+E23,0) -> 40000 | F24: =IFERROR(F18+F22+F23,0) -> 38000 | G24: =IFERROR(G18+G22+G23,0) -> 40600 | H24: =IFERROR(H18+H22+H23,0) -> 42000 | I24: =IFERROR(I18+I22+I23,0) -> 41200 | J24: =IFERROR(J18+J22+J23,0) -> 42400 | ... L24: =IFERROR(L18+L22+L23,0) -> 362200
B25: Bilanzdifferenz (sollte = 0 sein) | C25: =IFERROR(C15-C24,0) -> 32000 | D25: =IFERROR(D15-D24,0) -> 33500 | E25: =IFERROR(E15-E24,0) -> 35000 | F25: =IFERROR(F15-F24,0) -> 33000 | G25: =IFERROR(G15-G24,0) -> 36400 | H25: =IFERROR(H15-H24,0) -> 37500 | I25: =IFERROR(I15-I24,0) -> 37300 | J25: =IFERROR(J15-J24,0) -> 39600 | ... L25: =IFERROR(L15-L24,0) -> 324800

Sheet Tabelle1

Sheet 01_Einstellungen
A1: ⚙ DATEV BWA Reporting Master — Einstellungen & Mandantensteuerung
A3: Steuerung des Berichtsmodus, Datenquellen und Mandantenselektion — alle Auswertungen greifen auf diese Parameter zurück.
A5: Parameter | B5: Wert | C5: Beschreibung | D5: Mögliche Werte | E5: Beispiel
A6: Datenquelle BWA | B6: DATEV_BWA.csv | C6: Pfad/Dateiname der importierten BWA-CSV | D6: *.csv, *.xlsx | E6: DATEV_BWA_2025.csv
A7: Datenquelle Mitarbeiter | B7: Mitarbeiter.csv | C7: Pfad/Dateiname der Personal-CSV | D7: *.csv | E7: mitarbeiter_2025.csv
A8: Mandantenmodus | B8: Kumuliert | C8: Welche Sicht wird im Report angezeigt | D8: Einzeln / Kumuliert / Final | E8: Kumuliert
A9: Aktiver Mandant | B9: Mustermann GmbH | C9: Wird im Einzelmodus als Fokus-Mandant angezeigt | D9: Mandantenname aus Tabelle | E9: Cheftresor Solutions GmbH
A10: Berichtsmonat | B10: Sep 2025 | C10: Monatsfokus für die Reportseite | D10: Mmm JJJJ | E10: Jun 2025
A11: Diagrammstil | B11: Executive | C11: Layoutvariante für Charts und Reports | D11: Executive / Compact / Kanzlei | E11: Executive
A12: KI-Kommentar | B12: Aktiv | C12: Automatische KI-Textauswertung ein/aus | D12: Aktiv / Inaktiv | E12: Aktiv
A13: Kostenstellenanalyse | B13: Aktiv | C13: Drill-down auf Teams und Kostenstellen | D13: Aktiv / Inaktiv | E13: Aktiv
A14: Mandanten kumulieren | B14: Ja | C14: Zusammenfassung aller aktiven Firmen | D14: Ja / Nein | E14: Ja
A15: Vorjahresvergleich | B15: Aktiv | C15: VJ-Spalten in Dashboard und Bericht einblenden | D15: Aktiv / Inaktiv | E15: Aktiv
A16: Ziel-EBIT-Marge % | B16: 18 | C16: Schwellwert für Ampel-Logik EBIT | D16: Zahl (Prozent) | E16: 20
A17: Ziel-Liquidität % | B17: 120 | C17: Mindestziel Liquidität 1. Grades | D17: Zahl | E17: 100
A20: MANDANTENSTEUERUNG
A21: Mandant | B21: Status | C21: Im Einzelbericht | D21: In Kumulierung | E21: Im Finalbericht | F21: Typ | G21: Bemerkung
A22: Mustermann GmbH | B22: ✓ Aktiv | C22: ✓ Ja | D22: ✓ Ja | E22: ✓ Ja | F22: GmbH | G22: Hauptmandant
A23: Beispiel Handel GmbH | B23: ✓ Aktiv | C23: ✓ Ja | D23: ✓ Ja | E23: ✓ Ja | F23: GmbH | G23: Handelsbereich
A24: Alpha Services UG | B24: ✓ Aktiv | C24: ✓ Ja | D24: ✓ Ja | E24: ✓ Ja | F24: UG | G24: Dienstleistung
A25: Beta Technik GmbH | B25: ✓ Aktiv | C25: – | D25: ✓ Ja | E25: – | F25: GmbH | G25: Nur intern
A26: Gamma Holding GmbH | B26: ✗ Inaktiv | C26: – | D26: – | E26: – | F26: GmbH | G26: Inaktiv / in Gründung
A28: Logik & Hinweise
A29: Einzelmodus → zeigt exakt den 'Aktiven Mandanten' aus den Parametern. | Kumuliert → fasst alle Firmen mit Kumulierung=Ja zusammen. | Finalbericht → verwendet Firmen mit Final=Ja. | Ampelfarben basieren auf Ziel-EBIT-Marge und Ziel-Liquidität aus Parametertabelle.
